{
    "2026-07-03 00:47:54": [
        {
            "index": 1,
            "title": "中国男篮对日本12人大名单公布",
            "hot": 12115754,
            "url": "https://www.douyin.com/search/%E4%B8%AD%E5%9B%BD%E7%94%B7%E7%AF%AE%E5%AF%B9%E6%97%A5%E6%9C%AC12%E4%BA%BA%E5%A4%A7%E5%90%8D%E5%8D%95%E5%85%AC%E5%B8%83",
            "img_url": "https://p26-sign.douyinpic.com/tos-cn-p-0015/oo0AyfnMagf9DQdQNZ4EAaBC8ARFQG8Lq5m16S~noop.jpeg?lk3s=bfd515bb&x-expires=1783029600&x-signature=%2BDA7tBpdgAVoESfS8Np%2F6szpiBc%3D&from=3218412987",
            "push_time": "2026-07-02 22:55:23",
            "now_time": "2026-07-03",
            "type": "热搜",
            "source": "抖音"
        },
        {
            "index": 2,
            "title": "爱的双手滋养出最灿烂的鲜花",
            "hot": 12102822,
            "url": "https://www.douyin.com/search/%E7%88%B1%E7%9A%84%E5%8F%8C%E6%89%8B%E6%BB%8B%E5%85%BB%E5%87%BA%E6%9C%80%E7%81%BF%E7%83%82%E7%9A%84%E9%B2%9C%E8%8A%B1",
            "img_url": "https://p3-sign.douyinpic.com/tos-cn-p-0015c000-ce/oUqInQWawAvBEvot9FfPiqDB00Re6EASwP3LDM~noop.jpeg?lk3s=bfd515bb&x-expires=1783029600&x-signature=zACAcOsxD1dJTeFijOeBaIXm%2B9Y%3D&from=3218412987",
            "push_time": "2026-07-02 17:46:13",
            "now_time": "2026-07-03",
            "type": "热搜",
            "source": "抖音"
        },
        {
            "index": 3,
            "title": "前5月我国农机出口超336亿元",
            "hot": 12096147,
            "url": "https://www.douyin.com/search/%E5%89%8D5%E6%9C%88%E6%88%91%E5%9B%BD%E5%86%9C%E6%9C%BA%E5%87%BA%E5%8F%A3%E8%B6%85336%E4%BA%BF%E5%85%83",
            "img_url": "https://p26-sign.douyinpic.com/tos-cn-p-0015/oMOlICB3aDAaKBOyLiFuA9qHxAggfBkRIpfwGE~noop.jpeg?lk3s=bfd515bb&x-expires=1783029600&x-signature=BjeDYzOJjHGi477380D%2B3X3U4Wg%3D&from=3218412987",
            "push_time": "2026-07-02 20:17:36",
            "now_time": "2026-07-03",
            "type": "热搜",
            "source": "抖音"
        },
        {
            "index": 4,
            "title": "时间胶囊写给未来的自己",
            "hot": 11641127,
            "url": "https://www.douyin.com/search/%E6%97%B6%E9%97%B4%E8%83%B6%E5%9B%8A%E5%86%99%E7%BB%99%E6%9C%AA%E6%9D%A5%E7%9A%84%E8%87%AA%E5%B7%B1",
            "img_url": "https://p26-sign.douyinpic.com/tos-cn-p-0015c000-ce/o8Ft28GVfRVeMOmP9Zf94vpIDIfLQDomTQAAXP~noop.jpeg?lk3s=bfd515bb&x-expires=1783029600&x-signature=%2BUsRJmybqXKVIYvF1SVy%2FpfOfWc%3D&from=3218412987",
            "push_time": "2026-07-02 16:58:37",
            "now_time": "2026-07-03",
            "type": "热搜",
            "source": "抖音"
        },
        {
            "index": 5,
            "title": "被光照亮的人成了光",
            "hot": 10995351,
            "url": "https://www.douyin.com/search/%E8%A2%AB%E5%85%89%E7%85%A7%E4%BA%AE%E7%9A%84%E4%BA%BA%E6%88%90%E4%BA%86%E5%85%89",
            "img_url": "https://p26-sign.douyinpic.com/tos-cn-p-0015/oA7dAIGieN1fdQdsCgCwLIRIIA31uxBY6wzAiB~noop.jpeg?lk3s=bfd515bb&x-expires=1783029600&x-signature=cMZZwUZFEFqUvXXibE5fN2yJreU%3D&from=3218412987",
            "push_time": "2026-07-02 17:25:54",
            "now_time": "2026-07-03",
            "type": "热搜",
            "source": "抖音"
        },
        {
            "index": 6,
            "title": "香港演员梁珊去世",
            "hot": 10902276,
            "url": "https://www.douyin.com/search/%E9%A6%99%E6%B8%AF%E6%BC%94%E5%91%98%E6%A2%81%E7%8F%8A%E5%8E%BB%E4%B8%96",
            "img_url": "https://p3-sign.douyinpic.com/tos-cn-p-0015/osu9igBIIEiKDmwAgCqAGDMBRQsFDUffgAtFp9~noop.jpeg?lk3s=bfd515bb&x-expires=1783029600&x-signature=RQq%2BkYO4hsERn0laJ2FqtVcif9Y%3D&from=3218412987",
            "push_time": "2026-07-02 14:53:40",
            "now_time": "2026-07-03",
            "type": "热搜",
            "source": "抖音"
        },
        {
            "index": 7,
            "title": "交换你相册里的蓝色瞬间",
            "hot": 9398754,
            "url": "https://www.douyin.com/search/%E4%BA%A4%E6%8D%A2%E4%BD%A0%E7%9B%B8%E5%86%8C%E9%87%8C%E7%9A%84%E8%93%9D%E8%89%B2%E7%9E%AC%E9%97%B4",
            "img_url": "https://p3-sign.douyinpic.com/tos-cn-p-0015/ogaasKFJnIgP0zIrkIuiQgOSBPLv51iEA6GAy~noop.jpeg?lk3s=bfd515bb&x-expires=1783029600&x-signature=Z9IT9%2FOFs435LiESsNk7%2BDEjPfg%3D&from=3218412987",
            "push_time": "2026-07-02 11:29:55",
            "now_time": "2026-07-03",
            "type": "热搜",
            "source": "抖音"
        },
        {
            "index": 8,
            "title": "潮流舞蹈这票到底投给谁",
            "hot": 9348776,
            "url": "https://www.douyin.com/search/%E6%BD%AE%E6%B5%81%E8%88%9E%E8%B9%88%E8%BF%99%E7%A5%A8%E5%88%B0%E5%BA%95%E6%8A%95%E7%BB%99%E8%B0%81",
            "img_url": "https://p11-sign.douyinpic.com/tos-cn-p-0015/owsL7YEIEAgqBUQfAdFCCtBsekRjXAAHDBn9Ax~noop.jpeg?lk3s=bfd515bb&x-expires=1783029600&x-signature=l%2BBfcwyhITTzCVMLrzx1QfQvhF4%3D&from=3218412987",
            "push_time": "2026-07-01 17:14:11",
            "now_time": "2026-07-03",
            "type": "热搜",
            "source": "抖音"
        },
        {
            "index": 9,
            "title": "殷墟还藏了多少老祖宗的秘密",
            "hot": 9273754,
            "url": "https://www.douyin.com/search/%E6%AE%B7%E5%A2%9F%E8%BF%98%E8%97%8F%E4%BA%86%E5%A4%9A%E5%B0%91%E8%80%81%E7%A5%96%E5%AE%97%E7%9A%84%E7%A7%98%E5%AF%86",
            "img_url": "https://p26-sign.douyinpic.com/tos-cn-p-0015/o8v03LIBIQhQAgiZ3Fep2opA7ej2UGEeBG08Cb~noop.jpeg?lk3s=bfd515bb&x-expires=1783029600&x-signature=8wa9Wu72SPpzk6SLBv6%2F065t5m0%3D&from=3218412987",
            "push_time": "2026-07-02 14:26:46",
            "now_time": "2026-07-03",
            "type": "热搜",
            "source": "抖音"
        },
        {
            "index": 10,
            "title": "原来每个省都有自己的省冰",
            "hot": 9148070,
            "url": "https://www.douyin.com/search/%E5%8E%9F%E6%9D%A5%E6%AF%8F%E4%B8%AA%E7%9C%81%E9%83%BD%E6%9C%89%E8%87%AA%E5%B7%B1%E7%9A%84%E7%9C%81%E5%86%B0",
            "img_url": "https://p26-sign.douyinpic.com/tos-cn-p-0015/oYmlzBPkItwdz4ANAVDQEIT8dkPdGqiG24Bia~noop.jpeg?lk3s=bfd515bb&x-expires=1783029600&x-signature=8xnHJcmOSJfr1lVITEA00HR6JYM%3D&from=3218412987",
            "push_time": "2026-07-02 11:19:07",
            "now_time": "2026-07-03",
            "type": "热搜",
            "source": "抖音"
        },
        {
            "index": 11,
            "title": "今年第9号台风巴威已生成",
            "hot": 8986616,
            "url": "https://www.douyin.com/search/%E4%BB%8A%E5%B9%B4%E7%AC%AC9%E5%8F%B7%E5%8F%B0%E9%A3%8E%E5%B7%B4%E5%A8%81%E5%B7%B2%E7%94%9F%E6%88%90",
            "img_url": "https://p26-sign.douyinpic.com/tos-cn-p-0015/owlMm8iIIAg1k0Ifj0iDFDJZzMhE3AAUBBueD4~noop.jpeg?lk3s=bfd515bb&x-expires=1783029600&x-signature=%2B1tWVQYRBxDnO9ln8%2FzmlAHb3i0%3D&from=3218412987",
            "push_time": "2026-07-02 16:32:37",
            "now_time": "2026-07-03",
            "type": "热搜",
            "source": "抖音"
        },
        {
            "index": 12,
            "title": "一篇长文讲述我父亲的一生",
            "hot": 8721398,
            "url": "https://www.douyin.com/search/%E4%B8%80%E7%AF%87%E9%95%BF%E6%96%87%E8%AE%B2%E8%BF%B0%E6%88%91%E7%88%B6%E4%BA%B2%E7%9A%84%E4%B8%80%E7%94%9F",
            "img_url": "https://p26-sign.douyinpic.com/tos-cn-i-0813/oM0VALfIe7I7LAfSA6AQt9FLgeCgC3HQEG0QAe~noop.jpeg?lk3s=bfd515bb&x-expires=1783029600&x-signature=Nx5bQY3GPJginbyS5Db4WVfJZq4%3D&from=3218412987",
            "push_time": "2026-07-02 15:56:20",
            "now_time": "2026-07-03",
            "type": "热搜",
            "source": "抖音"
        },
        {
            "index": 13,
            "title": "“深圳开放无人驾驶”系误读",
            "hot": 8702849,
            "url": "https://www.douyin.com/search/%E2%80%9C%E6%B7%B1%E5%9C%B3%E5%BC%80%E6%94%BE%E6%97%A0%E4%BA%BA%E9%A9%BE%E9%A9%B6%E2%80%9D%E7%B3%BB%E8%AF%AF%E8%AF%BB",
            "img_url": "https://p3-sign.douyinpic.com/tos-cn-i-dy/fb481ba4581d4f129f60b1611cb7f88c~noop.jpeg?lk3s=bfd515bb&x-expires=1783029600&x-signature=eM3FGiO3M2p4nLXKFSP%2FxoUnJrU%3D&from=3218412987",
            "push_time": "2026-07-02 19:51:53",
            "now_time": "2026-07-03",
            "type": "热搜",
            "source": "抖音"
        },
        {
            "index": 14,
            "title": "广东荔枝木烧鹅真的太正了",
            "hot": 8691983,
            "url": "https://www.douyin.com/search/%E5%B9%BF%E4%B8%9C%E8%8D%94%E6%9E%9D%E6%9C%A8%E7%83%A7%E9%B9%85%E7%9C%9F%E7%9A%84%E5%A4%AA%E6%AD%A3%E4%BA%86",
            "img_url": "https://p11-sign.douyinpic.com/tos-cn-p-0015/oAMJfABIdGBAuieO14kv0BCAgExGBZpIoxywi9~noop.jpeg?lk3s=bfd515bb&x-expires=1783029600&x-signature=PAqVRSrj6gawbJZ6FP9ciC13cmw%3D&from=3218412987",
            "push_time": "2026-07-02 16:56:58",
            "now_time": "2026-07-03",
            "type": "热搜",
            "source": "抖音"
        },
        {
            "index": 15,
            "title": "半导体开启年内第二轮涨价",
            "hot": 8579981,
            "url": "https://www.douyin.com/search/%E5%8D%8A%E5%AF%BC%E4%BD%93%E5%BC%80%E5%90%AF%E5%B9%B4%E5%86%85%E7%AC%AC%E4%BA%8C%E8%BD%AE%E6%B6%A8%E4%BB%B7",
            "img_url": "https://p3-sign.douyinpic.com/tos-cn-p-0015/o4iL8vAgQ1MAiazW3eCSqUcMVJfB7BHfQEzr8z~noop.jpeg?lk3s=bfd515bb&x-expires=1783029600&x-signature=iD36TUCuBV3FrOsWXgG7ljMoVso%3D&from=3218412987",
            "push_time": "2026-07-02 09:46:09",
            "now_time": "2026-07-03",
            "type": "热搜",
            "source": "抖音"
        },
        {
            "index": 16,
            "title": "茉莉奶白侵害LV商标权一审败诉",
            "hot": 8307450,
            "url": "https://www.douyin.com/search/%E8%8C%89%E8%8E%89%E5%A5%B6%E7%99%BD%E4%BE%B5%E5%AE%B3LV%E5%95%86%E6%A0%87%E6%9D%83%E4%B8%80%E5%AE%A1%E8%B4%A5%E8%AF%89",
            "img_url": "https://p3-sign.douyinpic.com/tos-cn-p-0015/okGDwIiOMwDY4QBAiQJksEa4FA9CYI1vpIPH3~noop.jpeg?lk3s=bfd515bb&x-expires=1783029600&x-signature=rMvQinmc0k0T3qMG%2BF3OaD%2BdqYU%3D&from=3218412987",
            "push_time": "2026-07-02 15:51:45",
            "now_time": "2026-07-03",
            "type": "热搜",
            "source": "抖音"
        },
        {
            "index": 17,
            "title": "佛得角总统称能1:0击败阿根廷",
            "hot": 8189518,
            "url": "https://www.douyin.com/search/%E4%BD%9B%E5%BE%97%E8%A7%92%E6%80%BB%E7%BB%9F%E7%A7%B0%E8%83%BD1%3A0%E5%87%BB%E8%B4%A5%E9%98%BF%E6%A0%B9%E5%BB%B7",
            "img_url": "https://p3-sign.douyinpic.com/tos-cn-p-0015/oAeGh8yElZ9LFIWIJBFqADFDg4CQwAAKfgRAL1~noop.jpeg?lk3s=bfd515bb&x-expires=1783029600&x-signature=TILHQrwnSF5RAiZXlUO4slWJiRk%3D&from=3218412987",
            "push_time": "2026-07-02 15:17:38",
            "now_time": "2026-07-03",
            "type": "热搜",
            "source": "抖音"
        },
        {
            "index": 18,
            "title": "逆战未来S3无主之地赛季上线",
            "hot": 7849575,
            "url": "https://www.douyin.com/search/%E9%80%86%E6%88%98%E6%9C%AA%E6%9D%A5S3%E6%97%A0%E4%B8%BB%E4%B9%8B%E5%9C%B0%E8%B5%9B%E5%AD%A3%E4%B8%8A%E7%BA%BF",
            "img_url": "https://p11-sign.douyinpic.com/tos-cn-p-0015/osfVFPJAAFBEJNgfkWDRCqIERIDOHB9xQFlAFP~noop.jpeg?lk3s=bfd515bb&x-expires=1783029600&x-signature=AKh%2BCyolAYx9O3abCDvhtUzdi7A%3D&from=3218412987",
            "push_time": "2026-07-02 13:50:50",
            "now_time": "2026-07-03",
            "type": "热搜",
            "source": "抖音"
        },
        {
            "index": 19,
            "title": "葡萄牙vs克罗地亚",
            "hot": 7843015,
            "url": "https://www.douyin.com/search/%E8%91%A1%E8%90%84%E7%89%99vs%E5%85%8B%E7%BD%97%E5%9C%B0%E4%BA%9A",
            "img_url": "https://p26-sign.douyinpic.com/tos-cn-p-0015/osAkmZIgNcAimiwAJoe6yIfC1CBkABvIhDZ1sG~noop.jpeg?lk3s=bfd515bb&x-expires=1783029600&x-signature=c5bDR8eE3kQHY4j5qJoDJjRVXCQ%3D&from=3218412987",
            "push_time": "2026-07-02 18:38:10",
            "now_time": "2026-07-03",
            "type": "热搜",
            "source": "抖音"
        },
        {
            "index": 20,
            "title": "学姐我注册抖音号了",
            "hot": 7814804,
            "url": "https://www.douyin.com/search/%E5%AD%A6%E5%A7%90%E6%88%91%E6%B3%A8%E5%86%8C%E6%8A%96%E9%9F%B3%E5%8F%B7%E4%BA%86",
            "img_url": "https://p3-sign.douyinpic.com/tos-cn-p-0015c000-ce/ocQA5BE7SED49cwPhrxfFsDEfunAZqIAuIEQsA~noop.jpeg?lk3s=bfd515bb&x-expires=1783029600&x-signature=zLdn92xVntuZAmag0qGHzIgJlW8%3D&from=3218412987",
            "push_time": "2026-07-02 14:41:45",
            "now_time": "2026-07-03",
            "type": "热搜",
            "source": "抖音"
        },
        {
            "index": 21,
            "title": "永劫无间手游二周年开启",
            "hot": 7806680,
            "url": "https://www.douyin.com/search/%E6%B0%B8%E5%8A%AB%E6%97%A0%E9%97%B4%E6%89%8B%E6%B8%B8%E4%BA%8C%E5%91%A8%E5%B9%B4%E5%BC%80%E5%90%AF",
            "img_url": "https://p3-sign.douyinpic.com/tos-cn-p-0015c000-ce/ogfiDfg5BEhOIIcfdBUgFDZEEN7NAHOWNJoVZI~noop.jpeg?lk3s=bfd515bb&x-expires=1783029600&x-signature=ZcxFhEXRSKQfvwcHxoTuF1RpnJM%3D&from=3218412987",
            "push_time": "2026-07-02 13:51:51",
            "now_time": "2026-07-03",
            "type": "热搜",
            "source": "抖音"
        },
        {
            "index": 22,
            "title": "动画电影去你的岛定档",
            "hot": 7803585,
            "url": "https://www.douyin.com/search/%E5%8A%A8%E7%94%BB%E7%94%B5%E5%BD%B1%E5%8E%BB%E4%BD%A0%E7%9A%84%E5%B2%9B%E5%AE%9A%E6%A1%A3",
            "img_url": "https://p5-ex-gddgtc-sign.douyinpic.com/tos-cn-p-0015/oo1EBjJNILAbBiBAI7tGa5ML4fxFxfUFIB8eCr~noop.jpeg?lk3s=bfd515bb&x-expires=1783029600&x-signature=C%2Bp%2BU6UfYCzLvxajV8mQfNV%2FtB4%3D&from=3218412987",
            "push_time": "2026-07-02 11:02:37",
            "now_time": "2026-07-03",
            "type": "热搜",
            "source": "抖音"
        },
        {
            "index": 23,
            "title": "杰伦布朗保罗乔治互换东家",
            "hot": 7782109,
            "url": "https://www.douyin.com/search/%E6%9D%B0%E4%BC%A6%E5%B8%83%E6%9C%97%E4%BF%9D%E7%BD%97%E4%B9%94%E6%B2%BB%E4%BA%92%E6%8D%A2%E4%B8%9C%E5%AE%B6",
            "img_url": "https://p5-ex-gddgtc-sign.douyinpic.com/tos-cn-p-0015/ogQbQGOfFMA8m1fH3zWPB7UGBBaAfCPiQu8gFQ~noop.jpeg?lk3s=bfd515bb&x-expires=1783029600&x-signature=NxwllU83cbQ61rh0bh97UVzfhhY%3D&from=3218412987",
            "push_time": "2026-07-02 07:12:53",
            "now_time": "2026-07-03",
            "type": "热搜",
            "source": "抖音"
        },
        {
            "index": 24,
            "title": "千香黎非摇鞠婧祎本尊驾到",
            "hot": 7770260,
            "url": "https://www.douyin.com/search/%E5%8D%83%E9%A6%99%E9%BB%8E%E9%9D%9E%E6%91%87%E9%9E%A0%E5%A9%A7%E7%A5%8E%E6%9C%AC%E5%B0%8A%E9%A9%BE%E5%88%B0",
            "img_url": "https://p26-sign.douyinpic.com/tos-cn-p-0015c000-ce/oogZHIMeUJUBz89ZAGDfiE3jLDwIQQe7bBxiMA~noop.jpeg?lk3s=bfd515bb&x-expires=1783029600&x-signature=7EUJHlXo9Xur0y88bynczfrvdww%3D&from=3218412987",
            "push_time": "2026-07-02 21:47:38",
            "now_time": "2026-07-03",
            "type": "热搜",
            "source": "抖音"
        },
        {
            "index": 25,
            "title": "我已加入松弛派对",
            "hot": 7764646,
            "url": "https://www.douyin.com/search/%E6%88%91%E5%B7%B2%E5%8A%A0%E5%85%A5%E6%9D%BE%E5%BC%9B%E6%B4%BE%E5%AF%B9",
            "img_url": "https://p26-sign.douyinpic.com/tos-cn-i-0813/owtvFABquNAAAiI1BIiPACgtr3GAe6EgeAB4A8~noop.jpeg?lk3s=bfd515bb&x-expires=1783029600&x-signature=n5OLJ4znWdzo8OdwbwvnpW8fXgk%3D&from=3218412987",
            "push_time": "2026-07-02 21:04:55",
            "now_time": "2026-07-03",
            "type": "热搜",
            "source": "抖音"
        },
        {
            "index": 26,
            "title": "天黑不睡觉天亮还在熬",
            "hot": 7763076,
            "url": "https://www.douyin.com/search/%E5%A4%A9%E9%BB%91%E4%B8%8D%E7%9D%A1%E8%A7%89%E5%A4%A9%E4%BA%AE%E8%BF%98%E5%9C%A8%E7%86%AC",
            "img_url": "https://p11-sign.douyinpic.com/tos-cn-i-0813c000-ce/oQrqJ3AqEihgVMAEkh1AEBNEIInMexAfwAPiBe~noop.jpeg?lk3s=bfd515bb&x-expires=1783029600&x-signature=JjAQ6iVDZ2JB8Q7ihuaYiCGdxv8%3D&from=3218412987",
            "push_time": "2026-07-02 16:30:51",
            "now_time": "2026-07-03",
            "type": "热搜",
            "source": "抖音"
        },
        {
            "index": 27,
            "title": "徐良伴舞小哥终于更新了",
            "hot": 7744854,
            "url": "https://www.douyin.com/search/%E5%BE%90%E8%89%AF%E4%BC%B4%E8%88%9E%E5%B0%8F%E5%93%A5%E7%BB%88%E4%BA%8E%E6%9B%B4%E6%96%B0%E4%BA%86",
            "img_url": "https://p26-sign.douyinpic.com/tos-cn-p-0015/ogAtBBuUaENCE7ZQTuLfCF6iaD0ekfI2hkQv5A~noop.jpeg?lk3s=bfd515bb&x-expires=1783029600&x-signature=orNlUJKzLn7jXLLVXDqxa%2BcaIeI%3D&from=3218412987",
            "push_time": "2026-07-02 15:36:30",
            "now_time": "2026-07-03",
            "type": "热搜",
            "source": "抖音"
        },
        {
            "index": 28,
            "title": "哈兰德破纪录后发了5条抖音",
            "hot": 7729138,
            "url": "https://www.douyin.com/search/%E5%93%88%E5%85%B0%E5%BE%B7%E7%A0%B4%E7%BA%AA%E5%BD%95%E5%90%8E%E5%8F%91%E4%BA%865%E6%9D%A1%E6%8A%96%E9%9F%B3",
            "img_url": "https://p26-sign.douyinpic.com/tos-cn-i-0813c000-ce/osHAAiKBwOACQeOiPA1eEAAyEdEzmIIGgYDBFo~noop.jpeg?lk3s=bfd515bb&x-expires=1783029600&x-signature=6RIgafbbf%2FNFNGqkDiaHFGlFddI%3D&from=3218412987",
            "push_time": "2026-07-02 21:16:33",
            "now_time": "2026-07-03",
            "type": "热搜",
            "source": "抖音"
        },
        {
            "index": 29,
            "title": "当你觉得身边的人没品味时",
            "hot": 7726426,
            "url": "https://www.douyin.com/search/%E5%BD%93%E4%BD%A0%E8%A7%89%E5%BE%97%E8%BA%AB%E8%BE%B9%E7%9A%84%E4%BA%BA%E6%B2%A1%E5%93%81%E5%91%B3%E6%97%B6",
            "img_url": "https://p3-sign.douyinpic.com/tos-cn-p-0015/oEevQUD9HAOMzxDmAVgFdPJqQfkXqCEBwGgh5A~noop.jpeg?lk3s=bfd515bb&x-expires=1783029600&x-signature=%2BdPtr108CGbI26TJU5UcKn9h9I8%3D&from=3218412987",
            "push_time": "2026-07-02 21:43:55",
            "now_time": "2026-07-03",
            "type": "热搜",
            "source": "抖音"
        },
        {
            "index": 30,
            "title": "野狗骨头定档",
            "hot": 7717490,
            "url": "https://www.douyin.com/search/%E9%87%8E%E7%8B%97%E9%AA%A8%E5%A4%B4%E5%AE%9A%E6%A1%A3",
            "img_url": "https://p11-sign.douyinpic.com/tos-cn-i-dy/2bd0b5e090454e7d8c6e9cd6d0a3ccfe~noop.jpeg?lk3s=bfd515bb&x-expires=1783029600&x-signature=PhDwtLz4fc48SDbYP31whHSJSuc%3D&from=3218412987",
            "push_time": "2026-07-02 20:57:00",
            "now_time": "2026-07-03",
            "type": "热搜",
            "source": "抖音"
        },
        {
            "index": 31,
            "title": "被百厨大战安利了煎蟹",
            "hot": 7716828,
            "url": "https://www.douyin.com/search/%E8%A2%AB%E7%99%BE%E5%8E%A8%E5%A4%A7%E6%88%98%E5%AE%89%E5%88%A9%E4%BA%86%E7%85%8E%E8%9F%B9",
            "img_url": "https://p3-sign.douyinpic.com/tos-cn-p-0015c000-ce/oMtOBiB2ZEMkxpwKtIvApzbCskrwEAWiPiaTH~noop.jpeg?lk3s=bfd515bb&x-expires=1783029600&x-signature=aROGIFlIMnCwWglXuDu7JEkbydU%3D&from=3218412987",
            "push_time": "2026-07-02 16:49:39",
            "now_time": "2026-07-03",
            "type": "热搜",
            "source": "抖音"
        },
        {
            "index": 32,
            "title": "异环真红",
            "hot": 7714084,
            "url": "https://www.douyin.com/search/%E5%BC%82%E7%8E%AF%E7%9C%9F%E7%BA%A2",
            "img_url": "https://p3-sign.douyinpic.com/tos-cn-p-0015/os3EAgfDDQyP9AqAlwfESRVOJBZAdEDgFC6CQg~noop.jpeg?lk3s=bfd515bb&x-expires=1783029600&x-signature=ISewf4%2FKZXansugL6DuRQsbf%2Fs4%3D&from=3218412987",
            "push_time": "2026-07-02 11:07:45",
            "now_time": "2026-07-03",
            "type": "热搜",
            "source": "抖音"
        },
        {
            "index": 33,
            "title": "王楚钦孙颖莎逆转进四强",
            "hot": 7711879,
            "url": "https://www.douyin.com/search/%E7%8E%8B%E6%A5%9A%E9%92%A6%E5%AD%99%E9%A2%96%E8%8E%8E%E9%80%86%E8%BD%AC%E8%BF%9B%E5%9B%9B%E5%BC%BA",
            "img_url": "https://p3-sign.douyinpic.com/tos-cn-p-0015/oMdqNapbPAVoF9NfgQFMRNCDufVIPQZEAABiLQ~noop.jpeg?lk3s=bfd515bb&x-expires=1783029600&x-signature=yEX9Fryy4f3%2B4yKdSYygB2HpOZg%3D&from=3218412987",
            "push_time": "2026-07-02 07:05:54",
            "now_time": "2026-07-03",
            "type": "热搜",
            "source": "抖音"
        },
        {
            "index": 34,
            "title": "在喜欢你6里看到社交入侵",
            "hot": 7709993,
            "url": "https://www.douyin.com/search/%E5%9C%A8%E5%96%9C%E6%AC%A2%E4%BD%A06%E9%87%8C%E7%9C%8B%E5%88%B0%E7%A4%BE%E4%BA%A4%E5%85%A5%E4%BE%B5",
            "img_url": "https://p26-sign.douyinpic.com/tos-cn-p-0015/ocgEMsgQEZDAQDZFlfBhCqrdvPxA9ACmIas3fX~noop.jpeg?lk3s=bfd515bb&x-expires=1783029600&x-signature=6uVDzm3BVavkgDnS6SV8OdSxXfU%3D&from=3218412987",
            "push_time": "2026-07-02 07:01:01",
            "now_time": "2026-07-03",
            "type": "热搜",
            "source": "抖音"
        },
        {
            "index": 35,
            "title": "在毕业致辞中感受语言的力量",
            "hot": 7703878,
            "url": "https://www.douyin.com/search/%E5%9C%A8%E6%AF%95%E4%B8%9A%E8%87%B4%E8%BE%9E%E4%B8%AD%E6%84%9F%E5%8F%97%E8%AF%AD%E8%A8%80%E7%9A%84%E5%8A%9B%E9%87%8F",
            "img_url": "https://p26-sign.douyinpic.com/tos-cn-i-0813c000-ce/oQBiyWbcEF7AoXICkGmBfE5ezkAiAAywAcB1IU~noop.jpeg?lk3s=bfd515bb&x-expires=1783029600&x-signature=nAL9T0S9lqLBPgrXv%2B%2BSMvwVirU%3D&from=3218412987",
            "push_time": "2026-07-02 20:52:47",
            "now_time": "2026-07-03",
            "type": "热搜",
            "source": "抖音"
        },
        {
            "index": 36,
            "title": "V8和CORTIS一起鬼步舞",
            "hot": 7703153,
            "url": "https://www.douyin.com/search/V8%E5%92%8CCORTIS%E4%B8%80%E8%B5%B7%E9%AC%BC%E6%AD%A5%E8%88%9E",
            "img_url": "https://p11-sign.douyinpic.com/tos-cn-p-0015/oggLTElaqAxfpN8xADBAyRuRFDMINQf9qAZhMY~noop.jpeg?lk3s=bfd515bb&x-expires=1783029600&x-signature=Hx8lJQJi9keGCjPQybh8%2FIbRMEs%3D&from=3218412987",
            "push_time": "2026-07-02 20:32:16",
            "now_time": "2026-07-03",
            "type": "热搜",
            "source": "抖音"
        },
        {
            "index": 37,
            "title": "迷核手势舞",
            "hot": 7699122,
            "url": "https://www.douyin.com/search/%E8%BF%B7%E6%A0%B8%E6%89%8B%E5%8A%BF%E8%88%9E",
            "img_url": "https://p5-ex-gddgtc-sign.douyinpic.com/tos-cn-p-0015c000-ce/oQJAdNiIcEByEzAAc7DwfEiX1AImeEqEe2jEjC~noop.jpeg?lk3s=bfd515bb&x-expires=1783029600&x-signature=O0ltYPrhWbm3gv9kN1lqwvM82WY%3D&from=3218412987",
            "push_time": "2026-07-01 23:16:17",
            "now_time": "2026-07-03",
            "type": "热搜",
            "source": "抖音"
        },
        {
            "index": 38,
            "title": "我是姆巴佩中国分佩",
            "hot": 7697169,
            "url": "https://www.douyin.com/search/%E6%88%91%E6%98%AF%E5%A7%86%E5%B7%B4%E4%BD%A9%E4%B8%AD%E5%9B%BD%E5%88%86%E4%BD%A9",
            "img_url": "https://p3-sign.douyinpic.com/tos-cn-p-0015c000-ce/oIpDedWN1EeuAvExrCIizNdiIdBE9QAUswfdvv~noop.jpeg?lk3s=bfd515bb&x-expires=1783029600&x-signature=0U6zhzsdO%2BmyQU7XzDE4AHgYcHU%3D&from=3218412987",
            "push_time": "2026-07-01 14:36:08",
            "now_time": "2026-07-03",
            "type": "热搜",
            "source": "抖音"
        },
        {
            "index": 39,
            "title": "你说我变了反差转场",
            "hot": 7697161,
            "url": "https://www.douyin.com/search/%E4%BD%A0%E8%AF%B4%E6%88%91%E5%8F%98%E4%BA%86%E5%8F%8D%E5%B7%AE%E8%BD%AC%E5%9C%BA",
            "img_url": "https://p26-sign.douyinpic.com/tos-cn-p-0015c000-ce/o0U88XHjPCuI4AL7vJ1Qv6eCMhBtgNeiiLgGIe~noop.jpeg?lk3s=bfd515bb&x-expires=1783029600&x-signature=TRY%2FvqJOYb2knWaEcPs6GgKlQg0%3D&from=3218412987",
            "push_time": "2026-07-01 14:32:01",
            "now_time": "2026-07-03",
            "type": "热搜",
            "source": "抖音"
        },
        {
            "index": 40,
            "title": "花式上马就看清明上河园",
            "hot": 7695764,
            "url": "https://www.douyin.com/search/%E8%8A%B1%E5%BC%8F%E4%B8%8A%E9%A9%AC%E5%B0%B1%E7%9C%8B%E6%B8%85%E6%98%8E%E4%B8%8A%E6%B2%B3%E5%9B%AD",
            "img_url": "https://p3-sign.douyinpic.com/tos-cn-p-0015c000-ce/ogVpEnED88fEW7mGyqcFAfvIqKF0i9ARMYBDpw~noop.jpeg?lk3s=bfd515bb&x-expires=1783029600&x-signature=KD2WdOusB5zn%2BVjAXnv6LVoeJ8c%3D&from=3218412987",
            "push_time": "2026-07-02 16:04:18",
            "now_time": "2026-07-03",
            "type": "热搜",
            "source": "抖音"
        },
        {
            "index": 41,
            "title": "当我看到比利时绝境逆转",
            "hot": 7695745,
            "url": "https://www.douyin.com/search/%E5%BD%93%E6%88%91%E7%9C%8B%E5%88%B0%E6%AF%94%E5%88%A9%E6%97%B6%E7%BB%9D%E5%A2%83%E9%80%86%E8%BD%AC",
            "img_url": "https://p3-sign.douyinpic.com/tos-cn-p-0015/o8BJAQjRuFCpZAaNQqEDxKfGQ76fgBb3ANLIc9~noop.jpeg?lk3s=bfd515bb&x-expires=1783029600&x-signature=7L73A4l35TO3L9NLJ%2BdZv7vQk7s%3D&from=3218412987",
            "push_time": "2026-07-02 08:55:27",
            "now_time": "2026-07-03",
            "type": "热搜",
            "source": "抖音"
        },
        {
            "index": 42,
            "title": "杀死比尔血色全传定档8月7日",
            "hot": 7687621,
            "url": "https://www.douyin.com/search/%E6%9D%80%E6%AD%BB%E6%AF%94%E5%B0%94%E8%A1%80%E8%89%B2%E5%85%A8%E4%BC%A0%E5%AE%9A%E6%A1%A38%E6%9C%887%E6%97%A5",
            "img_url": "https://p26-sign.douyinpic.com/tos-cn-p-0015/o49BoFAfEjdfqlRSEqi0AWNJdzQAQhxzDMlIEg~noop.jpeg?lk3s=bfd515bb&x-expires=1783029600&x-signature=34X4e1jV7kTiKlw4MmvRm5%2BkW2Q%3D&from=3218412987",
            "push_time": "2026-07-02 11:28:53",
            "now_time": "2026-07-03",
            "type": "热搜",
            "source": "抖音"
        },
        {
            "index": 43,
            "title": "晒出我的面试穿搭",
            "hot": 7683573,
            "url": "https://www.douyin.com/search/%E6%99%92%E5%87%BA%E6%88%91%E7%9A%84%E9%9D%A2%E8%AF%95%E7%A9%BF%E6%90%AD",
            "img_url": "https://p26-sign.douyinpic.com/tos-cn-p-0015c000-ce/oUeN6NMJTUq0QgIaPD5LeBfGCQaETQ7NxK8ADJ~noop.jpeg?lk3s=bfd515bb&x-expires=1783029600&x-signature=9JuKNTne2xbhKT0dIuk3DzMT8s0%3D&from=3218412987",
            "push_time": "2026-07-01 10:55:00",
            "now_time": "2026-07-03",
            "type": "热搜",
            "source": "抖音"
        },
        {
            "index": 44,
            "title": "用早茶晚酒支持你的主队",
            "hot": 7677366,
            "url": "https://www.douyin.com/search/%E7%94%A8%E6%97%A9%E8%8C%B6%E6%99%9A%E9%85%92%E6%94%AF%E6%8C%81%E4%BD%A0%E7%9A%84%E4%B8%BB%E9%98%9F",
            "img_url": "https://p26-sign.douyinpic.com/tos-cn-p-0015/o4fbIiVNPBAFYhwQIQxx64AaK0KgyqEFDA9eEZ~noop.jpeg?lk3s=bfd515bb&x-expires=1783029600&x-signature=ykasfw6lICTpNmTCgYrdgI%2FP%2FP0%3D&from=3218412987",
            "push_time": "2026-07-02 14:54:56",
            "now_time": "2026-07-03",
            "type": "热搜",
            "source": "抖音"
        },
        {
            "index": 45,
            "title": "吃桃子也有南北差异吗",
            "hot": 7673348,
            "url": "https://www.douyin.com/search/%E5%90%83%E6%A1%83%E5%AD%90%E4%B9%9F%E6%9C%89%E5%8D%97%E5%8C%97%E5%B7%AE%E5%BC%82%E5%90%97",
            "img_url": "https://p26-sign.douyinpic.com/tos-cn-p-0015c000-ce/okBa3dBPNY4OdvUE1CiiJgDaHEIyPCkABAMpu~noop.jpeg?lk3s=bfd515bb&x-expires=1783029600&x-signature=tmjLZ7zxvteZpwLMJ%2FF9QnKt41s%3D&from=3218412987",
            "push_time": "2026-07-01 17:08:52",
            "now_time": "2026-07-03",
            "type": "热搜",
            "source": "抖音"
        },
        {
            "index": 46,
            "title": "下半年也要去看更美的风景",
            "hot": 7670812,
            "url": "https://www.douyin.com/search/%E4%B8%8B%E5%8D%8A%E5%B9%B4%E4%B9%9F%E8%A6%81%E5%8E%BB%E7%9C%8B%E6%9B%B4%E7%BE%8E%E7%9A%84%E9%A3%8E%E6%99%AF",
            "img_url": "https://p3-sign.douyinpic.com/tos-cn-p-0015/oIA6EMPFI7PBIAXklvQa0Id0ikDM9ii9NwzQV~noop.jpeg?lk3s=bfd515bb&x-expires=1783029600&x-signature=2WM5qscIQNdd6YwCYWDJJ0lfTC8%3D&from=3218412987",
            "push_time": "2026-07-01 15:31:10",
            "now_time": "2026-07-03",
            "type": "热搜",
            "source": "抖音"
        },
        {
            "index": 47,
            "title": "地瓜炉变身全能烧烤炉",
            "hot": 7669619,
            "url": "https://www.douyin.com/search/%E5%9C%B0%E7%93%9C%E7%82%89%E5%8F%98%E8%BA%AB%E5%85%A8%E8%83%BD%E7%83%A7%E7%83%A4%E7%82%89",
            "img_url": "https://p11-sign.douyinpic.com/tos-cn-p-0015c000-ce/oUFjVeJqQA7CEZVFEoo859yCevDfQIhmAOcwID~noop.jpeg?lk3s=bfd515bb&x-expires=1783029600&x-signature=I30jNVsw9eHt0ZQMkNENlNmE6Ao%3D&from=3218412987",
            "push_time": "2026-07-01 09:36:29",
            "now_time": "2026-07-03",
            "type": "热搜",
            "source": "抖音"
        },
        {
            "index": 48,
            "title": "唇印四宫格美得太犯规",
            "hot": 7664878,
            "url": "https://www.douyin.com/search/%E5%94%87%E5%8D%B0%E5%9B%9B%E5%AE%AB%E6%A0%BC%E7%BE%8E%E5%BE%97%E5%A4%AA%E7%8A%AF%E8%A7%84",
            "img_url": "https://p26-sign.douyinpic.com/tos-cn-p-0015c000-ce/oseUDHlXEhZF4a3AxgeIhAkA7xVIDJC0BfXQJQ~noop.jpeg?lk3s=bfd515bb&x-expires=1783029600&x-signature=EdjhrtVHDkSRcSVgv5jWfBsH3FA%3D&from=3218412987",
            "push_time": "2026-07-02 12:52:29",
            "now_time": "2026-07-03",
            "type": "热搜",
            "source": "抖音"
        },
        {
            "index": 49,
            "title": "妙脆角给小猫种好了不用谢",
            "hot": 7653295,
            "url": "https://www.douyin.com/search/%E5%A6%99%E8%84%86%E8%A7%92%E7%BB%99%E5%B0%8F%E7%8C%AB%E7%A7%8D%E5%A5%BD%E4%BA%86%E4%B8%8D%E7%94%A8%E8%B0%A2",
            "img_url": "https://p11-sign.douyinpic.com/tos-cn-p-0015c000-ce/owFAqfSFSwr9DtoQCSmEAXBnIERFIkw0qxBSfp~noop.jpeg?lk3s=bfd515bb&x-expires=1783029600&x-signature=xcVEq8WKB4Z8WEReSTPefcf4lBA%3D&from=3218412987",
            "push_time": "2026-07-02 14:19:11",
            "now_time": "2026-07-03",
            "type": "热搜",
            "source": "抖音"
        },
        {
            "index": 50,
            "title": "宋威龙张婧仪头碰头上甜度了",
            "hot": 7651340,
            "url": "https://www.douyin.com/search/%E5%AE%8B%E5%A8%81%E9%BE%99%E5%BC%A0%E5%A9%A7%E4%BB%AA%E5%A4%B4%E7%A2%B0%E5%A4%B4%E4%B8%8A%E7%94%9C%E5%BA%A6%E4%BA%86",
            "img_url": "https://p5-ex-gddgtc-sign.douyinpic.com/tos-cn-p-0015c000-ce/oYMAAVIaSFPhkEiG6Ru1UPmdxCin2BCYZ3X4b~noop.jpeg?lk3s=bfd515bb&x-expires=1783029600&x-signature=t41uw8T7uFw7HCdZmP1dQRWyQ%2F4%3D&from=3218412987",
            "push_time": "2026-07-02 20:26:48",
            "now_time": "2026-07-03",
            "type": "热搜",
            "source": "抖音"
        }
    ],
    "2026-07-03 01:46:43": [
        {
            "index": 1,
            "title": "中国男篮对日本12人大名单公布",
            "hot": 12105228,
            "url": "https://www.douyin.com/search/%E4%B8%AD%E5%9B%BD%E7%94%B7%E7%AF%AE%E5%AF%B9%E6%97%A5%E6%9C%AC12%E4%BA%BA%E5%A4%A7%E5%90%8D%E5%8D%95%E5%85%AC%E5%B8%83",
            "img_url": "https://p11-sign.douyinpic.com/tos-cn-p-0015/oo0AyfnMagf9DQdQNZ4EAaBC8ARFQG8Lq5m16S~noop.jpeg?lk3s=bfd515bb&x-expires=1783033200&x-signature=2B84nzQ3syaV5gtH7WxLvkwsFJI%3D&from=3218412987",
            "push_time": "2026-07-02 22:55:23",
            "now_time": "2026-07-03",
            "type": "热搜",
            "source": "抖音"
        },
        {
            "index": 2,
            "title": "爱的双手滋养出最灿烂的鲜花",
            "hot": 12103153,
            "url": "https://www.douyin.com/search/%E7%88%B1%E7%9A%84%E5%8F%8C%E6%89%8B%E6%BB%8B%E5%85%BB%E5%87%BA%E6%9C%80%E7%81%BF%E7%83%82%E7%9A%84%E9%B2%9C%E8%8A%B1",
            "img_url": "https://p26-sign.douyinpic.com/tos-cn-p-0015c000-ce/oUqInQWawAvBEvot9FfPiqDB00Re6EASwP3LDM~noop.jpeg?lk3s=bfd515bb&x-expires=1783033200&x-signature=CouH3jVBPaj5J5TwdU10vT77trg%3D&from=3218412987",
            "push_time": "2026-07-02 17:46:13",
            "now_time": "2026-07-03",
            "type": "热搜",
            "source": "抖音"
        },
        {
            "index": 3,
            "title": "前5月我国农机出口超336亿元",
            "hot": 12100102,
            "url": "https://www.douyin.com/search/%E5%89%8D5%E6%9C%88%E6%88%91%E5%9B%BD%E5%86%9C%E6%9C%BA%E5%87%BA%E5%8F%A3%E8%B6%85336%E4%BA%BF%E5%85%83",
            "img_url": "https://p5-ex-gddgtc-sign.douyinpic.com/tos-cn-p-0015/oMOlICB3aDAaKBOyLiFuA9qHxAggfBkRIpfwGE~noop.jpeg?lk3s=bfd515bb&x-expires=1783033200&x-signature=m2uQniTrKbVMdMwuwKPG7ClZsVI%3D&from=3218412987",
            "push_time": "2026-07-02 20:17:36",
            "now_time": "2026-07-03",
            "type": "热搜",
            "source": "抖音"
        },
        {
            "index": 4,
            "title": "时间胶囊写给未来的自己",
            "hot": 11518575,
            "url": "https://www.douyin.com/search/%E6%97%B6%E9%97%B4%E8%83%B6%E5%9B%8A%E5%86%99%E7%BB%99%E6%9C%AA%E6%9D%A5%E7%9A%84%E8%87%AA%E5%B7%B1",
            "img_url": "https://p26-sign.douyinpic.com/tos-cn-p-0015c000-ce/o8Ft28GVfRVeMOmP9Zf94vpIDIfLQDomTQAAXP~noop.jpeg?lk3s=bfd515bb&x-expires=1783033200&x-signature=pxRQoCvD2Oeh%2B3b11KA8vM0tbpE%3D&from=3218412987",
            "push_time": "2026-07-02 16:58:37",
            "now_time": "2026-07-03",
            "type": "热搜",
            "source": "抖音"
        },
        {
            "index": 5,
            "title": "香港演员梁珊去世",
            "hot": 10784095,
            "url": "https://www.douyin.com/search/%E9%A6%99%E6%B8%AF%E6%BC%94%E5%91%98%E6%A2%81%E7%8F%8A%E5%8E%BB%E4%B8%96",
            "img_url": "https://p11-sign.douyinpic.com/tos-cn-p-0015/osu9igBIIEiKDmwAgCqAGDMBRQsFDUffgAtFp9~noop.jpeg?lk3s=bfd515bb&x-expires=1783033200&x-signature=4hOPuIa3knfe0BXKJ1UTMn0Z2H8%3D&from=3218412987",
            "push_time": "2026-07-02 14:53:40",
            "now_time": "2026-07-03",
            "type": "热搜",
            "source": "抖音"
        },
        {
            "index": 6,
            "title": "被光照亮的人成了光",
            "hot": 10442056,
            "url": "https://www.douyin.com/search/%E8%A2%AB%E5%85%89%E7%85%A7%E4%BA%AE%E7%9A%84%E4%BA%BA%E6%88%90%E4%BA%86%E5%85%89",
            "img_url": "https://p5-ex-gddgtc-sign.douyinpic.com/tos-cn-p-0015/oA7dAIGieN1fdQdsCgCwLIRIIA31uxBY6wzAiB~noop.jpeg?lk3s=bfd515bb&x-expires=1783033200&x-signature=6e8NYoG7SJoR%2FOPkMekfiwNSEJc%3D&from=3218412987",
            "push_time": "2026-07-02 17:25:54",
            "now_time": "2026-07-03",
            "type": "热搜",
            "source": "抖音"
        },
        {
            "index": 7,
            "title": "交换你相册里的蓝色瞬间",
            "hot": 9333531,
            "url": "https://www.douyin.com/search/%E4%BA%A4%E6%8D%A2%E4%BD%A0%E7%9B%B8%E5%86%8C%E9%87%8C%E7%9A%84%E8%93%9D%E8%89%B2%E7%9E%AC%E9%97%B4",
            "img_url": "https://p26-sign.douyinpic.com/tos-cn-p-0015/ogaasKFJnIgP0zIrkIuiQgOSBPLv51iEA6GAy~noop.jpeg?lk3s=bfd515bb&x-expires=1783033200&x-signature=KKEvhLCT3bZYQkjaqXoYAvXRico%3D&from=3218412987",
            "push_time": "2026-07-02 11:29:55",
            "now_time": "2026-07-03",
            "type": "热搜",
            "source": "抖音"
        },
        {
            "index": 8,
            "title": "潮流舞蹈这票到底投给谁",
            "hot": 9333153,
            "url": "https://www.douyin.com/search/%E6%BD%AE%E6%B5%81%E8%88%9E%E8%B9%88%E8%BF%99%E7%A5%A8%E5%88%B0%E5%BA%95%E6%8A%95%E7%BB%99%E8%B0%81",
            "img_url": "https://p11-sign.douyinpic.com/tos-cn-p-0015/owsL7YEIEAgqBUQfAdFCCtBsekRjXAAHDBn9Ax~noop.jpeg?lk3s=bfd515bb&x-expires=1783033200&x-signature=yJ%2BwaFrOgQ2fFnX7pDSVILviqL8%3D&from=3218412987",
            "push_time": "2026-07-01 17:14:11",
            "now_time": "2026-07-03",
            "type": "热搜",
            "source": "抖音"
        },
        {
            "index": 9,
            "title": "一篇长文讲述我父亲的一生",
            "hot": 9274755,
            "url": "https://www.douyin.com/search/%E4%B8%80%E7%AF%87%E9%95%BF%E6%96%87%E8%AE%B2%E8%BF%B0%E6%88%91%E7%88%B6%E4%BA%B2%E7%9A%84%E4%B8%80%E7%94%9F",
            "img_url": "https://p26-sign.douyinpic.com/tos-cn-i-0813/oM0VALfIe7I7LAfSA6AQt9FLgeCgC3HQEG0QAe~noop.jpeg?lk3s=bfd515bb&x-expires=1783033200&x-signature=4PNQMkZcJ6ddCVDdnuEBaLyQyFQ%3D&from=3218412987",
            "push_time": "2026-07-02 15:56:20",
            "now_time": "2026-07-03",
            "type": "热搜",
            "source": "抖音"
        },
        {
            "index": 10,
            "title": "茉莉奶白侵害LV商标权一审败诉",
            "hot": 9226107,
            "url": "https://www.douyin.com/search/%E8%8C%89%E8%8E%89%E5%A5%B6%E7%99%BD%E4%BE%B5%E5%AE%B3LV%E5%95%86%E6%A0%87%E6%9D%83%E4%B8%80%E5%AE%A1%E8%B4%A5%E8%AF%89",
            "img_url": "https://p26-sign.douyinpic.com/tos-cn-p-0015/okGDwIiOMwDY4QBAiQJksEa4FA9CYI1vpIPH3~noop.jpeg?lk3s=bfd515bb&x-expires=1783033200&x-signature=hkzXi%2FmbXsfRwQvjbKQ21uUL6SI%3D&from=3218412987",
            "push_time": "2026-07-02 15:51:45",
            "now_time": "2026-07-03",
            "type": "热搜",
            "source": "抖音"
        },
        {
            "index": 11,
            "title": "殷墟还藏了多少老祖宗的秘密",
            "hot": 9098666,
            "url": "https://www.douyin.com/search/%E6%AE%B7%E5%A2%9F%E8%BF%98%E8%97%8F%E4%BA%86%E5%A4%9A%E5%B0%91%E8%80%81%E7%A5%96%E5%AE%97%E7%9A%84%E7%A7%98%E5%AF%86",
            "img_url": "https://p26-sign.douyinpic.com/tos-cn-p-0015/o8v03LIBIQhQAgiZ3Fep2opA7ej2UGEeBG08Cb~noop.jpeg?lk3s=bfd515bb&x-expires=1783033200&x-signature=%2BIh7fs5sxZHKfP6wxLmYHNzh2tk%3D&from=3218412987",
            "push_time": "2026-07-02 14:26:46",
            "now_time": "2026-07-03",
            "type": "热搜",
            "source": "抖音"
        },
        {
            "index": 12,
            "title": "西班牙vs奥地利",
            "hot": 9070871,
            "url": "https://www.douyin.com/search/%E8%A5%BF%E7%8F%AD%E7%89%99vs%E5%A5%A5%E5%9C%B0%E5%88%A9",
            "img_url": "https://p26-sign.douyinpic.com/tos-cn-p-0015/o4PAxII1gzBPVlnQ08GDAIa4UUFVRw3iCLikP~noop.jpeg?lk3s=bfd515bb&x-expires=1783033200&x-signature=VoIay1RbgfZgrvFkyEcFMAM1PI8%3D&from=3218412987",
            "push_time": "2026-07-02 18:35:05",
            "now_time": "2026-07-03",
            "type": "热搜",
            "source": "抖音"
        },
        {
            "index": 13,
            "title": "“深圳开放无人驾驶”系误读",
            "hot": 9059009,
            "url": "https://www.douyin.com/search/%E2%80%9C%E6%B7%B1%E5%9C%B3%E5%BC%80%E6%94%BE%E6%97%A0%E4%BA%BA%E9%A9%BE%E9%A9%B6%E2%80%9D%E7%B3%BB%E8%AF%AF%E8%AF%BB",
            "img_url": "https://p26-sign.douyinpic.com/tos-cn-i-dy/fb481ba4581d4f129f60b1611cb7f88c~noop.jpeg?lk3s=bfd515bb&x-expires=1783033200&x-signature=gVl9si%2BiIHFVT2XohjlXzlGWJvk%3D&from=3218412987",
            "push_time": "2026-07-02 19:51:53",
            "now_time": "2026-07-03",
            "type": "热搜",
            "source": "抖音"
        },
        {
            "index": 14,
            "title": "广东荔枝木烧鹅真的太正了",
            "hot": 8778719,
            "url": "https://www.douyin.com/search/%E5%B9%BF%E4%B8%9C%E8%8D%94%E6%9E%9D%E6%9C%A8%E7%83%A7%E9%B9%85%E7%9C%9F%E7%9A%84%E5%A4%AA%E6%AD%A3%E4%BA%86",
            "img_url": "https://p26-sign.douyinpic.com/tos-cn-p-0015/oAMJfABIdGBAuieO14kv0BCAgExGBZpIoxywi9~noop.jpeg?lk3s=bfd515bb&x-expires=1783033200&x-signature=r35YBx9BtBV%2BbfzLmqhwyGIxPOQ%3D&from=3218412987",
            "push_time": "2026-07-02 16:56:58",
            "now_time": "2026-07-03",
            "type": "热搜",
            "source": "抖音"
        },
        {
            "index": 15,
            "title": "今年第9号台风巴威已生成",
            "hot": 8663309,
            "url": "https://www.douyin.com/search/%E4%BB%8A%E5%B9%B4%E7%AC%AC9%E5%8F%B7%E5%8F%B0%E9%A3%8E%E5%B7%B4%E5%A8%81%E5%B7%B2%E7%94%9F%E6%88%90",
            "img_url": "https://p5-ex-gddgtc-sign.douyinpic.com/tos-cn-p-0015/owlMm8iIIAg1k0Ifj0iDFDJZzMhE3AAUBBueD4~noop.jpeg?lk3s=bfd515bb&x-expires=1783033200&x-signature=QZy%2BiDhurHzoqKNwvGtsNCkOAKk%3D&from=3218412987",
            "push_time": "2026-07-02 16:32:37",
            "now_time": "2026-07-03",
            "type": "热搜",
            "source": "抖音"
        },
        {
            "index": 16,
            "title": "佛得角总统称能1:0击败阿根廷",
            "hot": 8413641,
            "url": "https://www.douyin.com/search/%E4%BD%9B%E5%BE%97%E8%A7%92%E6%80%BB%E7%BB%9F%E7%A7%B0%E8%83%BD1%3A0%E5%87%BB%E8%B4%A5%E9%98%BF%E6%A0%B9%E5%BB%B7",
            "img_url": "https://p3-sign.douyinpic.com/tos-cn-p-0015/oAeGh8yElZ9LFIWIJBFqADFDg4CQwAAKfgRAL1~noop.jpeg?lk3s=bfd515bb&x-expires=1783033200&x-signature=VXwb9i9lfz0uZ5sUto1X55KjW6w%3D&from=3218412987",
            "push_time": "2026-07-02 15:17:38",
            "now_time": "2026-07-03",
            "type": "热搜",
            "source": "抖音"
        },
        {
            "index": 17,
            "title": "逆战未来S3无主之地赛季上线",
            "hot": 8392343,
            "url": "https://www.douyin.com/search/%E9%80%86%E6%88%98%E6%9C%AA%E6%9D%A5S3%E6%97%A0%E4%B8%BB%E4%B9%8B%E5%9C%B0%E8%B5%9B%E5%AD%A3%E4%B8%8A%E7%BA%BF",
            "img_url": "https://p3-sign.douyinpic.com/tos-cn-p-0015/osfVFPJAAFBEJNgfkWDRCqIERIDOHB9xQFlAFP~noop.jpeg?lk3s=bfd515bb&x-expires=1783033200&x-signature=UEvC1DXFI0116G14fEjaE1CgsPE%3D&from=3218412987",
            "push_time": "2026-07-02 13:50:50",
            "now_time": "2026-07-03",
            "type": "热搜",
            "source": "抖音"
        },
        {
            "index": 18,
            "title": "半导体开启年内第二轮涨价",
            "hot": 8317428,
            "url": "https://www.douyin.com/search/%E5%8D%8A%E5%AF%BC%E4%BD%93%E5%BC%80%E5%90%AF%E5%B9%B4%E5%86%85%E7%AC%AC%E4%BA%8C%E8%BD%AE%E6%B6%A8%E4%BB%B7",
            "img_url": "https://p26-sign.douyinpic.com/tos-cn-p-0015/o4iL8vAgQ1MAiazW3eCSqUcMVJfB7BHfQEzr8z~noop.jpeg?lk3s=bfd515bb&x-expires=1783033200&x-signature=4W4ULvlFTDMcRvK9u%2F%2Fku0jv9mI%3D&from=3218412987",
            "push_time": "2026-07-02 09:46:09",
            "now_time": "2026-07-03",
            "type": "热搜",
            "source": "抖音"
        },
        {
            "index": 19,
            "title": "葡萄牙vs克罗地亚",
            "hot": 7849254,
            "url": "https://www.douyin.com/search/%E8%91%A1%E8%90%84%E7%89%99vs%E5%85%8B%E7%BD%97%E5%9C%B0%E4%BA%9A",
            "img_url": "https://p9-sign.douyinpic.com/tos-cn-p-0015/osAkmZIgNcAimiwAJoe6yIfC1CBkABvIhDZ1sG~noop.jpeg?lk3s=bfd515bb&x-expires=1783033200&x-signature=jxMdbePq4ywNMqo2fIjIjIK0m6w%3D&from=3218412987",
            "push_time": "2026-07-02 18:38:10",
            "now_time": "2026-07-03",
            "type": "热搜",
            "source": "抖音"
        },
        {
            "index": 20,
            "title": "学姐我注册抖音号了",
            "hot": 7845172,
            "url": "https://www.douyin.com/search/%E5%AD%A6%E5%A7%90%E6%88%91%E6%B3%A8%E5%86%8C%E6%8A%96%E9%9F%B3%E5%8F%B7%E4%BA%86",
            "img_url": "https://p3-sign.douyinpic.com/tos-cn-p-0015c000-ce/ocQA5BE7SED49cwPhrxfFsDEfunAZqIAuIEQsA~noop.jpeg?lk3s=bfd515bb&x-expires=1783033200&x-signature=6r4Lv6AOM0xSegrPhbvh%2BTtr5vQ%3D&from=3218412987",
            "push_time": "2026-07-02 14:41:45",
            "now_time": "2026-07-03",
            "type": "热搜",
            "source": "抖音"
        },
        {
            "index": 21,
            "title": "永劫无间手游二周年开启",
            "hot": 7828879,
            "url": "https://www.douyin.com/search/%E6%B0%B8%E5%8A%AB%E6%97%A0%E9%97%B4%E6%89%8B%E6%B8%B8%E4%BA%8C%E5%91%A8%E5%B9%B4%E5%BC%80%E5%90%AF",
            "img_url": "https://p3-sign.douyinpic.com/tos-cn-p-0015c000-ce/ogfiDfg5BEhOIIcfdBUgFDZEEN7NAHOWNJoVZI~noop.jpeg?lk3s=bfd515bb&x-expires=1783033200&x-signature=oUPxHrcJzzWpQxFiLna4Q0YyH8s%3D&from=3218412987",
            "push_time": "2026-07-02 13:51:51",
            "now_time": "2026-07-03",
            "type": "热搜",
            "source": "抖音"
        },
        {
            "index": 22,
            "title": "杰伦布朗保罗乔治互换东家",
            "hot": 7805014,
            "url": "https://www.douyin.com/search/%E6%9D%B0%E4%BC%A6%E5%B8%83%E6%9C%97%E4%BF%9D%E7%BD%97%E4%B9%94%E6%B2%BB%E4%BA%92%E6%8D%A2%E4%B8%9C%E5%AE%B6",
            "img_url": "https://p26-sign.douyinpic.com/tos-cn-p-0015/ogQbQGOfFMA8m1fH3zWPB7UGBBaAfCPiQu8gFQ~noop.jpeg?lk3s=bfd515bb&x-expires=1783033200&x-signature=s6zpKmbsePny6Se2xshXwx21nv8%3D&from=3218412987",
            "push_time": "2026-07-02 07:12:53",
            "now_time": "2026-07-03",
            "type": "热搜",
            "source": "抖音"
        },
        {
            "index": 23,
            "title": "迷核手势舞",
            "hot": 7792826,
            "url": "https://www.douyin.com/search/%E8%BF%B7%E6%A0%B8%E6%89%8B%E5%8A%BF%E8%88%9E",
            "img_url": "https://p3-sign.douyinpic.com/tos-cn-p-0015c000-ce/oQJAdNiIcEByEzAAc7DwfEiX1AImeEqEe2jEjC~noop.jpeg?lk3s=bfd515bb&x-expires=1783033200&x-signature=Gtm0HsXIKXCtA2SDDYlUhppFwps%3D&from=3218412987",
            "push_time": "2026-07-01 23:16:17",
            "now_time": "2026-07-03",
            "type": "热搜",
            "source": "抖音"
        },
        {
            "index": 24,
            "title": "我已加入松弛派对",
            "hot": 7787165,
            "url": "https://www.douyin.com/search/%E6%88%91%E5%B7%B2%E5%8A%A0%E5%85%A5%E6%9D%BE%E5%BC%9B%E6%B4%BE%E5%AF%B9",
            "img_url": "https://p11-sign.douyinpic.com/tos-cn-i-0813/owtvFABquNAAAiI1BIiPACgtr3GAe6EgeAB4A8~noop.jpeg?lk3s=bfd515bb&x-expires=1783033200&x-signature=csdsYBzlXKw8ptoOK0GXHsNJGf4%3D&from=3218412987",
            "push_time": "2026-07-02 21:04:55",
            "now_time": "2026-07-03",
            "type": "热搜",
            "source": "抖音"
        },
        {
            "index": 25,
            "title": "千香黎非摇鞠婧祎本尊驾到",
            "hot": 7782097,
            "url": "https://www.douyin.com/search/%E5%8D%83%E9%A6%99%E9%BB%8E%E9%9D%9E%E6%91%87%E9%9E%A0%E5%A9%A7%E7%A5%8E%E6%9C%AC%E5%B0%8A%E9%A9%BE%E5%88%B0",
            "img_url": "https://p26-sign.douyinpic.com/tos-cn-p-0015c000-ce/oogZHIMeUJUBz89ZAGDfiE3jLDwIQQe7bBxiMA~noop.jpeg?lk3s=bfd515bb&x-expires=1783033200&x-signature=boNESwcsba8ygmzJbhyhezZYYfY%3D&from=3218412987",
            "push_time": "2026-07-02 21:47:38",
            "now_time": "2026-07-03",
            "type": "热搜",
            "source": "抖音"
        },
        {
            "index": 26,
            "title": "哈兰德破纪录后发了5条抖音",
            "hot": 7776453,
            "url": "https://www.douyin.com/search/%E5%93%88%E5%85%B0%E5%BE%B7%E7%A0%B4%E7%BA%AA%E5%BD%95%E5%90%8E%E5%8F%91%E4%BA%865%E6%9D%A1%E6%8A%96%E9%9F%B3",
            "img_url": "https://p3-sign.douyinpic.com/tos-cn-i-0813c000-ce/osHAAiKBwOACQeOiPA1eEAAyEdEzmIIGgYDBFo~noop.jpeg?lk3s=bfd515bb&x-expires=1783033200&x-signature=UMPMxG6I0Gjnkz%2F8zBDF2rK4ou0%3D&from=3218412987",
            "push_time": "2026-07-02 21:16:33",
            "now_time": "2026-07-03",
            "type": "热搜",
            "source": "抖音"
        },
        {
            "index": 27,
            "title": "天黑不睡觉天亮还在熬",
            "hot": 7762200,
            "url": "https://www.douyin.com/search/%E5%A4%A9%E9%BB%91%E4%B8%8D%E7%9D%A1%E8%A7%89%E5%A4%A9%E4%BA%AE%E8%BF%98%E5%9C%A8%E7%86%AC",
            "img_url": "https://p3-sign.douyinpic.com/tos-cn-i-0813c000-ce/oQrqJ3AqEihgVMAEkh1AEBNEIInMexAfwAPiBe~noop.jpeg?lk3s=bfd515bb&x-expires=1783033200&x-signature=CD2ZHXlD4KNrlBxa3VDhESmNhcQ%3D&from=3218412987",
            "push_time": "2026-07-02 16:30:51",
            "now_time": "2026-07-03",
            "type": "热搜",
            "source": "抖音"
        },
        {
            "index": 28,
            "title": "徐良伴舞小哥终于更新了",
            "hot": 7735849,
            "url": "https://www.douyin.com/search/%E5%BE%90%E8%89%AF%E4%BC%B4%E8%88%9E%E5%B0%8F%E5%93%A5%E7%BB%88%E4%BA%8E%E6%9B%B4%E6%96%B0%E4%BA%86",
            "img_url": "https://p11-sign.douyinpic.com/tos-cn-p-0015/ogAtBBuUaENCE7ZQTuLfCF6iaD0ekfI2hkQv5A~noop.jpeg?lk3s=bfd515bb&x-expires=1783033200&x-signature=DJM2EkaSwr7%2FHUcFmH3eJ%2FzBFYs%3D&from=3218412987",
            "push_time": "2026-07-02 15:36:30",
            "now_time": "2026-07-03",
            "type": "热搜",
            "source": "抖音"
        },
        {
            "index": 29,
            "title": "野狗骨头定档",
            "hot": 7731530,
            "url": "https://www.douyin.com/search/%E9%87%8E%E7%8B%97%E9%AA%A8%E5%A4%B4%E5%AE%9A%E6%A1%A3",
            "img_url": "https://p5-ex-gddgtc-sign.douyinpic.com/tos-cn-i-dy/2bd0b5e090454e7d8c6e9cd6d0a3ccfe~noop.jpeg?lk3s=bfd515bb&x-expires=1783033200&x-signature=GDrDoe6h%2F2xmeElmFz%2Fmuu4MOqQ%3D&from=3218412987",
            "push_time": "2026-07-02 20:57:00",
            "now_time": "2026-07-03",
            "type": "热搜",
            "source": "抖音"
        },
        {
            "index": 30,
            "title": "当你觉得身边的人没品味时",
            "hot": 7726626,
            "url": "https://www.douyin.com/search/%E5%BD%93%E4%BD%A0%E8%A7%89%E5%BE%97%E8%BA%AB%E8%BE%B9%E7%9A%84%E4%BA%BA%E6%B2%A1%E5%93%81%E5%91%B3%E6%97%B6",
            "img_url": "https://p11-sign.douyinpic.com/tos-cn-p-0015/oEevQUD9HAOMzxDmAVgFdPJqQfkXqCEBwGgh5A~noop.jpeg?lk3s=bfd515bb&x-expires=1783033200&x-signature=kq8Cdwy9XZbZVXPyKihB82cBfxU%3D&from=3218412987",
            "push_time": "2026-07-02 21:43:55",
            "now_time": "2026-07-03",
            "type": "热搜",
            "source": "抖音"
        },
        {
            "index": 31,
            "title": "被百厨大战安利了煎蟹",
            "hot": 7723269,
            "url": "https://www.douyin.com/search/%E8%A2%AB%E7%99%BE%E5%8E%A8%E5%A4%A7%E6%88%98%E5%AE%89%E5%88%A9%E4%BA%86%E7%85%8E%E8%9F%B9",
            "img_url": "https://p3-sign.douyinpic.com/tos-cn-p-0015c000-ce/oMtOBiB2ZEMkxpwKtIvApzbCskrwEAWiPiaTH~noop.jpeg?lk3s=bfd515bb&x-expires=1783033200&x-signature=0Pz0h9d3up6CeOw47dmSuQ7WFOw%3D&from=3218412987",
            "push_time": "2026-07-02 16:49:39",
            "now_time": "2026-07-03",
            "type": "热搜",
            "source": "抖音"
        },
        {
            "index": 32,
            "title": "在毕业致辞中感受语言的力量",
            "hot": 7719129,
            "url": "https://www.douyin.com/search/%E5%9C%A8%E6%AF%95%E4%B8%9A%E8%87%B4%E8%BE%9E%E4%B8%AD%E6%84%9F%E5%8F%97%E8%AF%AD%E8%A8%80%E7%9A%84%E5%8A%9B%E9%87%8F",
            "img_url": "https://p5-ex-gddgtc-sign.douyinpic.com/tos-cn-i-0813c000-ce/oQBiyWbcEF7AoXICkGmBfE5ezkAiAAywAcB1IU~noop.jpeg?lk3s=bfd515bb&x-expires=1783033200&x-signature=boXQQOvBSQzMCBnS1mv4H6C9fkg%3D&from=3218412987",
            "push_time": "2026-07-02 20:52:47",
            "now_time": "2026-07-03",
            "type": "热搜",
            "source": "抖音"
        },
        {
            "index": 33,
            "title": "异环真红",
            "hot": 7715404,
            "url": "https://www.douyin.com/search/%E5%BC%82%E7%8E%AF%E7%9C%9F%E7%BA%A2",
            "img_url": "https://p26-sign.douyinpic.com/tos-cn-p-0015/os3EAgfDDQyP9AqAlwfESRVOJBZAdEDgFC6CQg~noop.jpeg?lk3s=bfd515bb&x-expires=1783033200&x-signature=Der8dJaPdXYqYdJ1lg%2BiFD2RWHY%3D&from=3218412987",
            "push_time": "2026-07-02 11:07:45",
            "now_time": "2026-07-03",
            "type": "热搜",
            "source": "抖音"
        },
        {
            "index": 34,
            "title": "王楚钦孙颖莎逆转进四强",
            "hot": 7711172,
            "url": "https://www.douyin.com/search/%E7%8E%8B%E6%A5%9A%E9%92%A6%E5%AD%99%E9%A2%96%E8%8E%8E%E9%80%86%E8%BD%AC%E8%BF%9B%E5%9B%9B%E5%BC%BA",
            "img_url": "https://p5-ex-gddgtc-sign.douyinpic.com/tos-cn-p-0015/oMdqNapbPAVoF9NfgQFMRNCDufVIPQZEAABiLQ~noop.jpeg?lk3s=bfd515bb&x-expires=1783033200&x-signature=pi87xqzInmiDWBVoi3lsJla28%2BU%3D&from=3218412987",
            "push_time": "2026-07-02 07:05:54",
            "now_time": "2026-07-03",
            "type": "热搜",
            "source": "抖音"
        },
        {
            "index": 35,
            "title": "妙脆角给小猫种好了不用谢",
            "hot": 7706887,
            "url": "https://www.douyin.com/search/%E5%A6%99%E8%84%86%E8%A7%92%E7%BB%99%E5%B0%8F%E7%8C%AB%E7%A7%8D%E5%A5%BD%E4%BA%86%E4%B8%8D%E7%94%A8%E8%B0%A2",
            "img_url": "https://p26-sign.douyinpic.com/tos-cn-p-0015c000-ce/owFAqfSFSwr9DtoQCSmEAXBnIERFIkw0qxBSfp~noop.jpeg?lk3s=bfd515bb&x-expires=1783033200&x-signature=O8RkfaOhokEpnjS9Mx1ZQNadDM4%3D&from=3218412987",
            "push_time": "2026-07-02 14:19:11",
            "now_time": "2026-07-03",
            "type": "热搜",
            "source": "抖音"
        },
        {
            "index": 36,
            "title": "当我看到比利时绝境逆转",
            "hot": 7706845,
            "url": "https://www.douyin.com/search/%E5%BD%93%E6%88%91%E7%9C%8B%E5%88%B0%E6%AF%94%E5%88%A9%E6%97%B6%E7%BB%9D%E5%A2%83%E9%80%86%E8%BD%AC",
            "img_url": "https://p26-sign.douyinpic.com/tos-cn-p-0015/o8BJAQjRuFCpZAaNQqEDxKfGQ76fgBb3ANLIc9~noop.jpeg?lk3s=bfd515bb&x-expires=1783033200&x-signature=sZQj4Jajz08kkq8XKrUuZE2DbEY%3D&from=3218412987",
            "push_time": "2026-07-02 08:55:27",
            "now_time": "2026-07-03",
            "type": "热搜",
            "source": "抖音"
        },
        {
            "index": 37,
            "title": "动画电影去你的岛定档",
            "hot": 7698262,
            "url": "https://www.douyin.com/search/%E5%8A%A8%E7%94%BB%E7%94%B5%E5%BD%B1%E5%8E%BB%E4%BD%A0%E7%9A%84%E5%B2%9B%E5%AE%9A%E6%A1%A3",
            "img_url": "https://p26-sign.douyinpic.com/tos-cn-p-0015/oo1EBjJNILAbBiBAI7tGa5ML4fxFxfUFIB8eCr~noop.jpeg?lk3s=bfd515bb&x-expires=1783033200&x-signature=UXtPIa5wAQKK9QUflPIV3YG3yfc%3D&from=3218412987",
            "push_time": "2026-07-02 11:02:37",
            "now_time": "2026-07-03",
            "type": "热搜",
            "source": "抖音"
        },
        {
            "index": 38,
            "title": "花式上马就看清明上河园",
            "hot": 7697901,
            "url": "https://www.douyin.com/search/%E8%8A%B1%E5%BC%8F%E4%B8%8A%E9%A9%AC%E5%B0%B1%E7%9C%8B%E6%B8%85%E6%98%8E%E4%B8%8A%E6%B2%B3%E5%9B%AD",
            "img_url": "https://p26-sign.douyinpic.com/tos-cn-p-0015c000-ce/ogVpEnED88fEW7mGyqcFAfvIqKF0i9ARMYBDpw~noop.jpeg?lk3s=bfd515bb&x-expires=1783033200&x-signature=Y2LnClDU0EJ%2B%2BHsgGAdct9np9aY%3D&from=3218412987",
            "push_time": "2026-07-02 16:04:18",
            "now_time": "2026-07-03",
            "type": "热搜",
            "source": "抖音"
        },
        {
            "index": 39,
            "title": "在喜欢你6里看到社交入侵",
            "hot": 7697689,
            "url": "https://www.douyin.com/search/%E5%9C%A8%E5%96%9C%E6%AC%A2%E4%BD%A06%E9%87%8C%E7%9C%8B%E5%88%B0%E7%A4%BE%E4%BA%A4%E5%85%A5%E4%BE%B5",
            "img_url": "https://p3-sign.douyinpic.com/tos-cn-p-0015/ocgEMsgQEZDAQDZFlfBhCqrdvPxA9ACmIas3fX~noop.jpeg?lk3s=bfd515bb&x-expires=1783033200&x-signature=a38S4VtOB%2By4tpFjUswp0R4fVLM%3D&from=3218412987",
            "push_time": "2026-07-02 07:01:01",
            "now_time": "2026-07-03",
            "type": "热搜",
            "source": "抖音"
        },
        {
            "index": 40,
            "title": "我是姆巴佩中国分佩",
            "hot": 7694430,
            "url": "https://www.douyin.com/search/%E6%88%91%E6%98%AF%E5%A7%86%E5%B7%B4%E4%BD%A9%E4%B8%AD%E5%9B%BD%E5%88%86%E4%BD%A9",
            "img_url": "https://p26-sign.douyinpic.com/tos-cn-p-0015c000-ce/oIpDedWN1EeuAvExrCIizNdiIdBE9QAUswfdvv~noop.jpeg?lk3s=bfd515bb&x-expires=1783033200&x-signature=tuWakTY6tje6zS58WqWFf%2BPxNGI%3D&from=3218412987",
            "push_time": "2026-07-01 14:36:08",
            "now_time": "2026-07-03",
            "type": "热搜",
            "source": "抖音"
        },
        {
            "index": 41,
            "title": "你说我变了反差转场",
            "hot": 7692701,
            "url": "https://www.douyin.com/search/%E4%BD%A0%E8%AF%B4%E6%88%91%E5%8F%98%E4%BA%86%E5%8F%8D%E5%B7%AE%E8%BD%AC%E5%9C%BA",
            "img_url": "https://p26-sign.douyinpic.com/tos-cn-p-0015c000-ce/o0U88XHjPCuI4AL7vJ1Qv6eCMhBtgNeiiLgGIe~noop.jpeg?lk3s=bfd515bb&x-expires=1783033200&x-signature=mjNlm%2BraBLSRbfRdqoZnXJIXItc%3D&from=3218412987",
            "push_time": "2026-07-01 14:32:01",
            "now_time": "2026-07-03",
            "type": "热搜",
            "source": "抖音"
        },
        {
            "index": 42,
            "title": "晒出我的面试穿搭",
            "hot": 7687107,
            "url": "https://www.douyin.com/search/%E6%99%92%E5%87%BA%E6%88%91%E7%9A%84%E9%9D%A2%E8%AF%95%E7%A9%BF%E6%90%AD",
            "img_url": "https://p11-sign.douyinpic.com/tos-cn-p-0015c000-ce/oUeN6NMJTUq0QgIaPD5LeBfGCQaETQ7NxK8ADJ~noop.jpeg?lk3s=bfd515bb&x-expires=1783033200&x-signature=e2%2F60cDXnVGFjcIBVANdlp%2Bm%2Bjk%3D&from=3218412987",
            "push_time": "2026-07-01 10:55:00",
            "now_time": "2026-07-03",
            "type": "热搜",
            "source": "抖音"
        },
        {
            "index": 43,
            "title": "原来每个省都有自己的省冰",
            "hot": 7682441,
            "url": "https://www.douyin.com/search/%E5%8E%9F%E6%9D%A5%E6%AF%8F%E4%B8%AA%E7%9C%81%E9%83%BD%E6%9C%89%E8%87%AA%E5%B7%B1%E7%9A%84%E7%9C%81%E5%86%B0",
            "img_url": "https://p3-sign.douyinpic.com/tos-cn-p-0015/oYmlzBPkItwdz4ANAVDQEIT8dkPdGqiG24Bia~noop.jpeg?lk3s=bfd515bb&x-expires=1783033200&x-signature=AC71TTWCraK7HGhN%2Ffs2NPLxxJw%3D&from=3218412987",
            "push_time": "2026-07-02 11:19:07",
            "now_time": "2026-07-03",
            "type": "热搜",
            "source": "抖音"
        },
        {
            "index": 44,
            "title": "用早茶晚酒支持你的主队",
            "hot": 7676793,
            "url": "https://www.douyin.com/search/%E7%94%A8%E6%97%A9%E8%8C%B6%E6%99%9A%E9%85%92%E6%94%AF%E6%8C%81%E4%BD%A0%E7%9A%84%E4%B8%BB%E9%98%9F",
            "img_url": "https://p3-sign.douyinpic.com/tos-cn-p-0015/o4fbIiVNPBAFYhwQIQxx64AaK0KgyqEFDA9eEZ~noop.jpeg?lk3s=bfd515bb&x-expires=1783033200&x-signature=gPqzNgJgxvK3%2BsuSewuiIdtUPmU%3D&from=3218412987",
            "push_time": "2026-07-02 14:54:56",
            "now_time": "2026-07-03",
            "type": "热搜",
            "source": "抖音"
        },
        {
            "index": 45,
            "title": "吃桃子也有南北差异吗",
            "hot": 7675415,
            "url": "https://www.douyin.com/search/%E5%90%83%E6%A1%83%E5%AD%90%E4%B9%9F%E6%9C%89%E5%8D%97%E5%8C%97%E5%B7%AE%E5%BC%82%E5%90%97",
            "img_url": "https://p3-sign.douyinpic.com/tos-cn-p-0015c000-ce/okBa3dBPNY4OdvUE1CiiJgDaHEIyPCkABAMpu~noop.jpeg?lk3s=bfd515bb&x-expires=1783033200&x-signature=koWjGF1x72JkQkMgC7%2BlotUtDcA%3D&from=3218412987",
            "push_time": "2026-07-01 17:08:52",
            "now_time": "2026-07-03",
            "type": "热搜",
            "source": "抖音"
        },
        {
            "index": 46,
            "title": "下半年也要去看更美的风景",
            "hot": 7675315,
            "url": "https://www.douyin.com/search/%E4%B8%8B%E5%8D%8A%E5%B9%B4%E4%B9%9F%E8%A6%81%E5%8E%BB%E7%9C%8B%E6%9B%B4%E7%BE%8E%E7%9A%84%E9%A3%8E%E6%99%AF",
            "img_url": "https://p3-sign.douyinpic.com/tos-cn-p-0015/oIA6EMPFI7PBIAXklvQa0Id0ikDM9ii9NwzQV~noop.jpeg?lk3s=bfd515bb&x-expires=1783033200&x-signature=GjTWqzk6NdcMCgRXWPxR%2BCEhwoc%3D&from=3218412987",
            "push_time": "2026-07-01 15:31:10",
            "now_time": "2026-07-03",
            "type": "热搜",
            "source": "抖音"
        },
        {
            "index": 47,
            "title": "V8和CORTIS一起鬼步舞",
            "hot": 7668353,
            "url": "https://www.douyin.com/search/V8%E5%92%8CCORTIS%E4%B8%80%E8%B5%B7%E9%AC%BC%E6%AD%A5%E8%88%9E",
            "img_url": "https://p3-sign.douyinpic.com/tos-cn-p-0015/oggLTElaqAxfpN8xADBAyRuRFDMINQf9qAZhMY~noop.jpeg?lk3s=bfd515bb&x-expires=1783033200&x-signature=GE6D%2FL4u6c%2FI4phZuqJx9KG6pH4%3D&from=3218412987",
            "push_time": "2026-07-02 20:32:16",
            "now_time": "2026-07-03",
            "type": "热搜",
            "source": "抖音"
        },
        {
            "index": 48,
            "title": "地瓜炉变身全能烧烤炉",
            "hot": 7665333,
            "url": "https://www.douyin.com/search/%E5%9C%B0%E7%93%9C%E7%82%89%E5%8F%98%E8%BA%AB%E5%85%A8%E8%83%BD%E7%83%A7%E7%83%A4%E7%82%89",
            "img_url": "https://p9-sign.douyinpic.com/tos-cn-p-0015c000-ce/oUFjVeJqQA7CEZVFEoo859yCevDfQIhmAOcwID~noop.jpeg?lk3s=bfd515bb&x-expires=1783033200&x-signature=UnxtAnD8LWqFNgro1JPDVyuBjCs%3D&from=3218412987",
            "push_time": "2026-07-01 09:36:29",
            "now_time": "2026-07-03",
            "type": "热搜",
            "source": "抖音"
        },
        {
            "index": 49,
            "title": "唇印四宫格美得太犯规",
            "hot": 7660885,
            "url": "https://www.douyin.com/search/%E5%94%87%E5%8D%B0%E5%9B%9B%E5%AE%AB%E6%A0%BC%E7%BE%8E%E5%BE%97%E5%A4%AA%E7%8A%AF%E8%A7%84",
            "img_url": "https://p26-sign.douyinpic.com/tos-cn-p-0015c000-ce/oseUDHlXEhZF4a3AxgeIhAkA7xVIDJC0BfXQJQ~noop.jpeg?lk3s=bfd515bb&x-expires=1783033200&x-signature=y7LtgAohaXnaHmz86zlb3My8O5w%3D&from=3218412987",
            "push_time": "2026-07-02 12:52:29",
            "now_time": "2026-07-03",
            "type": "热搜",
            "source": "抖音"
        },
        {
            "index": 50,
            "title": "宋威龙张婧仪头碰头上甜度了",
            "hot": 7659811,
            "url": "https://www.douyin.com/search/%E5%AE%8B%E5%A8%81%E9%BE%99%E5%BC%A0%E5%A9%A7%E4%BB%AA%E5%A4%B4%E7%A2%B0%E5%A4%B4%E4%B8%8A%E7%94%9C%E5%BA%A6%E4%BA%86",
            "img_url": "https://p26-sign.douyinpic.com/tos-cn-p-0015c000-ce/oYMAAVIaSFPhkEiG6Ru1UPmdxCin2BCYZ3X4b~noop.jpeg?lk3s=bfd515bb&x-expires=1783033200&x-signature=nylqBKoYVB3d%2B9040KCYiGhVqyg%3D&from=3218412987",
            "push_time": "2026-07-02 20:26:48",
            "now_time": "2026-07-03",
            "type": "热搜",
            "source": "抖音"
        }
    ],
    "2026-07-03 02:44:53": [
        {
            "index": 1,
            "title": "中国男篮对日本12人大名单公布",
            "hot": 12103400,
            "url": "https://www.douyin.com/search/%E4%B8%AD%E5%9B%BD%E7%94%B7%E7%AF%AE%E5%AF%B9%E6%97%A5%E6%9C%AC12%E4%BA%BA%E5%A4%A7%E5%90%8D%E5%8D%95%E5%85%AC%E5%B8%83",
            "img_url": "https://p3-sign.douyinpic.com/tos-cn-p-0015/oo0AyfnMagf9DQdQNZ4EAaBC8ARFQG8Lq5m16S~noop.jpeg?lk3s=bfd515bb&x-expires=1783036800&x-signature=COh8qKQMNm9%2BJ06%2Ba5CBq52S0k8%3D&from=3218412987",
            "push_time": "2026-07-02 22:55:23",
            "now_time": "2026-07-03",
            "type": "热搜",
            "source": "抖音"
        },
        {
            "index": 2,
            "title": "爱的双手滋养出最灿烂的鲜花",
            "hot": 12093514,
            "url": "https://www.douyin.com/search/%E7%88%B1%E7%9A%84%E5%8F%8C%E6%89%8B%E6%BB%8B%E5%85%BB%E5%87%BA%E6%9C%80%E7%81%BF%E7%83%82%E7%9A%84%E9%B2%9C%E8%8A%B1",
            "img_url": "https://p5-ex-gddgtc-sign.douyinpic.com/tos-cn-p-0015c000-ce/oUqInQWawAvBEvot9FfPiqDB00Re6EASwP3LDM~noop.jpeg?lk3s=bfd515bb&x-expires=1783036800&x-signature=wtJPQGXV%2BKXdlTQuPbBipO55O0U%3D&from=3218412987",
            "push_time": "2026-07-02 17:46:13",
            "now_time": "2026-07-03",
            "type": "热搜",
            "source": "抖音"
        },
        {
            "index": 3,
            "title": "前5月我国农机出口超336亿元",
            "hot": 11797092,
            "url": "https://www.douyin.com/search/%E5%89%8D5%E6%9C%88%E6%88%91%E5%9B%BD%E5%86%9C%E6%9C%BA%E5%87%BA%E5%8F%A3%E8%B6%85336%E4%BA%BF%E5%85%83",
            "img_url": "https://p26-sign.douyinpic.com/tos-cn-p-0015/oMOlICB3aDAaKBOyLiFuA9qHxAggfBkRIpfwGE~noop.jpeg?lk3s=bfd515bb&x-expires=1783036800&x-signature=SSk00sXTybZ6HA26VR63Z8VSkdI%3D&from=3218412987",
            "push_time": "2026-07-02 20:17:36",
            "now_time": "2026-07-03",
            "type": "热搜",
            "source": "抖音"
        },
        {
            "index": 4,
            "title": "时间胶囊写给未来的自己",
            "hot": 11476358,
            "url": "https://www.douyin.com/search/%E6%97%B6%E9%97%B4%E8%83%B6%E5%9B%8A%E5%86%99%E7%BB%99%E6%9C%AA%E6%9D%A5%E7%9A%84%E8%87%AA%E5%B7%B1",
            "img_url": "https://p26-sign.douyinpic.com/tos-cn-p-0015c000-ce/o8Ft28GVfRVeMOmP9Zf94vpIDIfLQDomTQAAXP~noop.jpeg?lk3s=bfd515bb&x-expires=1783036800&x-signature=PyfNDuOW1HLbK0uj0Tu%2FERCj%2BCs%3D&from=3218412987",
            "push_time": "2026-07-02 16:58:37",
            "now_time": "2026-07-03",
            "type": "热搜",
            "source": "抖音"
        },
        {
            "index": 5,
            "title": "香港演员梁珊去世",
            "hot": 10485656,
            "url": "https://www.douyin.com/search/%E9%A6%99%E6%B8%AF%E6%BC%94%E5%91%98%E6%A2%81%E7%8F%8A%E5%8E%BB%E4%B8%96",
            "img_url": "https://p3-sign.douyinpic.com/tos-cn-p-0015/osu9igBIIEiKDmwAgCqAGDMBRQsFDUffgAtFp9~noop.jpeg?lk3s=bfd515bb&x-expires=1783036800&x-signature=AiAhxvvqfvewnUG5KGlHfC1r850%3D&from=3218412987",
            "push_time": "2026-07-02 14:53:40",
            "now_time": "2026-07-03",
            "type": "热搜",
            "source": "抖音"
        },
        {
            "index": 6,
            "title": "交换你相册里的蓝色瞬间",
            "hot": 10478906,
            "url": "https://www.douyin.com/search/%E4%BA%A4%E6%8D%A2%E4%BD%A0%E7%9B%B8%E5%86%8C%E9%87%8C%E7%9A%84%E8%93%9D%E8%89%B2%E7%9E%AC%E9%97%B4",
            "img_url": "https://p3-sign.douyinpic.com/tos-cn-p-0015/ogaasKFJnIgP0zIrkIuiQgOSBPLv51iEA6GAy~noop.jpeg?lk3s=bfd515bb&x-expires=1783036800&x-signature=fzYXSOiHJTHo7%2BkBHTlY7ULfIM0%3D&from=3218412987",
            "push_time": "2026-07-02 11:29:55",
            "now_time": "2026-07-03",
            "type": "热搜",
            "source": "抖音"
        },
        {
            "index": 7,
            "title": "被光照亮的人成了光",
            "hot": 9278685,
            "url": "https://www.douyin.com/search/%E8%A2%AB%E5%85%89%E7%85%A7%E4%BA%AE%E7%9A%84%E4%BA%BA%E6%88%90%E4%BA%86%E5%85%89",
            "img_url": "https://p26-sign.douyinpic.com/tos-cn-p-0015/oA7dAIGieN1fdQdsCgCwLIRIIA31uxBY6wzAiB~noop.jpeg?lk3s=bfd515bb&x-expires=1783036800&x-signature=TcAw7J9%2Ff5lhY3fUzI27w%2F91nDk%3D&from=3218412987",
            "push_time": "2026-07-02 17:25:54",
            "now_time": "2026-07-03",
            "type": "热搜",
            "source": "抖音"
        },
        {
            "index": 8,
            "title": "一篇长文讲述我父亲的一生",
            "hot": 9207280,
            "url": "https://www.douyin.com/search/%E4%B8%80%E7%AF%87%E9%95%BF%E6%96%87%E8%AE%B2%E8%BF%B0%E6%88%91%E7%88%B6%E4%BA%B2%E7%9A%84%E4%B8%80%E7%94%9F",
            "img_url": "https://p5-ex-gddgtc-sign.douyinpic.com/tos-cn-i-0813/oM0VALfIe7I7LAfSA6AQt9FLgeCgC3HQEG0QAe~noop.jpeg?lk3s=bfd515bb&x-expires=1783036800&x-signature=ZgGM%2FYNgX1JZAWheeqtq788w6yU%3D&from=3218412987",
            "push_time": "2026-07-02 15:56:20",
            "now_time": "2026-07-03",
            "type": "热搜",
            "source": "抖音"
        },
        {
            "index": 9,
            "title": "花式上马就看清明上河园",
            "hot": 9147540,
            "url": "https://www.douyin.com/search/%E8%8A%B1%E5%BC%8F%E4%B8%8A%E9%A9%AC%E5%B0%B1%E7%9C%8B%E6%B8%85%E6%98%8E%E4%B8%8A%E6%B2%B3%E5%9B%AD",
            "img_url": "https://p3-sign.douyinpic.com/tos-cn-p-0015c000-ce/ogVpEnED88fEW7mGyqcFAfvIqKF0i9ARMYBDpw~noop.jpeg?lk3s=bfd515bb&x-expires=1783036800&x-signature=gz3%2F0DCqMK8apKyF95l7dl8yXIo%3D&from=3218412987",
            "push_time": "2026-07-02 16:04:18",
            "now_time": "2026-07-03",
            "type": "热搜",
            "source": "抖音"
        },
        {
            "index": 10,
            "title": "原来每个省都有自己的省冰",
            "hot": 9145843,
            "url": "https://www.douyin.com/search/%E5%8E%9F%E6%9D%A5%E6%AF%8F%E4%B8%AA%E7%9C%81%E9%83%BD%E6%9C%89%E8%87%AA%E5%B7%B1%E7%9A%84%E7%9C%81%E5%86%B0",
            "img_url": "https://p5-ex-gddgtc-sign.douyinpic.com/tos-cn-p-0015/oYmlzBPkItwdz4ANAVDQEIT8dkPdGqiG24Bia~noop.jpeg?lk3s=bfd515bb&x-expires=1783036800&x-signature=Q8Cl5wOXEITvu7G82DE83o%2FxgVA%3D&from=3218412987",
            "push_time": "2026-07-02 11:19:07",
            "now_time": "2026-07-03",
            "type": "热搜",
            "source": "抖音"
        },
        {
            "index": 11,
            "title": "潮流舞蹈这票到底投给谁",
            "hot": 9118513,
            "url": "https://www.douyin.com/search/%E6%BD%AE%E6%B5%81%E8%88%9E%E8%B9%88%E8%BF%99%E7%A5%A8%E5%88%B0%E5%BA%95%E6%8A%95%E7%BB%99%E8%B0%81",
            "img_url": "https://p26-sign.douyinpic.com/tos-cn-p-0015/owsL7YEIEAgqBUQfAdFCCtBsekRjXAAHDBn9Ax~noop.jpeg?lk3s=bfd515bb&x-expires=1783036800&x-signature=l7H0bN8ikdsCHo7VxIJZFAw4X4M%3D&from=3218412987",
            "push_time": "2026-07-01 17:14:11",
            "now_time": "2026-07-03",
            "type": "热搜",
            "source": "抖音"
        },
        {
            "index": 12,
            "title": "西班牙vs奥地利",
            "hot": 9035982,
            "url": "https://www.douyin.com/search/%E8%A5%BF%E7%8F%AD%E7%89%99vs%E5%A5%A5%E5%9C%B0%E5%88%A9",
            "img_url": "https://p11-sign.douyinpic.com/tos-cn-p-0015/o4PAxII1gzBPVlnQ08GDAIa4UUFVRw3iCLikP~noop.jpeg?lk3s=bfd515bb&x-expires=1783036800&x-signature=6ngKh4Aj6U8C%2FhEkiRstW5Sc6hg%3D&from=3218412987",
            "push_time": "2026-07-02 18:35:05",
            "now_time": "2026-07-03",
            "type": "热搜",
            "source": "抖音"
        },
        {
            "index": 13,
            "title": "“深圳开放无人驾驶”系误读",
            "hot": 8776915,
            "url": "https://www.douyin.com/search/%E2%80%9C%E6%B7%B1%E5%9C%B3%E5%BC%80%E6%94%BE%E6%97%A0%E4%BA%BA%E9%A9%BE%E9%A9%B6%E2%80%9D%E7%B3%BB%E8%AF%AF%E8%AF%BB",
            "img_url": "https://p11-sign.douyinpic.com/tos-cn-i-dy/fb481ba4581d4f129f60b1611cb7f88c~noop.jpeg?lk3s=bfd515bb&x-expires=1783036800&x-signature=EY9%2FbkbXTUWQ2BdnAruf6TU6Qdo%3D&from=3218412987",
            "push_time": "2026-07-02 19:51:53",
            "now_time": "2026-07-03",
            "type": "热搜",
            "source": "抖音"
        },
        {
            "index": 14,
            "title": "广东荔枝木烧鹅真的太正了",
            "hot": 8639214,
            "url": "https://www.douyin.com/search/%E5%B9%BF%E4%B8%9C%E8%8D%94%E6%9E%9D%E6%9C%A8%E7%83%A7%E9%B9%85%E7%9C%9F%E7%9A%84%E5%A4%AA%E6%AD%A3%E4%BA%86",
            "img_url": "https://p3-sign.douyinpic.com/tos-cn-p-0015/oAMJfABIdGBAuieO14kv0BCAgExGBZpIoxywi9~noop.jpeg?lk3s=bfd515bb&x-expires=1783036800&x-signature=muGYdaAAvZgeIB0VS1e%2B9vIHr6w%3D&from=3218412987",
            "push_time": "2026-07-02 16:56:58",
            "now_time": "2026-07-03",
            "type": "热搜",
            "source": "抖音"
        },
        {
            "index": 15,
            "title": "今年第9号台风巴威已生成",
            "hot": 8383046,
            "url": "https://www.douyin.com/search/%E4%BB%8A%E5%B9%B4%E7%AC%AC9%E5%8F%B7%E5%8F%B0%E9%A3%8E%E5%B7%B4%E5%A8%81%E5%B7%B2%E7%94%9F%E6%88%90",
            "img_url": "https://p26-sign.douyinpic.com/tos-cn-p-0015/owlMm8iIIAg1k0Ifj0iDFDJZzMhE3AAUBBueD4~noop.jpeg?lk3s=bfd515bb&x-expires=1783036800&x-signature=M0AO3uS7NtXcMPme7IvU0FldTp8%3D&from=3218412987",
            "push_time": "2026-07-02 16:32:37",
            "now_time": "2026-07-03",
            "type": "热搜",
            "source": "抖音"
        },
        {
            "index": 16,
            "title": "茉莉奶白侵害LV商标权一审败诉",
            "hot": 7845399,
            "url": "https://www.douyin.com/search/%E8%8C%89%E8%8E%89%E5%A5%B6%E7%99%BD%E4%BE%B5%E5%AE%B3LV%E5%95%86%E6%A0%87%E6%9D%83%E4%B8%80%E5%AE%A1%E8%B4%A5%E8%AF%89",
            "img_url": "https://p3-sign.douyinpic.com/tos-cn-p-0015/okGDwIiOMwDY4QBAiQJksEa4FA9CYI1vpIPH3~noop.jpeg?lk3s=bfd515bb&x-expires=1783036800&x-signature=oWGPqqpHB7ZAJOzy%2BCJKPSbkJbM%3D&from=3218412987",
            "push_time": "2026-07-02 15:51:45",
            "now_time": "2026-07-03",
            "type": "热搜",
            "source": "抖音"
        },
        {
            "index": 17,
            "title": "逆战未来S3无主之地赛季上线",
            "hot": 7834192,
            "url": "https://www.douyin.com/search/%E9%80%86%E6%88%98%E6%9C%AA%E6%9D%A5S3%E6%97%A0%E4%B8%BB%E4%B9%8B%E5%9C%B0%E8%B5%9B%E5%AD%A3%E4%B8%8A%E7%BA%BF",
            "img_url": "https://p3-sign.douyinpic.com/tos-cn-p-0015/osfVFPJAAFBEJNgfkWDRCqIERIDOHB9xQFlAFP~noop.jpeg?lk3s=bfd515bb&x-expires=1783036800&x-signature=vNwZb7WR3OmyDtiMkbCVhmx8KNs%3D&from=3218412987",
            "push_time": "2026-07-02 13:50:50",
            "now_time": "2026-07-03",
            "type": "热搜",
            "source": "抖音"
        },
        {
            "index": 18,
            "title": "杰伦布朗保罗乔治互换东家",
            "hot": 7832872,
            "url": "https://www.douyin.com/search/%E6%9D%B0%E4%BC%A6%E5%B8%83%E6%9C%97%E4%BF%9D%E7%BD%97%E4%B9%94%E6%B2%BB%E4%BA%92%E6%8D%A2%E4%B8%9C%E5%AE%B6",
            "img_url": "https://p26-sign.douyinpic.com/tos-cn-p-0015/ogQbQGOfFMA8m1fH3zWPB7UGBBaAfCPiQu8gFQ~noop.jpeg?lk3s=bfd515bb&x-expires=1783036800&x-signature=vDr1b3nG2UkW7sMrQLC6tECQ7Ek%3D&from=3218412987",
            "push_time": "2026-07-02 07:12:53",
            "now_time": "2026-07-03",
            "type": "热搜",
            "source": "抖音"
        },
        {
            "index": 19,
            "title": "葡萄牙vs克罗地亚",
            "hot": 7824833,
            "url": "https://www.douyin.com/search/%E8%91%A1%E8%90%84%E7%89%99vs%E5%85%8B%E7%BD%97%E5%9C%B0%E4%BA%9A",
            "img_url": "https://p26-sign.douyinpic.com/tos-cn-p-0015/osAkmZIgNcAimiwAJoe6yIfC1CBkABvIhDZ1sG~noop.jpeg?lk3s=bfd515bb&x-expires=1783036800&x-signature=Scw9GGmJ58sfpTVKCNUKz6hUWhs%3D&from=3218412987",
            "push_time": "2026-07-02 18:38:10",
            "now_time": "2026-07-03",
            "type": "热搜",
            "source": "抖音"
        },
        {
            "index": 20,
            "title": "永劫无间手游二周年开启",
            "hot": 7779480,
            "url": "https://www.douyin.com/search/%E6%B0%B8%E5%8A%AB%E6%97%A0%E9%97%B4%E6%89%8B%E6%B8%B8%E4%BA%8C%E5%91%A8%E5%B9%B4%E5%BC%80%E5%90%AF",
            "img_url": "https://p11-sign.douyinpic.com/tos-cn-p-0015c000-ce/ogfiDfg5BEhOIIcfdBUgFDZEEN7NAHOWNJoVZI~noop.jpeg?lk3s=bfd515bb&x-expires=1783036800&x-signature=v0NXIfCo%2BYIDYfndAdizAHkB6h8%3D&from=3218412987",
            "push_time": "2026-07-02 13:51:51",
            "now_time": "2026-07-03",
            "type": "热搜",
            "source": "抖音"
        },
        {
            "index": 21,
            "title": "学姐我注册抖音号了",
            "hot": 7766149,
            "url": "https://www.douyin.com/search/%E5%AD%A6%E5%A7%90%E6%88%91%E6%B3%A8%E5%86%8C%E6%8A%96%E9%9F%B3%E5%8F%B7%E4%BA%86",
            "img_url": "https://p3-sign.douyinpic.com/tos-cn-p-0015c000-ce/ocQA5BE7SED49cwPhrxfFsDEfunAZqIAuIEQsA~noop.jpeg?lk3s=bfd515bb&x-expires=1783036800&x-signature=Nzssy89iCXPj6s9JzaSNXmkVh9k%3D&from=3218412987",
            "push_time": "2026-07-02 14:41:45",
            "now_time": "2026-07-03",
            "type": "热搜",
            "source": "抖音"
        },
        {
            "index": 22,
            "title": "迷核手势舞",
            "hot": 7742846,
            "url": "https://www.douyin.com/search/%E8%BF%B7%E6%A0%B8%E6%89%8B%E5%8A%BF%E8%88%9E",
            "img_url": "https://p5-ex-gddgtc-sign.douyinpic.com/tos-cn-p-0015c000-ce/oQJAdNiIcEByEzAAc7DwfEiX1AImeEqEe2jEjC~noop.jpeg?lk3s=bfd515bb&x-expires=1783036800&x-signature=i3g%2B%2Bur1tGSjq7dIIJBQJNAPvpA%3D&from=3218412987",
            "push_time": "2026-07-01 23:16:17",
            "now_time": "2026-07-03",
            "type": "热搜",
            "source": "抖音"
        },
        {
            "index": 23,
            "title": "千香黎非摇鞠婧祎本尊驾到",
            "hot": 7740247,
            "url": "https://www.douyin.com/search/%E5%8D%83%E9%A6%99%E9%BB%8E%E9%9D%9E%E6%91%87%E9%9E%A0%E5%A9%A7%E7%A5%8E%E6%9C%AC%E5%B0%8A%E9%A9%BE%E5%88%B0",
            "img_url": "https://p11-sign.douyinpic.com/tos-cn-p-0015c000-ce/oogZHIMeUJUBz89ZAGDfiE3jLDwIQQe7bBxiMA~noop.jpeg?lk3s=bfd515bb&x-expires=1783036800&x-signature=AGDty4hbcHFoxdYiNCJBVRO2A2w%3D&from=3218412987",
            "push_time": "2026-07-02 21:47:38",
            "now_time": "2026-07-03",
            "type": "热搜",
            "source": "抖音"
        },
        {
            "index": 24,
            "title": "天黑不睡觉天亮还在熬",
            "hot": 7719785,
            "url": "https://www.douyin.com/search/%E5%A4%A9%E9%BB%91%E4%B8%8D%E7%9D%A1%E8%A7%89%E5%A4%A9%E4%BA%AE%E8%BF%98%E5%9C%A8%E7%86%AC",
            "img_url": "https://p26-sign.douyinpic.com/tos-cn-i-0813c000-ce/oQrqJ3AqEihgVMAEkh1AEBNEIInMexAfwAPiBe~noop.jpeg?lk3s=bfd515bb&x-expires=1783036800&x-signature=3yydiZxg9hDKWwDbYD2dIhPqSec%3D&from=3218412987",
            "push_time": "2026-07-02 16:30:51",
            "now_time": "2026-07-03",
            "type": "热搜",
            "source": "抖音"
        },
        {
            "index": 25,
            "title": "徐良伴舞小哥终于更新了",
            "hot": 7719269,
            "url": "https://www.douyin.com/search/%E5%BE%90%E8%89%AF%E4%BC%B4%E8%88%9E%E5%B0%8F%E5%93%A5%E7%BB%88%E4%BA%8E%E6%9B%B4%E6%96%B0%E4%BA%86",
            "img_url": "https://p3-sign.douyinpic.com/tos-cn-p-0015/ogAtBBuUaENCE7ZQTuLfCF6iaD0ekfI2hkQv5A~noop.jpeg?lk3s=bfd515bb&x-expires=1783036800&x-signature=HD2NnwzM8s4xO%2BXt6CYDN%2FecXtU%3D&from=3218412987",
            "push_time": "2026-07-02 15:36:30",
            "now_time": "2026-07-03",
            "type": "热搜",
            "source": "抖音"
        },
        {
            "index": 26,
            "title": "哈兰德破纪录后发了5条抖音",
            "hot": 7713463,
            "url": "https://www.douyin.com/search/%E5%93%88%E5%85%B0%E5%BE%B7%E7%A0%B4%E7%BA%AA%E5%BD%95%E5%90%8E%E5%8F%91%E4%BA%865%E6%9D%A1%E6%8A%96%E9%9F%B3",
            "img_url": "https://p5-ex-gddgtc-sign.douyinpic.com/tos-cn-i-0813c000-ce/osHAAiKBwOACQeOiPA1eEAAyEdEzmIIGgYDBFo~noop.jpeg?lk3s=bfd515bb&x-expires=1783036800&x-signature=PC%2FnOzMyVebDTkugnAhS%2F1ZLboI%3D&from=3218412987",
            "push_time": "2026-07-02 21:16:33",
            "now_time": "2026-07-03",
            "type": "热搜",
            "source": "抖音"
        },
        {
            "index": 27,
            "title": "异环真红",
            "hot": 7713156,
            "url": "https://www.douyin.com/search/%E5%BC%82%E7%8E%AF%E7%9C%9F%E7%BA%A2",
            "img_url": "https://p26-sign.douyinpic.com/tos-cn-p-0015/os3EAgfDDQyP9AqAlwfESRVOJBZAdEDgFC6CQg~noop.jpeg?lk3s=bfd515bb&x-expires=1783036800&x-signature=lF63M6zy0IpFSJ7%2F9KHnJWf25Mo%3D&from=3218412987",
            "push_time": "2026-07-02 11:07:45",
            "now_time": "2026-07-03",
            "type": "热搜",
            "source": "抖音"
        },
        {
            "index": 28,
            "title": "动画电影去你的岛定档",
            "hot": 7708253,
            "url": "https://www.douyin.com/search/%E5%8A%A8%E7%94%BB%E7%94%B5%E5%BD%B1%E5%8E%BB%E4%BD%A0%E7%9A%84%E5%B2%9B%E5%AE%9A%E6%A1%A3",
            "img_url": "https://p26-sign.douyinpic.com/tos-cn-p-0015/oo1EBjJNILAbBiBAI7tGa5ML4fxFxfUFIB8eCr~noop.jpeg?lk3s=bfd515bb&x-expires=1783036800&x-signature=ewkdvaMhGo9Vy4rNrDrcf6Spne8%3D&from=3218412987",
            "push_time": "2026-07-02 11:02:37",
            "now_time": "2026-07-03",
            "type": "热搜",
            "source": "抖音"
        },
        {
            "index": 29,
            "title": "野狗骨头定档",
            "hot": 7705262,
            "url": "https://www.douyin.com/search/%E9%87%8E%E7%8B%97%E9%AA%A8%E5%A4%B4%E5%AE%9A%E6%A1%A3",
            "img_url": "https://p9-sign.douyinpic.com/tos-cn-i-dy/2bd0b5e090454e7d8c6e9cd6d0a3ccfe~noop.jpeg?lk3s=bfd515bb&x-expires=1783036800&x-signature=UpY9n3XOvU1f4GGUPm3qWQpUWFE%3D&from=3218412987",
            "push_time": "2026-07-02 20:57:00",
            "now_time": "2026-07-03",
            "type": "热搜",
            "source": "抖音"
        },
        {
            "index": 30,
            "title": "我已加入松弛派对",
            "hot": 7703105,
            "url": "https://www.douyin.com/search/%E6%88%91%E5%B7%B2%E5%8A%A0%E5%85%A5%E6%9D%BE%E5%BC%9B%E6%B4%BE%E5%AF%B9",
            "img_url": "https://p5-ex-gddgtc-sign.douyinpic.com/tos-cn-i-0813/owtvFABquNAAAiI1BIiPACgtr3GAe6EgeAB4A8~noop.jpeg?lk3s=bfd515bb&x-expires=1783036800&x-signature=%2FJT95x2LqNphk6tDzUCxn5NC8wM%3D&from=3218412987",
            "push_time": "2026-07-02 21:04:55",
            "now_time": "2026-07-03",
            "type": "热搜",
            "source": "抖音"
        },
        {
            "index": 31,
            "title": "被百厨大战安利了煎蟹",
            "hot": 7702566,
            "url": "https://www.douyin.com/search/%E8%A2%AB%E7%99%BE%E5%8E%A8%E5%A4%A7%E6%88%98%E5%AE%89%E5%88%A9%E4%BA%86%E7%85%8E%E8%9F%B9",
            "img_url": "https://p11-sign.douyinpic.com/tos-cn-p-0015c000-ce/oMtOBiB2ZEMkxpwKtIvApzbCskrwEAWiPiaTH~noop.jpeg?lk3s=bfd515bb&x-expires=1783036800&x-signature=r6dqoTjZWqUVgxd5uqDfM36A7fk%3D&from=3218412987",
            "push_time": "2026-07-02 16:49:39",
            "now_time": "2026-07-03",
            "type": "热搜",
            "source": "抖音"
        },
        {
            "index": 32,
            "title": "2026王者之战",
            "hot": 7702316,
            "url": "https://www.douyin.com/search/2026%E7%8E%8B%E8%80%85%E4%B9%8B%E6%88%98",
            "img_url": "https://p3-sign.douyinpic.com/tos-cn-i-dy/3b7b3f7bfeb247b4811c8fac693b22c0~noop.jpeg?lk3s=bfd515bb&x-expires=1783036800&x-signature=hGdnNH3%2BLIu%2Fhd%2BTpwJzUNxsr0w%3D&from=3218412987",
            "push_time": "2026-07-02 16:32:45",
            "now_time": "2026-07-03",
            "type": "热搜",
            "source": "抖音"
        },
        {
            "index": 33,
            "title": "当你觉得身边的人没品味时",
            "hot": 7690166,
            "url": "https://www.douyin.com/search/%E5%BD%93%E4%BD%A0%E8%A7%89%E5%BE%97%E8%BA%AB%E8%BE%B9%E7%9A%84%E4%BA%BA%E6%B2%A1%E5%93%81%E5%91%B3%E6%97%B6",
            "img_url": "https://p5-ex-gddgtc-sign.douyinpic.com/tos-cn-p-0015/oEevQUD9HAOMzxDmAVgFdPJqQfkXqCEBwGgh5A~noop.jpeg?lk3s=bfd515bb&x-expires=1783036800&x-signature=2q7pit8np6CPdTIvTGumQA2gu1w%3D&from=3218412987",
            "push_time": "2026-07-02 21:43:55",
            "now_time": "2026-07-03",
            "type": "热搜",
            "source": "抖音"
        },
        {
            "index": 34,
            "title": "妙脆角给小猫种好了不用谢",
            "hot": 7683553,
            "url": "https://www.douyin.com/search/%E5%A6%99%E8%84%86%E8%A7%92%E7%BB%99%E5%B0%8F%E7%8C%AB%E7%A7%8D%E5%A5%BD%E4%BA%86%E4%B8%8D%E7%94%A8%E8%B0%A2",
            "img_url": "https://p11-sign.douyinpic.com/tos-cn-p-0015c000-ce/owFAqfSFSwr9DtoQCSmEAXBnIERFIkw0qxBSfp~noop.jpeg?lk3s=bfd515bb&x-expires=1783036800&x-signature=Nc68ELNBlRB%2FpBcwY2vOPtff9Ng%3D&from=3218412987",
            "push_time": "2026-07-02 14:19:11",
            "now_time": "2026-07-03",
            "type": "热搜",
            "source": "抖音"
        },
        {
            "index": 35,
            "title": "在毕业致辞中感受语言的力量",
            "hot": 7683103,
            "url": "https://www.douyin.com/search/%E5%9C%A8%E6%AF%95%E4%B8%9A%E8%87%B4%E8%BE%9E%E4%B8%AD%E6%84%9F%E5%8F%97%E8%AF%AD%E8%A8%80%E7%9A%84%E5%8A%9B%E9%87%8F",
            "img_url": "https://p5-ex-gddgtc-sign.douyinpic.com/tos-cn-i-0813c000-ce/oQBiyWbcEF7AoXICkGmBfE5ezkAiAAywAcB1IU~noop.jpeg?lk3s=bfd515bb&x-expires=1783036800&x-signature=OHEvRjS0U2%2BDAIIskX%2BSjFuKyxw%3D&from=3218412987",
            "push_time": "2026-07-02 20:52:47",
            "now_time": "2026-07-03",
            "type": "热搜",
            "source": "抖音"
        },
        {
            "index": 36,
            "title": "唇印四宫格美得太犯规",
            "hot": 7676496,
            "url": "https://www.douyin.com/search/%E5%94%87%E5%8D%B0%E5%9B%9B%E5%AE%AB%E6%A0%BC%E7%BE%8E%E5%BE%97%E5%A4%AA%E7%8A%AF%E8%A7%84",
            "img_url": "https://p9-sign.douyinpic.com/tos-cn-p-0015c000-ce/oseUDHlXEhZF4a3AxgeIhAkA7xVIDJC0BfXQJQ~noop.jpeg?lk3s=bfd515bb&x-expires=1783036800&x-signature=cudhKEJklN5KE83GPRIjfNnJcPg%3D&from=3218412987",
            "push_time": "2026-07-02 12:52:29",
            "now_time": "2026-07-03",
            "type": "热搜",
            "source": "抖音"
        },
        {
            "index": 37,
            "title": "当我看到比利时绝境逆转",
            "hot": 7671037,
            "url": "https://www.douyin.com/search/%E5%BD%93%E6%88%91%E7%9C%8B%E5%88%B0%E6%AF%94%E5%88%A9%E6%97%B6%E7%BB%9D%E5%A2%83%E9%80%86%E8%BD%AC",
            "img_url": "https://p26-sign.douyinpic.com/tos-cn-p-0015/o8BJAQjRuFCpZAaNQqEDxKfGQ76fgBb3ANLIc9~noop.jpeg?lk3s=bfd515bb&x-expires=1783036800&x-signature=aXbMJUw8jLtnWrXS5XJzqL7XNTk%3D&from=3218412987",
            "push_time": "2026-07-02 08:55:27",
            "now_time": "2026-07-03",
            "type": "热搜",
            "source": "抖音"
        },
        {
            "index": 38,
            "title": "王楚钦孙颖莎逆转进四强",
            "hot": 7670139,
            "url": "https://www.douyin.com/search/%E7%8E%8B%E6%A5%9A%E9%92%A6%E5%AD%99%E9%A2%96%E8%8E%8E%E9%80%86%E8%BD%AC%E8%BF%9B%E5%9B%9B%E5%BC%BA",
            "img_url": "https://p26-sign.douyinpic.com/tos-cn-p-0015/oMdqNapbPAVoF9NfgQFMRNCDufVIPQZEAABiLQ~noop.jpeg?lk3s=bfd515bb&x-expires=1783036800&x-signature=EDfhSjdiIY1PCeipk8o3Jdh52GM%3D&from=3218412987",
            "push_time": "2026-07-02 07:05:54",
            "now_time": "2026-07-03",
            "type": "热搜",
            "source": "抖音"
        },
        {
            "index": 39,
            "title": "在喜欢你6里看到社交入侵",
            "hot": 7668478,
            "url": "https://www.douyin.com/search/%E5%9C%A8%E5%96%9C%E6%AC%A2%E4%BD%A06%E9%87%8C%E7%9C%8B%E5%88%B0%E7%A4%BE%E4%BA%A4%E5%85%A5%E4%BE%B5",
            "img_url": "https://p3-sign.douyinpic.com/tos-cn-p-0015/ocgEMsgQEZDAQDZFlfBhCqrdvPxA9ACmIas3fX~noop.jpeg?lk3s=bfd515bb&x-expires=1783036800&x-signature=oyEjHjTYjuHSFaS048puGFwOoYY%3D&from=3218412987",
            "push_time": "2026-07-02 07:01:01",
            "now_time": "2026-07-03",
            "type": "热搜",
            "source": "抖音"
        },
        {
            "index": 40,
            "title": "用早茶晚酒支持你的主队",
            "hot": 7668324,
            "url": "https://www.douyin.com/search/%E7%94%A8%E6%97%A9%E8%8C%B6%E6%99%9A%E9%85%92%E6%94%AF%E6%8C%81%E4%BD%A0%E7%9A%84%E4%B8%BB%E9%98%9F",
            "img_url": "https://p26-sign.douyinpic.com/tos-cn-p-0015/o4fbIiVNPBAFYhwQIQxx64AaK0KgyqEFDA9eEZ~noop.jpeg?lk3s=bfd515bb&x-expires=1783036800&x-signature=nqPGi%2FKdGjKlzXrdci7ORIt6pio%3D&from=3218412987",
            "push_time": "2026-07-02 14:54:56",
            "now_time": "2026-07-03",
            "type": "热搜",
            "source": "抖音"
        },
        {
            "index": 41,
            "title": "下半年也要去看更美的风景",
            "hot": 7665032,
            "url": "https://www.douyin.com/search/%E4%B8%8B%E5%8D%8A%E5%B9%B4%E4%B9%9F%E8%A6%81%E5%8E%BB%E7%9C%8B%E6%9B%B4%E7%BE%8E%E7%9A%84%E9%A3%8E%E6%99%AF",
            "img_url": "https://p3-sign.douyinpic.com/tos-cn-p-0015/oIA6EMPFI7PBIAXklvQa0Id0ikDM9ii9NwzQV~noop.jpeg?lk3s=bfd515bb&x-expires=1783036800&x-signature=IEEn7MXF6WWm7HmiTSGlILTa5D8%3D&from=3218412987",
            "push_time": "2026-07-01 15:31:10",
            "now_time": "2026-07-03",
            "type": "热搜",
            "source": "抖音"
        },
        {
            "index": 42,
            "title": "V8和CORTIS一起鬼步舞",
            "hot": 7664295,
            "url": "https://www.douyin.com/search/V8%E5%92%8CCORTIS%E4%B8%80%E8%B5%B7%E9%AC%BC%E6%AD%A5%E8%88%9E",
            "img_url": "https://p11-sign.douyinpic.com/tos-cn-p-0015/oggLTElaqAxfpN8xADBAyRuRFDMINQf9qAZhMY~noop.jpeg?lk3s=bfd515bb&x-expires=1783036800&x-signature=F662WPygz2na0Tl92m7rXbnCXXs%3D&from=3218412987",
            "push_time": "2026-07-02 20:32:16",
            "now_time": "2026-07-03",
            "type": "热搜",
            "source": "抖音"
        },
        {
            "index": 43,
            "title": "吃桃子也有南北差异吗",
            "hot": 7662228,
            "url": "https://www.douyin.com/search/%E5%90%83%E6%A1%83%E5%AD%90%E4%B9%9F%E6%9C%89%E5%8D%97%E5%8C%97%E5%B7%AE%E5%BC%82%E5%90%97",
            "img_url": "https://p11-sign.douyinpic.com/tos-cn-p-0015c000-ce/okBa3dBPNY4OdvUE1CiiJgDaHEIyPCkABAMpu~noop.jpeg?lk3s=bfd515bb&x-expires=1783036800&x-signature=HT2d8YUi3v6qqKdt2abXINXPPJw%3D&from=3218412987",
            "push_time": "2026-07-01 17:08:52",
            "now_time": "2026-07-03",
            "type": "热搜",
            "source": "抖音"
        },
        {
            "index": 44,
            "title": "你说我变了反差转场",
            "hot": 7656627,
            "url": "https://www.douyin.com/search/%E4%BD%A0%E8%AF%B4%E6%88%91%E5%8F%98%E4%BA%86%E5%8F%8D%E5%B7%AE%E8%BD%AC%E5%9C%BA",
            "img_url": "https://p3-sign.douyinpic.com/tos-cn-p-0015c000-ce/o0U88XHjPCuI4AL7vJ1Qv6eCMhBtgNeiiLgGIe~noop.jpeg?lk3s=bfd515bb&x-expires=1783036800&x-signature=HQzp8mqLQur3UlEVMUM%2BiYi2Efo%3D&from=3218412987",
            "push_time": "2026-07-01 14:32:01",
            "now_time": "2026-07-03",
            "type": "热搜",
            "source": "抖音"
        },
        {
            "index": 45,
            "title": "晒出我的面试穿搭",
            "hot": 7655923,
            "url": "https://www.douyin.com/search/%E6%99%92%E5%87%BA%E6%88%91%E7%9A%84%E9%9D%A2%E8%AF%95%E7%A9%BF%E6%90%AD",
            "img_url": "https://p3-sign.douyinpic.com/tos-cn-p-0015c000-ce/oUeN6NMJTUq0QgIaPD5LeBfGCQaETQ7NxK8ADJ~noop.jpeg?lk3s=bfd515bb&x-expires=1783036800&x-signature=AQMcsUAM9ctzd3yjUztuwxMxrRs%3D&from=3218412987",
            "push_time": "2026-07-01 10:55:00",
            "now_time": "2026-07-03",
            "type": "热搜",
            "source": "抖音"
        },
        {
            "index": 46,
            "title": "地瓜炉变身全能烧烤炉",
            "hot": 7652975,
            "url": "https://www.douyin.com/search/%E5%9C%B0%E7%93%9C%E7%82%89%E5%8F%98%E8%BA%AB%E5%85%A8%E8%83%BD%E7%83%A7%E7%83%A4%E7%82%89",
            "img_url": "https://p3-sign.douyinpic.com/tos-cn-p-0015c000-ce/oUFjVeJqQA7CEZVFEoo859yCevDfQIhmAOcwID~noop.jpeg?lk3s=bfd515bb&x-expires=1783036800&x-signature=GM40tA0skmqcvYz%2BkDjR6pQ2L20%3D&from=3218412987",
            "push_time": "2026-07-01 09:36:29",
            "now_time": "2026-07-03",
            "type": "热搜",
            "source": "抖音"
        },
        {
            "index": 47,
            "title": "魏子宸单人cha",
            "hot": 7652265,
            "url": "https://www.douyin.com/search/%E9%AD%8F%E5%AD%90%E5%AE%B8%E5%8D%95%E4%BA%BAcha",
            "img_url": "https://p26-sign.douyinpic.com/tos-cn-p-0015c000-ce/oYJDffDFwAh2DKcIJ7jEAeGcETFFIrjopHeMNR~noop.jpeg?lk3s=bfd515bb&x-expires=1783036800&x-signature=Qx1Rh7oTNSkZIR96%2BgP24F5Pr84%3D&from=3218412987",
            "push_time": "2026-07-01 22:03:39",
            "now_time": "2026-07-03",
            "type": "热搜",
            "source": "抖音"
        },
        {
            "index": 48,
            "title": "我是姆巴佩中国分佩",
            "hot": 7648937,
            "url": "https://www.douyin.com/search/%E6%88%91%E6%98%AF%E5%A7%86%E5%B7%B4%E4%BD%A9%E4%B8%AD%E5%9B%BD%E5%88%86%E4%BD%A9",
            "img_url": "https://p26-sign.douyinpic.com/tos-cn-p-0015c000-ce/oIpDedWN1EeuAvExrCIizNdiIdBE9QAUswfdvv~noop.jpeg?lk3s=bfd515bb&x-expires=1783036800&x-signature=2XXwwRoPSkfm1%2BK9SPrkseAVakk%3D&from=3218412987",
            "push_time": "2026-07-01 14:36:08",
            "now_time": "2026-07-03",
            "type": "热搜",
            "source": "抖音"
        },
        {
            "index": 49,
            "title": "豪门顶美千金脸有画面了",
            "hot": 7648913,
            "url": "https://www.douyin.com/search/%E8%B1%AA%E9%97%A8%E9%A1%B6%E7%BE%8E%E5%8D%83%E9%87%91%E8%84%B8%E6%9C%89%E7%94%BB%E9%9D%A2%E4%BA%86",
            "img_url": "https://p3-sign.douyinpic.com/tos-cn-p-0015/osofzpDtgQrEEVQDQB7eFCAeE2LJ6IeqVATGRI~noop.jpeg?lk3s=bfd515bb&x-expires=1783036800&x-signature=%2BcZh5TVLfTLmuut7NyLekT3y004%3D&from=3218412987",
            "push_time": "2026-07-01 11:20:17",
            "now_time": "2026-07-03",
            "type": "热搜",
            "source": "抖音"
        },
        {
            "index": 50,
            "title": "董浩叔叔：叛逆染发活出真自我",
            "hot": 7647424,
            "url": "https://www.douyin.com/search/%E8%91%A3%E6%B5%A9%E5%8F%94%E5%8F%94%EF%BC%9A%E5%8F%9B%E9%80%86%E6%9F%93%E5%8F%91%E6%B4%BB%E5%87%BA%E7%9C%9F%E8%87%AA%E6%88%91",
            "img_url": "https://p5-ex-gddgtc-sign.douyinpic.com/tos-cn-p-0015/o865CfVlBA11iNdAEGiJxuIGIBNI1Hxg61erHA~noop.jpeg?lk3s=bfd515bb&x-expires=1783036800&x-signature=nlGasz462xnTBDzh69k9dfXgofw%3D&from=3218412987",
            "push_time": "2026-07-02 20:51:07",
            "now_time": "2026-07-03",
            "type": "热搜",
            "source": "抖音"
        }
    ]
}