{
    "2025-02-28 00:18:46": {
        "searches": [
            {
                "index": 1,
                "category": "电影",
                "title": "哪吒2配音演员起诉配音公司",
                "hot": 1788319,
                "url": "https://s.weibo.com/weibo?q=%E5%93%AA%E5%90%922%E9%85%8D%E9%9F%B3%E6%BC%94%E5%91%98%E8%B5%B7%E8%AF%89%E9%85%8D%E9%9F%B3%E5%85%AC%E5%8F%B8&Refer=index",
                "type": "Weibo",
                "datetime": "2025-02-28 00:18:46"
            },
            {
                "index": 2,
                "category": "汽车",
                "title": "小米SU7Ultra",
                "hot": 678174,
                "url": "https://s.weibo.com/weibo?q=%E5%B0%8F%E7%B1%B3SU7Ultra&Refer=index",
                "type": "Weibo",
                "datetime": "2025-02-28 00:18:46"
            },
            {
                "index": 3,
                "category": "正能量",
                "title": "看AI如何助力春耕育种",
                "hot": 40640,
                "url": "https://s.weibo.com/weibo?q=%E7%9C%8BAI%E5%A6%82%E4%BD%95%E5%8A%A9%E5%8A%9B%E6%98%A5%E8%80%95%E8%82%B2%E7%A7%8D&Refer=index",
                "type": "Weibo",
                "datetime": "2025-02-28 00:18:46"
            },
            {
                "index": 4,
                "category": "动漫,作品衍生",
                "title": "小猪佩奇猪妈妈怀三胎",
                "hot": 466696,
                "url": "https://s.weibo.com/weibo?q=%E5%B0%8F%E7%8C%AA%E4%BD%A9%E5%A5%87%E7%8C%AA%E5%A6%88%E5%A6%88%E6%80%80%E4%B8%89%E8%83%8E&Refer=index",
                "type": "Weibo",
                "datetime": "2025-02-28 00:18:46"
            },
            {
                "index": 5,
                "category": "汽车",
                "title": "小米SU7Ultra定价52.99万元",
                "hot": 463564,
                "url": "https://s.weibo.com/weibo?q=%E5%B0%8F%E7%B1%B3SU7Ultra%E5%AE%9A%E4%BB%B752.99%E4%B8%87%E5%85%83&Refer=index",
                "type": "Weibo",
                "datetime": "2025-02-28 00:18:46"
            },
            {
                "index": 6,
                "category": "民生新闻",
                "title": "建议春节假期取消调休",
                "hot": 326795,
                "url": "https://s.weibo.com/weibo?q=%E5%BB%BA%E8%AE%AE%E6%98%A5%E8%8A%82%E5%81%87%E6%9C%9F%E5%8F%96%E6%B6%88%E8%B0%83%E4%BC%91&Refer=index",
                "type": "Weibo",
                "datetime": "2025-02-28 00:18:46"
            },
            {
                "index": 7,
                "category": "艺人",
                "title": "前TVB甜妹唐宁回应满头白发",
                "hot": 407900,
                "url": "https://s.weibo.com/weibo?q=%E5%89%8DTVB%E7%94%9C%E5%A6%B9%E5%94%90%E5%AE%81%E5%9B%9E%E5%BA%94%E6%BB%A1%E5%A4%B4%E7%99%BD%E5%8F%91&Refer=index",
                "type": "Weibo",
                "datetime": "2025-02-28 00:18:46"
            },
            {
                "index": 8,
                "category": "汽车,互联网",
                "title": "雷军夸保时捷",
                "hot": 357185,
                "url": "https://s.weibo.com/weibo?q=%E9%9B%B7%E5%86%9B%E5%A4%B8%E4%BF%9D%E6%97%B6%E6%8D%B7&Refer=index",
                "type": "Weibo",
                "datetime": "2025-02-28 00:18:46"
            },
            {
                "index": 9,
                "category": "数码,汽车",
                "title": "小米15Ultra及SU7Ultra今日发布",
                "hot": 265476,
                "url": "https://s.weibo.com/weibo?q=%E5%B0%8F%E7%B1%B315Ultra%E5%8F%8ASU7Ultra%E4%BB%8A%E6%97%A5%E5%8F%91%E5%B8%83&Refer=index",
                "type": "Weibo",
                "datetime": "2025-02-28 00:18:46"
            },
            {
                "index": 10,
                "category": "民生新闻",
                "title": "零食鲍菇螺肉主配料为福寿螺肉",
                "hot": 102023,
                "url": "https://s.weibo.com/weibo?q=%E9%9B%B6%E9%A3%9F%E9%B2%8D%E8%8F%87%E8%9E%BA%E8%82%89%E4%B8%BB%E9%85%8D%E6%96%99%E4%B8%BA%E7%A6%8F%E5%AF%BF%E8%9E%BA%E8%82%89&Refer=index",
                "type": "Weibo",
                "datetime": "2025-02-28 00:18:46"
            },
            {
                "index": 11,
                "category": "民生新闻",
                "title": "接吻超58小时破纪录夫妇宣布分手",
                "hot": 647467,
                "url": "https://s.weibo.com/weibo?q=%E6%8E%A5%E5%90%BB%E8%B6%8558%E5%B0%8F%E6%97%B6%E7%A0%B4%E7%BA%AA%E5%BD%95%E5%A4%AB%E5%A6%87%E5%AE%A3%E5%B8%83%E5%88%86%E6%89%8B&Refer=index",
                "type": "Weibo",
                "datetime": "2025-02-28 00:18:46"
            },
            {
                "index": 12,
                "category": "网红",
                "title": "sk卡卡",
                "hot": 542581,
                "url": "https://s.weibo.com/weibo?q=sk%E5%8D%A1%E5%8D%A1&Refer=index",
                "type": "Weibo",
                "datetime": "2025-02-28 00:18:46"
            },
            {
                "index": 13,
                "category": "艺人",
                "title": "薛小婉怒斥韩安冉",
                "hot": 373154,
                "url": "https://s.weibo.com/weibo?q=%E8%96%9B%E5%B0%8F%E5%A9%89%E6%80%92%E6%96%A5%E9%9F%A9%E5%AE%89%E5%86%89&Refer=index",
                "type": "Weibo",
                "datetime": "2025-02-28 00:18:46"
            },
            {
                "index": 14,
                "category": "情感",
                "title": "香港丁克夫妻29平的房怎么住",
                "hot": 353112,
                "url": "https://s.weibo.com/weibo?q=%E9%A6%99%E6%B8%AF%E4%B8%81%E5%85%8B%E5%A4%AB%E5%A6%BB29%E5%B9%B3%E7%9A%84%E6%88%BF%E6%80%8E%E4%B9%88%E4%BD%8F&Refer=index",
                "type": "Weibo",
                "datetime": "2025-02-28 00:18:46"
            },
            {
                "index": 15,
                "category": "艺人",
                "title": "李维嘉这辈子有为王栎鑫拼过命",
                "hot": 352355,
                "url": "https://s.weibo.com/weibo?q=%E6%9D%8E%E7%BB%B4%E5%98%89%E8%BF%99%E8%BE%88%E5%AD%90%E6%9C%89%E4%B8%BA%E7%8E%8B%E6%A0%8E%E9%91%AB%E6%8B%BC%E8%BF%87%E5%91%BD&Refer=index",
                "type": "Weibo",
                "datetime": "2025-02-28 00:18:46"
            },
            {
                "index": 16,
                "category": "民生新闻",
                "title": "女子嫌金价太高在家自制金戒指",
                "hot": 237157,
                "url": "https://s.weibo.com/weibo?q=%E5%A5%B3%E5%AD%90%E5%AB%8C%E9%87%91%E4%BB%B7%E5%A4%AA%E9%AB%98%E5%9C%A8%E5%AE%B6%E8%87%AA%E5%88%B6%E9%87%91%E6%88%92%E6%8C%87&Refer=index",
                "type": "Weibo",
                "datetime": "2025-02-28 00:18:46"
            },
            {
                "index": 17,
                "category": "海外新闻",
                "title": "美国民众称特朗普卖金卡是笑话",
                "hot": 187749,
                "url": "https://s.weibo.com/weibo?q=%E7%BE%8E%E5%9B%BD%E6%B0%91%E4%BC%97%E7%A7%B0%E7%89%B9%E6%9C%97%E6%99%AE%E5%8D%96%E9%87%91%E5%8D%A1%E6%98%AF%E7%AC%91%E8%AF%9D&Refer=index",
                "type": "Weibo",
                "datetime": "2025-02-28 00:18:46"
            },
            {
                "index": 18,
                "category": "电影",
                "title": "哪吒2票房已破140亿",
                "hot": 176526,
                "url": "https://s.weibo.com/weibo?q=%E5%93%AA%E5%90%922%E7%A5%A8%E6%88%BF%E5%B7%B2%E7%A0%B4140%E4%BA%BF&Refer=index",
                "type": "Weibo",
                "datetime": "2025-02-28 00:18:46"
            },
            {
                "index": 19,
                "category": "作品衍生,时尚",
                "title": "孟子义米兰时装周出发啦",
                "hot": 169806,
                "url": "https://s.weibo.com/weibo?q=%E5%AD%9F%E5%AD%90%E4%B9%89%E7%B1%B3%E5%85%B0%E6%97%B6%E8%A3%85%E5%91%A8%E5%87%BA%E5%8F%91%E5%95%A6&Refer=index",
                "type": "Weibo",
                "datetime": "2025-02-28 00:18:46"
            },
            {
                "index": 20,
                "category": "作品衍生,时尚",
                "title": "陈昊宇米兰首秀g社生图",
                "hot": 163311,
                "url": "https://s.weibo.com/weibo?q=%E9%99%88%E6%98%8A%E5%AE%87%E7%B1%B3%E5%85%B0%E9%A6%96%E7%A7%80g%E7%A4%BE%E7%94%9F%E5%9B%BE&Refer=index",
                "type": "Weibo",
                "datetime": "2025-02-28 00:18:46"
            },
            {
                "index": 21,
                "category": "艺人",
                "title": "偶遇靳东以为是公司领导",
                "hot": 167692,
                "url": "https://s.weibo.com/weibo?q=%E5%81%B6%E9%81%87%E9%9D%B3%E4%B8%9C%E4%BB%A5%E4%B8%BA%E6%98%AF%E5%85%AC%E5%8F%B8%E9%A2%86%E5%AF%BC&Refer=index",
                "type": "Weibo",
                "datetime": "2025-02-28 00:18:46"
            },
            {
                "index": 22,
                "category": "民生新闻",
                "title": "老人退休金9000多元家中却垃圾成山",
                "hot": 167179,
                "url": "https://s.weibo.com/weibo?q=%E8%80%81%E4%BA%BA%E9%80%80%E4%BC%91%E9%87%919000%E5%A4%9A%E5%85%83%E5%AE%B6%E4%B8%AD%E5%8D%B4%E5%9E%83%E5%9C%BE%E6%88%90%E5%B1%B1&Refer=index",
                "type": "Weibo",
                "datetime": "2025-02-28 00:18:46"
            },
            {
                "index": 23,
                "category": "艺人",
                "title": "章若楠追星周杰伦成功",
                "hot": 150903,
                "url": "https://s.weibo.com/weibo?q=%E7%AB%A0%E8%8B%A5%E6%A5%A0%E8%BF%BD%E6%98%9F%E5%91%A8%E6%9D%B0%E4%BC%A6%E6%88%90%E5%8A%9F&Refer=index",
                "type": "Weibo",
                "datetime": "2025-02-28 00:18:46"
            },
            {
                "index": 24,
                "category": "民生新闻",
                "title": "厂家回应零食主配料为福寿螺肉",
                "hot": 148660,
                "url": "https://s.weibo.com/weibo?q=%E5%8E%82%E5%AE%B6%E5%9B%9E%E5%BA%94%E9%9B%B6%E9%A3%9F%E4%B8%BB%E9%85%8D%E6%96%99%E4%B8%BA%E7%A6%8F%E5%AF%BF%E8%9E%BA%E8%82%89&Refer=index",
                "type": "Weibo",
                "datetime": "2025-02-28 00:18:46"
            },
            {
                "index": 25,
                "category": "游戏",
                "title": "宝可梦手游新作",
                "hot": 100633,
                "url": "https://s.weibo.com/weibo?q=%E5%AE%9D%E5%8F%AF%E6%A2%A6%E6%89%8B%E6%B8%B8%E6%96%B0%E4%BD%9C&Refer=index",
                "type": "Weibo",
                "datetime": "2025-02-28 00:18:46"
            },
            {
                "index": 26,
                "category": "网红",
                "title": "方媛感受到了祖国的温暖",
                "hot": 142244,
                "url": "https://s.weibo.com/weibo?q=%E6%96%B9%E5%AA%9B%E6%84%9F%E5%8F%97%E5%88%B0%E4%BA%86%E7%A5%96%E5%9B%BD%E7%9A%84%E6%B8%A9%E6%9A%96&Refer=index",
                "type": "Weibo",
                "datetime": "2025-02-28 00:18:46"
            },
            {
                "index": 27,
                "category": "艺人",
                "title": "韩佳人自曝曾一年内流产三次",
                "hot": 133596,
                "url": "https://s.weibo.com/weibo?q=%E9%9F%A9%E4%BD%B3%E4%BA%BA%E8%87%AA%E6%9B%9D%E6%9B%BE%E4%B8%80%E5%B9%B4%E5%86%85%E6%B5%81%E4%BA%A7%E4%B8%89%E6%AC%A1&Refer=index",
                "type": "Weibo",
                "datetime": "2025-02-28 00:18:46"
            },
            {
                "index": 28,
                "category": "综艺",
                "title": "翟潇闻创2的含金量还在上升",
                "hot": 125676,
                "url": "https://s.weibo.com/weibo?q=%E7%BF%9F%E6%BD%87%E9%97%BB%E5%88%9B2%E7%9A%84%E5%90%AB%E9%87%91%E9%87%8F%E8%BF%98%E5%9C%A8%E4%B8%8A%E5%8D%87&Refer=index",
                "type": "Weibo",
                "datetime": "2025-02-28 00:18:46"
            },
            {
                "index": 29,
                "category": "剧集",
                "title": "爱你",
                "hot": 115149,
                "url": "https://s.weibo.com/weibo?q=%E7%88%B1%E4%BD%A0&Refer=index",
                "type": "Weibo",
                "datetime": "2025-02-28 00:18:46"
            },
            {
                "index": 30,
                "category": "电影",
                "title": "哪吒炸出了多少民间高手",
                "hot": 99205,
                "url": "https://s.weibo.com/weibo?q=%E5%93%AA%E5%90%92%E7%82%B8%E5%87%BA%E4%BA%86%E5%A4%9A%E5%B0%91%E6%B0%91%E9%97%B4%E9%AB%98%E6%89%8B&Refer=index",
                "type": "Weibo",
                "datetime": "2025-02-28 00:18:46"
            },
            {
                "index": 31,
                "category": "民生新闻",
                "title": "我国古代已人手中国结",
                "hot": 132763,
                "url": "https://s.weibo.com/weibo?q=%E6%88%91%E5%9B%BD%E5%8F%A4%E4%BB%A3%E5%B7%B2%E4%BA%BA%E6%89%8B%E4%B8%AD%E5%9B%BD%E7%BB%93&Refer=index",
                "type": "Weibo",
                "datetime": "2025-02-28 00:18:46"
            },
            {
                "index": 32,
                "category": "作品衍生,时尚",
                "title": "柳智敏好美",
                "hot": 124502,
                "url": "https://s.weibo.com/weibo?q=%E6%9F%B3%E6%99%BA%E6%95%8F%E5%A5%BD%E7%BE%8E&Refer=index",
                "type": "Weibo",
                "datetime": "2025-02-28 00:18:46"
            },
            {
                "index": 33,
                "category": "民生新闻",
                "title": "婚房7年没住被小区保洁换锁养鸡",
                "hot": 119564,
                "url": "https://s.weibo.com/weibo?q=%E5%A9%9A%E6%88%BF7%E5%B9%B4%E6%B2%A1%E4%BD%8F%E8%A2%AB%E5%B0%8F%E5%8C%BA%E4%BF%9D%E6%B4%81%E6%8D%A2%E9%94%81%E5%85%BB%E9%B8%A1&Refer=index",
                "type": "Weibo",
                "datetime": "2025-02-28 00:18:46"
            },
            {
                "index": 34,
                "category": "动漫",
                "title": "鬼灭之刃变柱灭之刃",
                "hot": 118183,
                "url": "https://s.weibo.com/weibo?q=%E9%AC%BC%E7%81%AD%E4%B9%8B%E5%88%83%E5%8F%98%E6%9F%B1%E7%81%AD%E4%B9%8B%E5%88%83&Refer=index",
                "type": "Weibo",
                "datetime": "2025-02-28 00:18:46"
            },
            {
                "index": 35,
                "category": "数码",
                "title": "小米耳机",
                "hot": 109882,
                "url": "https://s.weibo.com/weibo?q=%E5%B0%8F%E7%B1%B3%E8%80%B3%E6%9C%BA&Refer=index",
                "type": "Weibo",
                "datetime": "2025-02-28 00:18:46"
            },
            {
                "index": 36,
                "category": "民生新闻",
                "title": "300元一张的始祖鸟吊牌到底谁在买",
                "hot": 105711,
                "url": "https://s.weibo.com/weibo?q=300%E5%85%83%E4%B8%80%E5%BC%A0%E7%9A%84%E5%A7%8B%E7%A5%96%E9%B8%9F%E5%90%8A%E7%89%8C%E5%88%B0%E5%BA%95%E8%B0%81%E5%9C%A8%E4%B9%B0&Refer=index",
                "type": "Weibo",
                "datetime": "2025-02-28 00:18:46"
            },
            {
                "index": 37,
                "category": "演出",
                "title": "周杰伦演唱会唱了难哄主题曲任性",
                "hot": 104102,
                "url": "https://s.weibo.com/weibo?q=%E5%91%A8%E6%9D%B0%E4%BC%A6%E6%BC%94%E5%94%B1%E4%BC%9A%E5%94%B1%E4%BA%86%E9%9A%BE%E5%93%84%E4%B8%BB%E9%A2%98%E6%9B%B2%E4%BB%BB%E6%80%A7&Refer=index",
                "type": "Weibo",
                "datetime": "2025-02-28 00:18:46"
            },
            {
                "index": 38,
                "category": "时尚",
                "title": "Prada大秀",
                "hot": 103740,
                "url": "https://s.weibo.com/weibo?q=Prada%E5%A4%A7%E7%A7%80&Refer=index",
                "type": "Weibo",
                "datetime": "2025-02-28 00:18:46"
            },
            {
                "index": 39,
                "category": "体育",
                "title": "樊振东可直接参加全运会决赛阶段单打比赛",
                "hot": 102070,
                "url": "https://s.weibo.com/weibo?q=%E6%A8%8A%E6%8C%AF%E4%B8%9C%E5%8F%AF%E7%9B%B4%E6%8E%A5%E5%8F%82%E5%8A%A0%E5%85%A8%E8%BF%90%E4%BC%9A%E5%86%B3%E8%B5%9B%E9%98%B6%E6%AE%B5%E5%8D%95%E6%89%93%E6%AF%94%E8%B5%9B&Refer=index",
                "type": "Weibo",
                "datetime": "2025-02-28 00:18:46"
            },
            {
                "index": 40,
                "category": "体育",
                "title": "卡卡我尽了一切努力挽救婚姻",
                "hot": 101103,
                "url": "https://s.weibo.com/weibo?q=%E5%8D%A1%E5%8D%A1%E6%88%91%E5%B0%BD%E4%BA%86%E4%B8%80%E5%88%87%E5%8A%AA%E5%8A%9B%E6%8C%BD%E6%95%91%E5%A9%9A%E5%A7%BB&Refer=index",
                "type": "Weibo",
                "datetime": "2025-02-28 00:18:46"
            },
            {
                "index": 41,
                "category": "民生新闻",
                "title": "长沙一32层居民楼承重墙被装修误拆",
                "hot": 92509,
                "url": "https://s.weibo.com/weibo?q=%E9%95%BF%E6%B2%99%E4%B8%8032%E5%B1%82%E5%B1%85%E6%B0%91%E6%A5%BC%E6%89%BF%E9%87%8D%E5%A2%99%E8%A2%AB%E8%A3%85%E4%BF%AE%E8%AF%AF%E6%8B%86&Refer=index",
                "type": "Weibo",
                "datetime": "2025-02-28 00:18:46"
            },
            {
                "index": 42,
                "category": "剧集",
                "title": "李嘉琦六姊妹杀青长文",
                "hot": 91773,
                "url": "https://s.weibo.com/weibo?q=%E6%9D%8E%E5%98%89%E7%90%A6%E5%85%AD%E5%A7%8A%E5%A6%B9%E6%9D%80%E9%9D%92%E9%95%BF%E6%96%87&Refer=index",
                "type": "Weibo",
                "datetime": "2025-02-28 00:18:46"
            },
            {
                "index": 43,
                "category": "教育",
                "title": "研招网回应考生伪造考研成绩",
                "hot": 91711,
                "url": "https://s.weibo.com/weibo?q=%E7%A0%94%E6%8B%9B%E7%BD%91%E5%9B%9E%E5%BA%94%E8%80%83%E7%94%9F%E4%BC%AA%E9%80%A0%E8%80%83%E7%A0%94%E6%88%90%E7%BB%A9&Refer=index",
                "type": "Weibo",
                "datetime": "2025-02-28 00:18:46"
            },
            {
                "index": 44,
                "category": "网红",
                "title": "周扬青自曝新恋情见光死",
                "hot": 90976,
                "url": "https://s.weibo.com/weibo?q=%E5%91%A8%E6%89%AC%E9%9D%92%E8%87%AA%E6%9B%9D%E6%96%B0%E6%81%8B%E6%83%85%E8%A7%81%E5%85%89%E6%AD%BB&Refer=index",
                "type": "Weibo",
                "datetime": "2025-02-28 00:18:46"
            },
            {
                "index": 45,
                "category": "艺人",
                "title": "赵露思新头像寓意",
                "hot": 87635,
                "url": "https://s.weibo.com/weibo?q=%E8%B5%B5%E9%9C%B2%E6%80%9D%E6%96%B0%E5%A4%B4%E5%83%8F%E5%AF%93%E6%84%8F&Refer=index",
                "type": "Weibo",
                "datetime": "2025-02-28 00:18:46"
            },
            {
                "index": 46,
                "category": "互联网,财经",
                "title": "雷军回应当首富",
                "hot": 85120,
                "url": "https://s.weibo.com/weibo?q=%E9%9B%B7%E5%86%9B%E5%9B%9E%E5%BA%94%E5%BD%93%E9%A6%96%E5%AF%8C&Refer=index",
                "type": "Weibo",
                "datetime": "2025-02-28 00:18:46"
            },
            {
                "index": 47,
                "category": "汽车,互联网",
                "title": "雷军喊话别抠镀金车标",
                "hot": 84994,
                "url": "https://s.weibo.com/weibo?q=%E9%9B%B7%E5%86%9B%E5%96%8A%E8%AF%9D%E5%88%AB%E6%8A%A0%E9%95%80%E9%87%91%E8%BD%A6%E6%A0%87&Refer=index",
                "type": "Weibo",
                "datetime": "2025-02-28 00:18:46"
            },
            {
                "index": 48,
                "category": "剧集",
                "title": "周雨彤回应辞职发疯戏",
                "hot": 78666,
                "url": "https://s.weibo.com/weibo?q=%E5%91%A8%E9%9B%A8%E5%BD%A4%E5%9B%9E%E5%BA%94%E8%BE%9E%E8%81%8C%E5%8F%91%E7%96%AF%E6%88%8F&Refer=index",
                "type": "Weibo",
                "datetime": "2025-02-28 00:18:46"
            },
            {
                "index": 49,
                "category": "互联网",
                "title": "雷军穿皮衣",
                "hot": 77774,
                "url": "https://s.weibo.com/weibo?q=%E9%9B%B7%E5%86%9B%E7%A9%BF%E7%9A%AE%E8%A1%A3&Refer=index",
                "type": "Weibo",
                "datetime": "2025-02-28 00:18:46"
            },
            {
                "index": 50,
                "category": "民生新闻",
                "title": "建议将防性侵列入中小学必修课",
                "hot": 75403,
                "url": "https://s.weibo.com/weibo?q=%E5%BB%BA%E8%AE%AE%E5%B0%86%E9%98%B2%E6%80%A7%E4%BE%B5%E5%88%97%E5%85%A5%E4%B8%AD%E5%B0%8F%E5%AD%A6%E5%BF%85%E4%BF%AE%E8%AF%BE&Refer=index",
                "type": "Weibo",
                "datetime": "2025-02-28 00:18:46"
            }
        ],
        "hot": [
            {
                "index": 1,
                "title": "哪吒2配音演员起诉配音公司",
                "category": "电影",
                "hot": 1788319,
                "url": "https://s.weibo.com/weibo?q=%E5%93%AA%E5%90%922%E9%85%8D%E9%9F%B3%E6%BC%94%E5%91%98%E8%B5%B7%E8%AF%89%E9%85%8D%E9%9F%B3%E5%85%AC%E5%8F%B8&Refer=index",
                "createtime": "2025-02-27 22:52:22",
                "datetime": "2025-02-28 00:18:46"
            },
            {
                "index": 2,
                "title": "小米SU7Ultra",
                "category": "汽车",
                "hot": 678174,
                "url": "https://s.weibo.com/weibo?q=%E5%B0%8F%E7%B1%B3SU7Ultra&Refer=index",
                "createtime": "2025-02-27 21:21:21",
                "datetime": "2025-02-28 00:18:46"
            },
            {
                "index": 3,
                "title": "看AI如何助力春耕育种",
                "category": "正能量",
                "hot": 40640,
                "url": "https://s.weibo.com/weibo?q=%E7%9C%8BAI%E5%A6%82%E4%BD%95%E5%8A%A9%E5%8A%9B%E6%98%A5%E8%80%95%E8%82%B2%E7%A7%8D&Refer=index",
                "createtime": "2025-02-27 23:02:21",
                "datetime": "2025-02-28 00:18:46"
            },
            {
                "index": 4,
                "title": "造车40年大作 长安启源Q07",
                "category": "Unknown",
                "hot": "Unknown",
                "url": "https://s.weibo.com/weibo?q=%E9%80%A0%E8%BD%A640%E5%B9%B4%E5%A4%A7%E4%BD%9C%20%E9%95%BF%E5%AE%89%E5%90%AF%E6%BA%90Q07&Refer=index",
                "createtime": "2025-02-28 00:18:49",
                "datetime": "2025-02-28 00:18:46"
            },
            {
                "index": 5,
                "title": "小猪佩奇猪妈妈怀三胎",
                "category": "动漫,作品衍生",
                "hot": 466696,
                "url": "https://s.weibo.com/weibo?q=%E5%B0%8F%E7%8C%AA%E4%BD%A9%E5%A5%87%E7%8C%AA%E5%A6%88%E5%A6%88%E6%80%80%E4%B8%89%E8%83%8E&Refer=index",
                "createtime": "2025-02-27 22:19:20",
                "datetime": "2025-02-28 00:18:46"
            },
            {
                "index": 6,
                "title": "小米SU7Ultra定价52.99万元",
                "category": "汽车",
                "hot": 463564,
                "url": "https://s.weibo.com/weibo?q=%E5%B0%8F%E7%B1%B3SU7Ultra%E5%AE%9A%E4%BB%B752.99%E4%B8%87%E5%85%83&Refer=index",
                "createtime": "2025-02-27 21:28:20",
                "datetime": "2025-02-28 00:18:46"
            },
            {
                "index": 7,
                "title": "建议春节假期取消调休",
                "category": "民生新闻",
                "hot": 326795,
                "url": "https://s.weibo.com/weibo?q=%E5%BB%BA%E8%AE%AE%E6%98%A5%E8%8A%82%E5%81%87%E6%9C%9F%E5%8F%96%E6%B6%88%E8%B0%83%E4%BC%91&Refer=index",
                "createtime": "2025-02-27 17:50:20",
                "datetime": "2025-02-28 00:18:46"
            },
            {
                "index": 8,
                "title": "前TVB甜妹唐宁回应满头白发",
                "category": "艺人",
                "hot": 407900,
                "url": "https://s.weibo.com/weibo?q=%E5%89%8DTVB%E7%94%9C%E5%A6%B9%E5%94%90%E5%AE%81%E5%9B%9E%E5%BA%94%E6%BB%A1%E5%A4%B4%E7%99%BD%E5%8F%91&Refer=index",
                "createtime": "2025-02-27 23:01:19",
                "datetime": "2025-02-28 00:18:46"
            },
            {
                "index": 9,
                "title": "雷军夸保时捷",
                "category": "汽车,互联网",
                "hot": 357185,
                "url": "https://s.weibo.com/weibo?q=%E9%9B%B7%E5%86%9B%E5%A4%B8%E4%BF%9D%E6%97%B6%E6%8D%B7&Refer=index",
                "createtime": "2025-02-27 20:45:19",
                "datetime": "2025-02-28 00:18:46"
            },
            {
                "index": 10,
                "title": "小米15Ultra及SU7Ultra今日发布",
                "category": "数码,汽车",
                "hot": 265476,
                "url": "https://s.weibo.com/weibo?q=%E5%B0%8F%E7%B1%B315Ultra%E5%8F%8ASU7Ultra%E4%BB%8A%E6%97%A5%E5%8F%91%E5%B8%83&Refer=index",
                "createtime": "2025-02-27 23:45:19",
                "datetime": "2025-02-28 00:18:46"
            },
            {
                "index": 11,
                "title": "零食鲍菇螺肉主配料为福寿螺肉",
                "category": "民生新闻",
                "hot": 102023,
                "url": "https://s.weibo.com/weibo?q=%E9%9B%B6%E9%A3%9F%E9%B2%8D%E8%8F%87%E8%9E%BA%E8%82%89%E4%B8%BB%E9%85%8D%E6%96%99%E4%B8%BA%E7%A6%8F%E5%AF%BF%E8%9E%BA%E8%82%89&Refer=index",
                "createtime": "2025-02-27 23:09:21",
                "datetime": "2025-02-28 00:18:46"
            },
            {
                "index": 12,
                "title": "接吻超58小时破纪录夫妇宣布分手",
                "category": "民生新闻",
                "hot": 647467,
                "url": "https://s.weibo.com/weibo?q=%E6%8E%A5%E5%90%BB%E8%B6%8558%E5%B0%8F%E6%97%B6%E7%A0%B4%E7%BA%AA%E5%BD%95%E5%A4%AB%E5%A6%87%E5%AE%A3%E5%B8%83%E5%88%86%E6%89%8B&Refer=index",
                "createtime": "2025-02-27 19:25:19",
                "datetime": "2025-02-28 00:18:46"
            },
            {
                "index": 13,
                "title": "sk卡卡",
                "category": "网红",
                "hot": 542581,
                "url": "https://s.weibo.com/weibo?q=sk%E5%8D%A1%E5%8D%A1&Refer=index",
                "createtime": "2025-02-27 23:34:18",
                "datetime": "2025-02-28 00:18:46"
            },
            {
                "index": 14,
                "title": "薛小婉怒斥韩安冉",
                "category": "艺人",
                "hot": 373154,
                "url": "https://s.weibo.com/weibo?q=%E8%96%9B%E5%B0%8F%E5%A9%89%E6%80%92%E6%96%A5%E9%9F%A9%E5%AE%89%E5%86%89&Refer=index",
                "createtime": "2025-02-27 18:14:19",
                "datetime": "2025-02-28 00:18:46"
            },
            {
                "index": 15,
                "title": "香港丁克夫妻29平的房怎么住",
                "category": "情感",
                "hot": 353112,
                "url": "https://s.weibo.com/weibo?q=%E9%A6%99%E6%B8%AF%E4%B8%81%E5%85%8B%E5%A4%AB%E5%A6%BB29%E5%B9%B3%E7%9A%84%E6%88%BF%E6%80%8E%E4%B9%88%E4%BD%8F&Refer=index",
                "createtime": "2025-02-27 21:56:21",
                "datetime": "2025-02-28 00:18:46"
            },
            {
                "index": 16,
                "title": "李维嘉这辈子有为王栎鑫拼过命",
                "category": "艺人",
                "hot": 352355,
                "url": "https://s.weibo.com/weibo?q=%E6%9D%8E%E7%BB%B4%E5%98%89%E8%BF%99%E8%BE%88%E5%AD%90%E6%9C%89%E4%B8%BA%E7%8E%8B%E6%A0%8E%E9%91%AB%E6%8B%BC%E8%BF%87%E5%91%BD&Refer=index",
                "createtime": "2025-02-27 21:10:20",
                "datetime": "2025-02-28 00:18:46"
            },
            {
                "index": 17,
                "title": "女子嫌金价太高在家自制金戒指",
                "category": "民生新闻",
                "hot": 237157,
                "url": "https://s.weibo.com/weibo?q=%E5%A5%B3%E5%AD%90%E5%AB%8C%E9%87%91%E4%BB%B7%E5%A4%AA%E9%AB%98%E5%9C%A8%E5%AE%B6%E8%87%AA%E5%88%B6%E9%87%91%E6%88%92%E6%8C%87&Refer=index",
                "createtime": "2025-02-27 19:43:19",
                "datetime": "2025-02-28 00:18:46"
            },
            {
                "index": 18,
                "title": "美国民众称特朗普卖金卡是笑话",
                "category": "海外新闻",
                "hot": 187749,
                "url": "https://s.weibo.com/weibo?q=%E7%BE%8E%E5%9B%BD%E6%B0%91%E4%BC%97%E7%A7%B0%E7%89%B9%E6%9C%97%E6%99%AE%E5%8D%96%E9%87%91%E5%8D%A1%E6%98%AF%E7%AC%91%E8%AF%9D&Refer=index",
                "createtime": "2025-02-27 23:30:18",
                "datetime": "2025-02-28 00:18:46"
            },
            {
                "index": 19,
                "title": "哪吒2票房已破140亿",
                "category": "电影",
                "hot": 176526,
                "url": "https://s.weibo.com/weibo?q=%E5%93%AA%E5%90%922%E7%A5%A8%E6%88%BF%E5%B7%B2%E7%A0%B4140%E4%BA%BF&Refer=index",
                "createtime": "2025-02-27 17:43:18",
                "datetime": "2025-02-28 00:18:46"
            },
            {
                "index": 20,
                "title": "孟子义米兰时装周出发啦",
                "category": "作品衍生,时尚",
                "hot": 169806,
                "url": "https://s.weibo.com/weibo?q=%E5%AD%9F%E5%AD%90%E4%B9%89%E7%B1%B3%E5%85%B0%E6%97%B6%E8%A3%85%E5%91%A8%E5%87%BA%E5%8F%91%E5%95%A6&Refer=index",
                "createtime": "2025-02-27 23:55:19",
                "datetime": "2025-02-28 00:18:46"
            },
            {
                "index": 21,
                "title": "陈昊宇米兰首秀g社生图",
                "category": "作品衍生,时尚",
                "hot": 163311,
                "url": "https://s.weibo.com/weibo?q=%E9%99%88%E6%98%8A%E5%AE%87%E7%B1%B3%E5%85%B0%E9%A6%96%E7%A7%80g%E7%A4%BE%E7%94%9F%E5%9B%BE&Refer=index",
                "createtime": "2025-02-27 22:20:19",
                "datetime": "2025-02-28 00:18:46"
            },
            {
                "index": 22,
                "title": "偶遇靳东以为是公司领导",
                "category": "艺人",
                "hot": 167692,
                "url": "https://s.weibo.com/weibo?q=%E5%81%B6%E9%81%87%E9%9D%B3%E4%B8%9C%E4%BB%A5%E4%B8%BA%E6%98%AF%E5%85%AC%E5%8F%B8%E9%A2%86%E5%AF%BC&Refer=index",
                "createtime": "2025-02-27 23:56:18",
                "datetime": "2025-02-28 00:18:46"
            },
            {
                "index": 23,
                "title": "老人退休金9000多元家中却垃圾成山",
                "category": "民生新闻",
                "hot": 167179,
                "url": "https://s.weibo.com/weibo?q=%E8%80%81%E4%BA%BA%E9%80%80%E4%BC%91%E9%87%919000%E5%A4%9A%E5%85%83%E5%AE%B6%E4%B8%AD%E5%8D%B4%E5%9E%83%E5%9C%BE%E6%88%90%E5%B1%B1&Refer=index",
                "createtime": "2025-02-27 19:12:19",
                "datetime": "2025-02-28 00:18:46"
            },
            {
                "index": 24,
                "title": "章若楠追星周杰伦成功",
                "category": "艺人",
                "hot": 150903,
                "url": "https://s.weibo.com/weibo?q=%E7%AB%A0%E8%8B%A5%E6%A5%A0%E8%BF%BD%E6%98%9F%E5%91%A8%E6%9D%B0%E4%BC%A6%E6%88%90%E5%8A%9F&Refer=index",
                "createtime": "2025-02-27 18:38:18",
                "datetime": "2025-02-28 00:18:46"
            },
            {
                "index": 25,
                "title": "厂家回应零食主配料为福寿螺肉",
                "category": "民生新闻",
                "hot": 148660,
                "url": "https://s.weibo.com/weibo?q=%E5%8E%82%E5%AE%B6%E5%9B%9E%E5%BA%94%E9%9B%B6%E9%A3%9F%E4%B8%BB%E9%85%8D%E6%96%99%E4%B8%BA%E7%A6%8F%E5%AF%BF%E8%9E%BA%E8%82%89&Refer=index",
                "createtime": "2025-02-27 23:07:20",
                "datetime": "2025-02-28 00:18:46"
            },
            {
                "index": 26,
                "title": "宝可梦手游新作",
                "category": "游戏",
                "hot": 100633,
                "url": "https://s.weibo.com/weibo?q=%E5%AE%9D%E5%8F%AF%E6%A2%A6%E6%89%8B%E6%B8%B8%E6%96%B0%E4%BD%9C&Refer=index",
                "createtime": "2025-02-27 23:31:19",
                "datetime": "2025-02-28 00:18:46"
            },
            {
                "index": 27,
                "title": "方媛感受到了祖国的温暖",
                "category": "网红",
                "hot": 142244,
                "url": "https://s.weibo.com/weibo?q=%E6%96%B9%E5%AA%9B%E6%84%9F%E5%8F%97%E5%88%B0%E4%BA%86%E7%A5%96%E5%9B%BD%E7%9A%84%E6%B8%A9%E6%9A%96&Refer=index",
                "createtime": "2025-02-27 23:46:18",
                "datetime": "2025-02-28 00:18:46"
            },
            {
                "index": 28,
                "title": "韩佳人自曝曾一年内流产三次",
                "category": "艺人",
                "hot": 133596,
                "url": "https://s.weibo.com/weibo?q=%E9%9F%A9%E4%BD%B3%E4%BA%BA%E8%87%AA%E6%9B%9D%E6%9B%BE%E4%B8%80%E5%B9%B4%E5%86%85%E6%B5%81%E4%BA%A7%E4%B8%89%E6%AC%A1&Refer=index",
                "createtime": "2025-02-27 16:56:20",
                "datetime": "2025-02-28 00:18:46"
            },
            {
                "index": 29,
                "title": "翟潇闻创2的含金量还在上升",
                "category": "综艺",
                "hot": 125676,
                "url": "https://s.weibo.com/weibo?q=%E7%BF%9F%E6%BD%87%E9%97%BB%E5%88%9B2%E7%9A%84%E5%90%AB%E9%87%91%E9%87%8F%E8%BF%98%E5%9C%A8%E4%B8%8A%E5%8D%87&Refer=index",
                "createtime": "2025-02-28 00:06:18",
                "datetime": "2025-02-28 00:18:46"
            },
            {
                "index": 30,
                "title": "爱你",
                "category": "剧集",
                "hot": 115149,
                "url": "https://s.weibo.com/weibo?q=%E7%88%B1%E4%BD%A0&Refer=index",
                "createtime": "2025-02-27 19:38:19",
                "datetime": "2025-02-28 00:18:46"
            },
            {
                "index": 31,
                "title": "哪吒炸出了多少民间高手",
                "category": "电影",
                "hot": 99205,
                "url": "https://s.weibo.com/weibo?q=%E5%93%AA%E5%90%92%E7%82%B8%E5%87%BA%E4%BA%86%E5%A4%9A%E5%B0%91%E6%B0%91%E9%97%B4%E9%AB%98%E6%89%8B&Refer=index",
                "createtime": "2025-02-27 21:29:20",
                "datetime": "2025-02-28 00:18:46"
            },
            {
                "index": 32,
                "title": "我国古代已人手中国结",
                "category": "民生新闻",
                "hot": 132763,
                "url": "https://s.weibo.com/weibo?q=%E6%88%91%E5%9B%BD%E5%8F%A4%E4%BB%A3%E5%B7%B2%E4%BA%BA%E6%89%8B%E4%B8%AD%E5%9B%BD%E7%BB%93&Refer=index",
                "createtime": "2025-02-27 23:29:18",
                "datetime": "2025-02-28 00:18:46"
            },
            {
                "index": 33,
                "title": "柳智敏好美",
                "category": "作品衍生,时尚",
                "hot": 124502,
                "url": "https://s.weibo.com/weibo?q=%E6%9F%B3%E6%99%BA%E6%95%8F%E5%A5%BD%E7%BE%8E&Refer=index",
                "createtime": "2025-02-27 21:54:21",
                "datetime": "2025-02-28 00:18:46"
            },
            {
                "index": 34,
                "title": "婚房7年没住被小区保洁换锁养鸡",
                "category": "民生新闻",
                "hot": 119564,
                "url": "https://s.weibo.com/weibo?q=%E5%A9%9A%E6%88%BF7%E5%B9%B4%E6%B2%A1%E4%BD%8F%E8%A2%AB%E5%B0%8F%E5%8C%BA%E4%BF%9D%E6%B4%81%E6%8D%A2%E9%94%81%E5%85%BB%E9%B8%A1&Refer=index",
                "createtime": "2025-02-27 18:50:18",
                "datetime": "2025-02-28 00:18:46"
            },
            {
                "index": 35,
                "title": "鬼灭之刃变柱灭之刃",
                "category": "动漫",
                "hot": 118183,
                "url": "https://s.weibo.com/weibo?q=%E9%AC%BC%E7%81%AD%E4%B9%8B%E5%88%83%E5%8F%98%E6%9F%B1%E7%81%AD%E4%B9%8B%E5%88%83&Refer=index",
                "createtime": "2025-02-27 23:13:20",
                "datetime": "2025-02-28 00:18:46"
            },
            {
                "index": 36,
                "title": "小米耳机",
                "category": "数码",
                "hot": 109882,
                "url": "https://s.weibo.com/weibo?q=%E5%B0%8F%E7%B1%B3%E8%80%B3%E6%9C%BA&Refer=index",
                "createtime": "2025-02-27 21:09:20",
                "datetime": "2025-02-28 00:18:46"
            },
            {
                "index": 37,
                "title": "300元一张的始祖鸟吊牌到底谁在买",
                "category": "民生新闻",
                "hot": 105711,
                "url": "https://s.weibo.com/weibo?q=300%E5%85%83%E4%B8%80%E5%BC%A0%E7%9A%84%E5%A7%8B%E7%A5%96%E9%B8%9F%E5%90%8A%E7%89%8C%E5%88%B0%E5%BA%95%E8%B0%81%E5%9C%A8%E4%B9%B0&Refer=index",
                "createtime": "2025-02-27 18:39:18",
                "datetime": "2025-02-28 00:18:46"
            },
            {
                "index": 38,
                "title": "周杰伦演唱会唱了难哄主题曲任性",
                "category": "演出",
                "hot": 104102,
                "url": "https://s.weibo.com/weibo?q=%E5%91%A8%E6%9D%B0%E4%BC%A6%E6%BC%94%E5%94%B1%E4%BC%9A%E5%94%B1%E4%BA%86%E9%9A%BE%E5%93%84%E4%B8%BB%E9%A2%98%E6%9B%B2%E4%BB%BB%E6%80%A7&Refer=index",
                "createtime": "2025-02-28 00:11:18",
                "datetime": "2025-02-28 00:18:46"
            },
            {
                "index": 39,
                "title": "Prada大秀",
                "category": "时尚",
                "hot": 103740,
                "url": "https://s.weibo.com/weibo?q=Prada%E5%A4%A7%E7%A7%80&Refer=index",
                "createtime": "2025-02-27 22:52:22",
                "datetime": "2025-02-28 00:18:46"
            },
            {
                "index": 40,
                "title": "樊振东可直接参加全运会决赛阶段单打比赛",
                "category": "体育",
                "hot": 102070,
                "url": "https://s.weibo.com/weibo?q=%E6%A8%8A%E6%8C%AF%E4%B8%9C%E5%8F%AF%E7%9B%B4%E6%8E%A5%E5%8F%82%E5%8A%A0%E5%85%A8%E8%BF%90%E4%BC%9A%E5%86%B3%E8%B5%9B%E9%98%B6%E6%AE%B5%E5%8D%95%E6%89%93%E6%AF%94%E8%B5%9B&Refer=index",
                "createtime": "2025-02-27 23:25:19",
                "datetime": "2025-02-28 00:18:46"
            },
            {
                "index": 41,
                "title": "卡卡我尽了一切努力挽救婚姻",
                "category": "体育",
                "hot": 101103,
                "url": "https://s.weibo.com/weibo?q=%E5%8D%A1%E5%8D%A1%E6%88%91%E5%B0%BD%E4%BA%86%E4%B8%80%E5%88%87%E5%8A%AA%E5%8A%9B%E6%8C%BD%E6%95%91%E5%A9%9A%E5%A7%BB&Refer=index",
                "createtime": "2025-02-27 21:56:21",
                "datetime": "2025-02-28 00:18:46"
            },
            {
                "index": 42,
                "title": "长沙一32层居民楼承重墙被装修误拆",
                "category": "民生新闻",
                "hot": 92509,
                "url": "https://s.weibo.com/weibo?q=%E9%95%BF%E6%B2%99%E4%B8%8032%E5%B1%82%E5%B1%85%E6%B0%91%E6%A5%BC%E6%89%BF%E9%87%8D%E5%A2%99%E8%A2%AB%E8%A3%85%E4%BF%AE%E8%AF%AF%E6%8B%86&Refer=index",
                "createtime": "2025-02-27 20:06:20",
                "datetime": "2025-02-28 00:18:46"
            },
            {
                "index": 43,
                "title": "李嘉琦六姊妹杀青长文",
                "category": "剧集",
                "hot": 91773,
                "url": "https://s.weibo.com/weibo?q=%E6%9D%8E%E5%98%89%E7%90%A6%E5%85%AD%E5%A7%8A%E5%A6%B9%E6%9D%80%E9%9D%92%E9%95%BF%E6%96%87&Refer=index",
                "createtime": "2025-02-27 19:40:17",
                "datetime": "2025-02-28 00:18:46"
            },
            {
                "index": 44,
                "title": "研招网回应考生伪造考研成绩",
                "category": "教育",
                "hot": 91711,
                "url": "https://s.weibo.com/weibo?q=%E7%A0%94%E6%8B%9B%E7%BD%91%E5%9B%9E%E5%BA%94%E8%80%83%E7%94%9F%E4%BC%AA%E9%80%A0%E8%80%83%E7%A0%94%E6%88%90%E7%BB%A9&Refer=index",
                "createtime": "2025-02-27 23:14:20",
                "datetime": "2025-02-28 00:18:46"
            },
            {
                "index": 45,
                "title": "周扬青自曝新恋情见光死",
                "category": "网红",
                "hot": 90976,
                "url": "https://s.weibo.com/weibo?q=%E5%91%A8%E6%89%AC%E9%9D%92%E8%87%AA%E6%9B%9D%E6%96%B0%E6%81%8B%E6%83%85%E8%A7%81%E5%85%89%E6%AD%BB&Refer=index",
                "createtime": "2025-02-27 16:17:19",
                "datetime": "2025-02-28 00:18:46"
            },
            {
                "index": 46,
                "title": "赵露思新头像寓意",
                "category": "艺人",
                "hot": 87635,
                "url": "https://s.weibo.com/weibo?q=%E8%B5%B5%E9%9C%B2%E6%80%9D%E6%96%B0%E5%A4%B4%E5%83%8F%E5%AF%93%E6%84%8F&Refer=index",
                "createtime": "2025-02-27 19:53:19",
                "datetime": "2025-02-28 00:18:46"
            },
            {
                "index": 47,
                "title": "雷军回应当首富",
                "category": "互联网,财经",
                "hot": 85120,
                "url": "https://s.weibo.com/weibo?q=%E9%9B%B7%E5%86%9B%E5%9B%9E%E5%BA%94%E5%BD%93%E9%A6%96%E5%AF%8C&Refer=index",
                "createtime": "2025-02-27 16:24:17",
                "datetime": "2025-02-28 00:18:46"
            },
            {
                "index": 48,
                "title": "雷军喊话别抠镀金车标",
                "category": "汽车,互联网",
                "hot": 84994,
                "url": "https://s.weibo.com/weibo?q=%E9%9B%B7%E5%86%9B%E5%96%8A%E8%AF%9D%E5%88%AB%E6%8A%A0%E9%95%80%E9%87%91%E8%BD%A6%E6%A0%87&Refer=index",
                "createtime": "2025-02-27 22:08:22",
                "datetime": "2025-02-28 00:18:46"
            },
            {
                "index": 49,
                "title": "周雨彤回应辞职发疯戏",
                "category": "剧集",
                "hot": 78666,
                "url": "https://s.weibo.com/weibo?q=%E5%91%A8%E9%9B%A8%E5%BD%A4%E5%9B%9E%E5%BA%94%E8%BE%9E%E8%81%8C%E5%8F%91%E7%96%AF%E6%88%8F&Refer=index",
                "createtime": "2025-02-27 18:17:19",
                "datetime": "2025-02-28 00:18:46"
            },
            {
                "index": 50,
                "title": "雷军穿皮衣",
                "category": "互联网",
                "hot": 77774,
                "url": "https://s.weibo.com/weibo?q=%E9%9B%B7%E5%86%9B%E7%A9%BF%E7%9A%AE%E8%A1%A3&Refer=index",
                "createtime": "2025-02-27 21:55:19",
                "datetime": "2025-02-28 00:18:46"
            },
            {
                "index": 51,
                "title": "建议将防性侵列入中小学必修课",
                "category": "民生新闻",
                "hot": 75403,
                "url": "https://s.weibo.com/weibo?q=%E5%BB%BA%E8%AE%AE%E5%B0%86%E9%98%B2%E6%80%A7%E4%BE%B5%E5%88%97%E5%85%A5%E4%B8%AD%E5%B0%8F%E5%AD%A6%E5%BF%85%E4%BF%AE%E8%AF%BE&Refer=index",
                "createtime": "2025-02-27 23:21:20",
                "datetime": "2025-02-28 00:18:46"
            }
        ]
    },
    "2025-02-28 00:44:38": {
        "searches": [
            {
                "index": 1,
                "category": "电影",
                "title": "哪吒2配音演员起诉配音公司",
                "hot": 1247066,
                "url": "https://s.weibo.com/weibo?q=%E5%93%AA%E5%90%922%E9%85%8D%E9%9F%B3%E6%BC%94%E5%91%98%E8%B5%B7%E8%AF%89%E9%85%8D%E9%9F%B3%E5%85%AC%E5%8F%B8&Refer=index",
                "type": "Weibo",
                "datetime": "2025-02-28 00:44:38"
            },
            {
                "index": 2,
                "category": "汽车",
                "title": "小米SU7Ultra",
                "hot": 453200,
                "url": "https://s.weibo.com/weibo?q=%E5%B0%8F%E7%B1%B3SU7Ultra&Refer=index",
                "type": "Weibo",
                "datetime": "2025-02-28 00:44:38"
            },
            {
                "index": 3,
                "category": "正能量",
                "title": "看AI如何助力春耕育种",
                "hot": 33186,
                "url": "https://s.weibo.com/weibo?q=%E7%9C%8BAI%E5%A6%82%E4%BD%95%E5%8A%A9%E5%8A%9B%E6%98%A5%E8%80%95%E8%82%B2%E7%A7%8D&Refer=index",
                "type": "Weibo",
                "datetime": "2025-02-28 00:44:38"
            },
            {
                "index": 4,
                "category": "",
                "title": "张婧仪美到头发丝",
                "hot": "Unknown",
                "url": "https://s.weibo.com/weibo?q=%E5%BC%A0%E5%A9%A7%E4%BB%AA%E7%BE%8E%E5%88%B0%E5%A4%B4%E5%8F%91%E4%B8%9D&Refer=index",
                "type": "Weibo",
                "datetime": "2025-02-28 00:44:38"
            },
            {
                "index": 5,
                "category": "汽车",
                "title": "小米SU7Ultra定价52.99万元",
                "hot": 333489,
                "url": "https://s.weibo.com/weibo?q=%E5%B0%8F%E7%B1%B3SU7Ultra%E5%AE%9A%E4%BB%B752.99%E4%B8%87%E5%85%83&Refer=index",
                "type": "Weibo",
                "datetime": "2025-02-28 00:44:38"
            },
            {
                "index": 6,
                "category": "动漫,作品衍生",
                "title": "小猪佩奇猪妈妈怀三胎",
                "hot": 312383,
                "url": "https://s.weibo.com/weibo?q=%E5%B0%8F%E7%8C%AA%E4%BD%A9%E5%A5%87%E7%8C%AA%E5%A6%88%E5%A6%88%E6%80%80%E4%B8%89%E8%83%8E&Refer=index",
                "type": "Weibo",
                "datetime": "2025-02-28 00:44:38"
            },
            {
                "index": 7,
                "category": "民生新闻",
                "title": "建议春节假期取消调休",
                "hot": 206781,
                "url": "https://s.weibo.com/weibo?q=%E5%BB%BA%E8%AE%AE%E6%98%A5%E8%8A%82%E5%81%87%E6%9C%9F%E5%8F%96%E6%B6%88%E8%B0%83%E4%BC%91&Refer=index",
                "type": "Weibo",
                "datetime": "2025-02-28 00:44:38"
            },
            {
                "index": 8,
                "category": "汽车,互联网",
                "title": "雷军夸保时捷",
                "hot": 290639,
                "url": "https://s.weibo.com/weibo?q=%E9%9B%B7%E5%86%9B%E5%A4%B8%E4%BF%9D%E6%97%B6%E6%8D%B7&Refer=index",
                "type": "Weibo",
                "datetime": "2025-02-28 00:44:38"
            },
            {
                "index": 9,
                "category": "艺人",
                "title": "前TVB甜妹唐宁回应满头白发",
                "hot": 273309,
                "url": "https://s.weibo.com/weibo?q=%E5%89%8DTVB%E7%94%9C%E5%A6%B9%E5%94%90%E5%AE%81%E5%9B%9E%E5%BA%94%E6%BB%A1%E5%A4%B4%E7%99%BD%E5%8F%91&Refer=index",
                "type": "Weibo",
                "datetime": "2025-02-28 00:44:38"
            },
            {
                "index": 10,
                "category": "数码,汽车",
                "title": "小米15Ultra及SU7Ultra今日发布",
                "hot": 219004,
                "url": "https://s.weibo.com/weibo?q=%E5%B0%8F%E7%B1%B315Ultra%E5%8F%8ASU7Ultra%E4%BB%8A%E6%97%A5%E5%8F%91%E5%B8%83&Refer=index",
                "type": "Weibo",
                "datetime": "2025-02-28 00:44:38"
            },
            {
                "index": 11,
                "category": "民生新闻",
                "title": "女子嫌金价太高在家自制金戒指",
                "hot": 178278,
                "url": "https://s.weibo.com/weibo?q=%E5%A5%B3%E5%AD%90%E5%AB%8C%E9%87%91%E4%BB%B7%E5%A4%AA%E9%AB%98%E5%9C%A8%E5%AE%B6%E8%87%AA%E5%88%B6%E9%87%91%E6%88%92%E6%8C%87&Refer=index",
                "type": "Weibo",
                "datetime": "2025-02-28 00:44:38"
            },
            {
                "index": 12,
                "category": "民生新闻",
                "title": "接吻超58小时破纪录夫妇宣布分手",
                "hot": 521633,
                "url": "https://s.weibo.com/weibo?q=%E6%8E%A5%E5%90%BB%E8%B6%8558%E5%B0%8F%E6%97%B6%E7%A0%B4%E7%BA%AA%E5%BD%95%E5%A4%AB%E5%A6%87%E5%AE%A3%E5%B8%83%E5%88%86%E6%89%8B&Refer=index",
                "type": "Weibo",
                "datetime": "2025-02-28 00:44:38"
            },
            {
                "index": 13,
                "category": "网红",
                "title": "sk卡卡",
                "hot": 412633,
                "url": "https://s.weibo.com/weibo?q=sk%E5%8D%A1%E5%8D%A1&Refer=index",
                "type": "Weibo",
                "datetime": "2025-02-28 00:44:38"
            },
            {
                "index": 14,
                "category": "艺人",
                "title": "薛小婉怒斥韩安冉",
                "hot": 318895,
                "url": "https://s.weibo.com/weibo?q=%E8%96%9B%E5%B0%8F%E5%A9%89%E6%80%92%E6%96%A5%E9%9F%A9%E5%AE%89%E5%86%89&Refer=index",
                "type": "Weibo",
                "datetime": "2025-02-28 00:44:38"
            },
            {
                "index": 15,
                "category": "艺人",
                "title": "李维嘉这辈子有为王栎鑫拼过命",
                "hot": 259777,
                "url": "https://s.weibo.com/weibo?q=%E6%9D%8E%E7%BB%B4%E5%98%89%E8%BF%99%E8%BE%88%E5%AD%90%E6%9C%89%E4%B8%BA%E7%8E%8B%E6%A0%8E%E9%91%AB%E6%8B%BC%E8%BF%87%E5%91%BD&Refer=index",
                "type": "Weibo",
                "datetime": "2025-02-28 00:44:38"
            },
            {
                "index": 16,
                "category": "作品衍生,时尚",
                "title": "孟子义米兰时装周出发啦",
                "hot": 230711,
                "url": "https://s.weibo.com/weibo?q=%E5%AD%9F%E5%AD%90%E4%B9%89%E7%B1%B3%E5%85%B0%E6%97%B6%E8%A3%85%E5%91%A8%E5%87%BA%E5%8F%91%E5%95%A6&Refer=index",
                "type": "Weibo",
                "datetime": "2025-02-28 00:44:38"
            },
            {
                "index": 17,
                "category": "网红",
                "title": "方媛感受到了祖国的温暖",
                "hot": 172881,
                "url": "https://s.weibo.com/weibo?q=%E6%96%B9%E5%AA%9B%E6%84%9F%E5%8F%97%E5%88%B0%E4%BA%86%E7%A5%96%E5%9B%BD%E7%9A%84%E6%B8%A9%E6%9A%96&Refer=index",
                "type": "Weibo",
                "datetime": "2025-02-28 00:44:38"
            },
            {
                "index": 18,
                "category": "正能量",
                "title": "男子陪妻子看病医生多看一眼救一命",
                "hot": 39100,
                "url": "https://s.weibo.com/weibo?q=%E7%94%B7%E5%AD%90%E9%99%AA%E5%A6%BB%E5%AD%90%E7%9C%8B%E7%97%85%E5%8C%BB%E7%94%9F%E5%A4%9A%E7%9C%8B%E4%B8%80%E7%9C%BC%E6%95%91%E4%B8%80%E5%91%BD&Refer=index",
                "type": "Weibo",
                "datetime": "2025-02-28 00:44:38"
            },
            {
                "index": 19,
                "category": "海外新闻",
                "title": "美国民众称特朗普卖金卡是笑话",
                "hot": 172246,
                "url": "https://s.weibo.com/weibo?q=%E7%BE%8E%E5%9B%BD%E6%B0%91%E4%BC%97%E7%A7%B0%E7%89%B9%E6%9C%97%E6%99%AE%E5%8D%96%E9%87%91%E5%8D%A1%E6%98%AF%E7%AC%91%E8%AF%9D&Refer=index",
                "type": "Weibo",
                "datetime": "2025-02-28 00:44:38"
            },
            {
                "index": 20,
                "category": "艺人",
                "title": "偶遇靳东以为是公司领导",
                "hot": 228941,
                "url": "https://s.weibo.com/weibo?q=%E5%81%B6%E9%81%87%E9%9D%B3%E4%B8%9C%E4%BB%A5%E4%B8%BA%E6%98%AF%E5%85%AC%E5%8F%B8%E9%A2%86%E5%AF%BC&Refer=index",
                "type": "Weibo",
                "datetime": "2025-02-28 00:44:38"
            },
            {
                "index": 21,
                "category": "作品衍生,时尚",
                "title": "陈昊宇柳智敏边佑锡生图",
                "hot": 212109,
                "url": "https://s.weibo.com/weibo?q=%E9%99%88%E6%98%8A%E5%AE%87%E6%9F%B3%E6%99%BA%E6%95%8F%E8%BE%B9%E4%BD%91%E9%94%A1%E7%94%9F%E5%9B%BE&Refer=index",
                "type": "Weibo",
                "datetime": "2025-02-28 00:44:38"
            },
            {
                "index": 22,
                "category": "艺人",
                "title": "关晓彤",
                "hot": 198218,
                "url": "https://s.weibo.com/weibo?q=%E5%85%B3%E6%99%93%E5%BD%A4&Refer=index",
                "type": "Weibo",
                "datetime": "2025-02-28 00:44:38"
            },
            {
                "index": 23,
                "category": "情感",
                "title": "香港丁克夫妻29平的房怎么住",
                "hot": 187959,
                "url": "https://s.weibo.com/weibo?q=%E9%A6%99%E6%B8%AF%E4%B8%81%E5%85%8B%E5%A4%AB%E5%A6%BB29%E5%B9%B3%E7%9A%84%E6%88%BF%E6%80%8E%E4%B9%88%E4%BD%8F&Refer=index",
                "type": "Weibo",
                "datetime": "2025-02-28 00:44:38"
            },
            {
                "index": 24,
                "category": "作品衍生,时尚",
                "title": "Gucci全平台更新肖战",
                "hot": 150308,
                "url": "https://s.weibo.com/weibo?q=Gucci%E5%85%A8%E5%B9%B3%E5%8F%B0%E6%9B%B4%E6%96%B0%E8%82%96%E6%88%98&Refer=index",
                "type": "Weibo",
                "datetime": "2025-02-28 00:44:38"
            },
            {
                "index": 25,
                "category": "民生新闻",
                "title": "零食鲍菇螺肉主配料为福寿螺肉",
                "hot": 128601,
                "url": "https://s.weibo.com/weibo?q=%E9%9B%B6%E9%A3%9F%E9%B2%8D%E8%8F%87%E8%9E%BA%E8%82%89%E4%B8%BB%E9%85%8D%E6%96%99%E4%B8%BA%E7%A6%8F%E5%AF%BF%E8%9E%BA%E8%82%89&Refer=index",
                "type": "Weibo",
                "datetime": "2025-02-28 00:44:38"
            },
            {
                "index": 26,
                "category": "游戏",
                "title": "宝可梦发布会",
                "hot": 74933,
                "url": "https://s.weibo.com/weibo?q=%E5%AE%9D%E5%8F%AF%E6%A2%A6%E5%8F%91%E5%B8%83%E4%BC%9A&Refer=index",
                "type": "Weibo",
                "datetime": "2025-02-28 00:44:38"
            },
            {
                "index": 27,
                "category": "电影",
                "title": "哪吒2票房已破140亿",
                "hot": 123035,
                "url": "https://s.weibo.com/weibo?q=%E5%93%AA%E5%90%922%E7%A5%A8%E6%88%BF%E5%B7%B2%E7%A0%B4140%E4%BA%BF&Refer=index",
                "type": "Weibo",
                "datetime": "2025-02-28 00:44:38"
            },
            {
                "index": 28,
                "category": "演出",
                "title": "周杰伦演唱会唱了难哄主题曲任性",
                "hot": 122996,
                "url": "https://s.weibo.com/weibo?q=%E5%91%A8%E6%9D%B0%E4%BC%A6%E6%BC%94%E5%94%B1%E4%BC%9A%E5%94%B1%E4%BA%86%E9%9A%BE%E5%93%84%E4%B8%BB%E9%A2%98%E6%9B%B2%E4%BB%BB%E6%80%A7&Refer=index",
                "type": "Weibo",
                "datetime": "2025-02-28 00:44:38"
            },
            {
                "index": 29,
                "category": "民生新闻",
                "title": "老人退休金9000多元家中却垃圾成山",
                "hot": 115464,
                "url": "https://s.weibo.com/weibo?q=%E8%80%81%E4%BA%BA%E9%80%80%E4%BC%91%E9%87%919000%E5%A4%9A%E5%85%83%E5%AE%B6%E4%B8%AD%E5%8D%B4%E5%9E%83%E5%9C%BE%E6%88%90%E5%B1%B1&Refer=index",
                "type": "Weibo",
                "datetime": "2025-02-28 00:44:38"
            },
            {
                "index": 30,
                "category": "综艺",
                "title": "翟潇闻创2的含金量还在上升",
                "hot": 106550,
                "url": "https://s.weibo.com/weibo?q=%E7%BF%9F%E6%BD%87%E9%97%BB%E5%88%9B2%E7%9A%84%E5%90%AB%E9%87%91%E9%87%8F%E8%BF%98%E5%9C%A8%E4%B8%8A%E5%8D%87&Refer=index",
                "type": "Weibo",
                "datetime": "2025-02-28 00:44:38"
            },
            {
                "index": 31,
                "category": "作品衍生,时尚",
                "title": "陈昊宇米兰首秀g社生图",
                "hot": 93556,
                "url": "https://s.weibo.com/weibo?q=%E9%99%88%E6%98%8A%E5%AE%87%E7%B1%B3%E5%85%B0%E9%A6%96%E7%A7%80g%E7%A4%BE%E7%94%9F%E5%9B%BE&Refer=index",
                "type": "Weibo",
                "datetime": "2025-02-28 00:44:38"
            },
            {
                "index": 32,
                "category": "动漫",
                "title": "鬼灭之刃变柱灭之刃",
                "hot": 97125,
                "url": "https://s.weibo.com/weibo?q=%E9%AC%BC%E7%81%AD%E4%B9%8B%E5%88%83%E5%8F%98%E6%9F%B1%E7%81%AD%E4%B9%8B%E5%88%83&Refer=index",
                "type": "Weibo",
                "datetime": "2025-02-28 00:44:38"
            },
            {
                "index": 33,
                "category": "艺人",
                "title": "章若楠追星周杰伦成功",
                "hot": 104098,
                "url": "https://s.weibo.com/weibo?q=%E7%AB%A0%E8%8B%A5%E6%A5%A0%E8%BF%BD%E6%98%9F%E5%91%A8%E6%9D%B0%E4%BC%A6%E6%88%90%E5%8A%9F&Refer=index",
                "type": "Weibo",
                "datetime": "2025-02-28 00:44:38"
            },
            {
                "index": 34,
                "category": "作品衍生,时尚",
                "title": "柳智敏好美",
                "hot": 95838,
                "url": "https://s.weibo.com/weibo?q=%E6%9F%B3%E6%99%BA%E6%95%8F%E5%A5%BD%E7%BE%8E&Refer=index",
                "type": "Weibo",
                "datetime": "2025-02-28 00:44:38"
            },
            {
                "index": 35,
                "category": "民生新闻",
                "title": "厂家回应零食主配料为福寿螺肉",
                "hot": 95330,
                "url": "https://s.weibo.com/weibo?q=%E5%8E%82%E5%AE%B6%E5%9B%9E%E5%BA%94%E9%9B%B6%E9%A3%9F%E4%B8%BB%E9%85%8D%E6%96%99%E4%B8%BA%E7%A6%8F%E5%AF%BF%E8%9E%BA%E8%82%89&Refer=index",
                "type": "Weibo",
                "datetime": "2025-02-28 00:44:38"
            },
            {
                "index": 36,
                "category": "剧集",
                "title": "爱你",
                "hot": 90919,
                "url": "https://s.weibo.com/weibo?q=%E7%88%B1%E4%BD%A0&Refer=index",
                "type": "Weibo",
                "datetime": "2025-02-28 00:44:38"
            },
            {
                "index": 37,
                "category": "电影",
                "title": "哪吒炸出了多少民间高手",
                "hot": 58946,
                "url": "https://s.weibo.com/weibo?q=%E5%93%AA%E5%90%92%E7%82%B8%E5%87%BA%E4%BA%86%E5%A4%9A%E5%B0%91%E6%B0%91%E9%97%B4%E9%AB%98%E6%89%8B&Refer=index",
                "type": "Weibo",
                "datetime": "2025-02-28 00:44:38"
            },
            {
                "index": 38,
                "category": "民生新闻",
                "title": "婚房7年没住被小区保洁换锁养鸡",
                "hot": 89942,
                "url": "https://s.weibo.com/weibo?q=%E5%A9%9A%E6%88%BF7%E5%B9%B4%E6%B2%A1%E4%BD%8F%E8%A2%AB%E5%B0%8F%E5%8C%BA%E4%BF%9D%E6%B4%81%E6%8D%A2%E9%94%81%E5%85%BB%E9%B8%A1&Refer=index",
                "type": "Weibo",
                "datetime": "2025-02-28 00:44:38"
            },
            {
                "index": 39,
                "category": "体育",
                "title": "卡卡我尽了一切努力挽救婚姻",
                "hot": 89699,
                "url": "https://s.weibo.com/weibo?q=%E5%8D%A1%E5%8D%A1%E6%88%91%E5%B0%BD%E4%BA%86%E4%B8%80%E5%88%87%E5%8A%AA%E5%8A%9B%E6%8C%BD%E6%95%91%E5%A9%9A%E5%A7%BB&Refer=index",
                "type": "Weibo",
                "datetime": "2025-02-28 00:44:38"
            },
            {
                "index": 40,
                "category": "艺人",
                "title": "韩佳人自曝曾一年内流产三次",
                "hot": 87953,
                "url": "https://s.weibo.com/weibo?q=%E9%9F%A9%E4%BD%B3%E4%BA%BA%E8%87%AA%E6%9B%9D%E6%9B%BE%E4%B8%80%E5%B9%B4%E5%86%85%E6%B5%81%E4%BA%A7%E4%B8%89%E6%AC%A1&Refer=index",
                "type": "Weibo",
                "datetime": "2025-02-28 00:44:38"
            },
            {
                "index": 41,
                "category": "民生新闻",
                "title": "300元一张的始祖鸟吊牌到底谁在买",
                "hot": 82458,
                "url": "https://s.weibo.com/weibo?q=300%E5%85%83%E4%B8%80%E5%BC%A0%E7%9A%84%E5%A7%8B%E7%A5%96%E9%B8%9F%E5%90%8A%E7%89%8C%E5%88%B0%E5%BA%95%E8%B0%81%E5%9C%A8%E4%B9%B0&Refer=index",
                "type": "Weibo",
                "datetime": "2025-02-28 00:44:38"
            },
            {
                "index": 42,
                "category": "教育",
                "title": "研招网回应考生伪造考研成绩",
                "hot": 80494,
                "url": "https://s.weibo.com/weibo?q=%E7%A0%94%E6%8B%9B%E7%BD%91%E5%9B%9E%E5%BA%94%E8%80%83%E7%94%9F%E4%BC%AA%E9%80%A0%E8%80%83%E7%A0%94%E6%88%90%E7%BB%A9&Refer=index",
                "type": "Weibo",
                "datetime": "2025-02-28 00:44:38"
            },
            {
                "index": 43,
                "category": "民生新闻",
                "title": "长沙一32层居民楼承重墙被装修误拆",
                "hot": 73187,
                "url": "https://s.weibo.com/weibo?q=%E9%95%BF%E6%B2%99%E4%B8%8032%E5%B1%82%E5%B1%85%E6%B0%91%E6%A5%BC%E6%89%BF%E9%87%8D%E5%A2%99%E8%A2%AB%E8%A3%85%E4%BF%AE%E8%AF%AF%E6%8B%86&Refer=index",
                "type": "Weibo",
                "datetime": "2025-02-28 00:44:38"
            },
            {
                "index": 44,
                "category": "数码",
                "title": "小米耳机",
                "hot": 72893,
                "url": "https://s.weibo.com/weibo?q=%E5%B0%8F%E7%B1%B3%E8%80%B3%E6%9C%BA&Refer=index",
                "type": "Weibo",
                "datetime": "2025-02-28 00:44:38"
            },
            {
                "index": 45,
                "category": "民生新闻",
                "title": "我国古代已人手中国结",
                "hot": 71368,
                "url": "https://s.weibo.com/weibo?q=%E6%88%91%E5%9B%BD%E5%8F%A4%E4%BB%A3%E5%B7%B2%E4%BA%BA%E6%89%8B%E4%B8%AD%E5%9B%BD%E7%BB%93&Refer=index",
                "type": "Weibo",
                "datetime": "2025-02-28 00:44:38"
            },
            {
                "index": 46,
                "category": "民生新闻",
                "title": "专家科普中国结来源",
                "hot": 64133,
                "url": "https://s.weibo.com/weibo?q=%E4%B8%93%E5%AE%B6%E7%A7%91%E6%99%AE%E4%B8%AD%E5%9B%BD%E7%BB%93%E6%9D%A5%E6%BA%90&Refer=index",
                "type": "Weibo",
                "datetime": "2025-02-28 00:44:38"
            },
            {
                "index": 47,
                "category": "体育",
                "title": "樊振东可直接参加全运会决赛阶段单打比赛",
                "hot": 70408,
                "url": "https://s.weibo.com/weibo?q=%E6%A8%8A%E6%8C%AF%E4%B8%9C%E5%8F%AF%E7%9B%B4%E6%8E%A5%E5%8F%82%E5%8A%A0%E5%85%A8%E8%BF%90%E4%BC%9A%E5%86%B3%E8%B5%9B%E9%98%B6%E6%AE%B5%E5%8D%95%E6%89%93%E6%AF%94%E8%B5%9B&Refer=index",
                "type": "Weibo",
                "datetime": "2025-02-28 00:44:38"
            },
            {
                "index": 48,
                "category": "艺人",
                "title": "赵露思新头像寓意",
                "hot": 70188,
                "url": "https://s.weibo.com/weibo?q=%E8%B5%B5%E9%9C%B2%E6%80%9D%E6%96%B0%E5%A4%B4%E5%83%8F%E5%AF%93%E6%84%8F&Refer=index",
                "type": "Weibo",
                "datetime": "2025-02-28 00:44:38"
            },
            {
                "index": 49,
                "category": "互联网,财经",
                "title": "雷军回应当首富",
                "hot": 68734,
                "url": "https://s.weibo.com/weibo?q=%E9%9B%B7%E5%86%9B%E5%9B%9E%E5%BA%94%E5%BD%93%E9%A6%96%E5%AF%8C&Refer=index",
                "type": "Weibo",
                "datetime": "2025-02-28 00:44:38"
            },
            {
                "index": 50,
                "category": "游戏",
                "title": "宝可梦手游新作",
                "hot": 66422,
                "url": "https://s.weibo.com/weibo?q=%E5%AE%9D%E5%8F%AF%E6%A2%A6%E6%89%8B%E6%B8%B8%E6%96%B0%E4%BD%9C&Refer=index",
                "type": "Weibo",
                "datetime": "2025-02-28 00:44:38"
            },
            {
                "index": 51,
                "category": "情感",
                "title": "行动是打消不安最好的利器",
                "hot": 59238,
                "url": "https://s.weibo.com/weibo?q=%E8%A1%8C%E5%8A%A8%E6%98%AF%E6%89%93%E6%B6%88%E4%B8%8D%E5%AE%89%E6%9C%80%E5%A5%BD%E7%9A%84%E5%88%A9%E5%99%A8&Refer=index",
                "type": "Weibo",
                "datetime": "2025-02-28 00:44:38"
            }
        ],
        "hot": [
            {
                "index": 1,
                "title": "哪吒2配音演员起诉配音公司",
                "category": "电影",
                "hot": 1247066,
                "url": "https://s.weibo.com/weibo?q=%E5%93%AA%E5%90%922%E9%85%8D%E9%9F%B3%E6%BC%94%E5%91%98%E8%B5%B7%E8%AF%89%E9%85%8D%E9%9F%B3%E5%85%AC%E5%8F%B8&Refer=index",
                "createtime": "2025-02-27 22:52:22",
                "datetime": "2025-02-28 00:44:38"
            },
            {
                "index": 2,
                "title": "小米SU7Ultra",
                "category": "汽车",
                "hot": 453200,
                "url": "https://s.weibo.com/weibo?q=%E5%B0%8F%E7%B1%B3SU7Ultra&Refer=index",
                "createtime": "2025-02-27 21:21:21",
                "datetime": "2025-02-28 00:44:38"
            },
            {
                "index": 3,
                "title": "看AI如何助力春耕育种",
                "category": "正能量",
                "hot": 33186,
                "url": "https://s.weibo.com/weibo?q=%E7%9C%8BAI%E5%A6%82%E4%BD%95%E5%8A%A9%E5%8A%9B%E6%98%A5%E8%80%95%E8%82%B2%E7%A7%8D&Refer=index",
                "createtime": "2025-02-27 23:02:21",
                "datetime": "2025-02-28 00:44:38"
            },
            {
                "index": 4,
                "title": "小米SU7Ultra开售",
                "category": "Unknown",
                "hot": "Unknown",
                "url": "https://s.weibo.com/weibo?q=%E5%B0%8F%E7%B1%B3SU7Ultra%E5%BC%80%E5%94%AE&Refer=index",
                "createtime": "2025-02-28 00:44:40",
                "datetime": "2025-02-28 00:44:38"
            },
            {
                "index": 5,
                "title": "小米SU7Ultra定价52.99万元",
                "category": "汽车",
                "hot": 333489,
                "url": "https://s.weibo.com/weibo?q=%E5%B0%8F%E7%B1%B3SU7Ultra%E5%AE%9A%E4%BB%B752.99%E4%B8%87%E5%85%83&Refer=index",
                "createtime": "2025-02-27 21:28:20",
                "datetime": "2025-02-28 00:44:38"
            },
            {
                "index": 6,
                "title": "小猪佩奇猪妈妈怀三胎",
                "category": "动漫,作品衍生",
                "hot": 312383,
                "url": "https://s.weibo.com/weibo?q=%E5%B0%8F%E7%8C%AA%E4%BD%A9%E5%A5%87%E7%8C%AA%E5%A6%88%E5%A6%88%E6%80%80%E4%B8%89%E8%83%8E&Refer=index",
                "createtime": "2025-02-27 22:19:20",
                "datetime": "2025-02-28 00:44:38"
            },
            {
                "index": 7,
                "title": "建议春节假期取消调休",
                "category": "民生新闻",
                "hot": 206781,
                "url": "https://s.weibo.com/weibo?q=%E5%BB%BA%E8%AE%AE%E6%98%A5%E8%8A%82%E5%81%87%E6%9C%9F%E5%8F%96%E6%B6%88%E8%B0%83%E4%BC%91&Refer=index",
                "createtime": "2025-02-27 17:50:20",
                "datetime": "2025-02-28 00:44:38"
            },
            {
                "index": 8,
                "title": "雷军夸保时捷",
                "category": "汽车,互联网",
                "hot": 290639,
                "url": "https://s.weibo.com/weibo?q=%E9%9B%B7%E5%86%9B%E5%A4%B8%E4%BF%9D%E6%97%B6%E6%8D%B7&Refer=index",
                "createtime": "2025-02-27 20:45:19",
                "datetime": "2025-02-28 00:44:38"
            },
            {
                "index": 9,
                "title": "前TVB甜妹唐宁回应满头白发",
                "category": "艺人",
                "hot": 273309,
                "url": "https://s.weibo.com/weibo?q=%E5%89%8DTVB%E7%94%9C%E5%A6%B9%E5%94%90%E5%AE%81%E5%9B%9E%E5%BA%94%E6%BB%A1%E5%A4%B4%E7%99%BD%E5%8F%91&Refer=index",
                "createtime": "2025-02-27 23:01:19",
                "datetime": "2025-02-28 00:44:38"
            },
            {
                "index": 10,
                "title": "小米15Ultra及SU7Ultra今日发布",
                "category": "数码,汽车",
                "hot": 219004,
                "url": "https://s.weibo.com/weibo?q=%E5%B0%8F%E7%B1%B315Ultra%E5%8F%8ASU7Ultra%E4%BB%8A%E6%97%A5%E5%8F%91%E5%B8%83&Refer=index",
                "createtime": "2025-02-27 23:45:19",
                "datetime": "2025-02-28 00:44:38"
            },
            {
                "index": 11,
                "title": "女子嫌金价太高在家自制金戒指",
                "category": "民生新闻",
                "hot": 178278,
                "url": "https://s.weibo.com/weibo?q=%E5%A5%B3%E5%AD%90%E5%AB%8C%E9%87%91%E4%BB%B7%E5%A4%AA%E9%AB%98%E5%9C%A8%E5%AE%B6%E8%87%AA%E5%88%B6%E9%87%91%E6%88%92%E6%8C%87&Refer=index",
                "createtime": "2025-02-27 19:43:19",
                "datetime": "2025-02-28 00:44:38"
            },
            {
                "index": 12,
                "title": "接吻超58小时破纪录夫妇宣布分手",
                "category": "民生新闻",
                "hot": 521633,
                "url": "https://s.weibo.com/weibo?q=%E6%8E%A5%E5%90%BB%E8%B6%8558%E5%B0%8F%E6%97%B6%E7%A0%B4%E7%BA%AA%E5%BD%95%E5%A4%AB%E5%A6%87%E5%AE%A3%E5%B8%83%E5%88%86%E6%89%8B&Refer=index",
                "createtime": "2025-02-27 19:25:19",
                "datetime": "2025-02-28 00:44:38"
            },
            {
                "index": 13,
                "title": "sk卡卡",
                "category": "网红",
                "hot": 412633,
                "url": "https://s.weibo.com/weibo?q=sk%E5%8D%A1%E5%8D%A1&Refer=index",
                "createtime": "2025-02-27 23:34:18",
                "datetime": "2025-02-28 00:44:38"
            },
            {
                "index": 14,
                "title": "薛小婉怒斥韩安冉",
                "category": "艺人",
                "hot": 318895,
                "url": "https://s.weibo.com/weibo?q=%E8%96%9B%E5%B0%8F%E5%A9%89%E6%80%92%E6%96%A5%E9%9F%A9%E5%AE%89%E5%86%89&Refer=index",
                "createtime": "2025-02-27 18:14:19",
                "datetime": "2025-02-28 00:44:38"
            },
            {
                "index": 15,
                "title": "李维嘉这辈子有为王栎鑫拼过命",
                "category": "艺人",
                "hot": 259777,
                "url": "https://s.weibo.com/weibo?q=%E6%9D%8E%E7%BB%B4%E5%98%89%E8%BF%99%E8%BE%88%E5%AD%90%E6%9C%89%E4%B8%BA%E7%8E%8B%E6%A0%8E%E9%91%AB%E6%8B%BC%E8%BF%87%E5%91%BD&Refer=index",
                "createtime": "2025-02-27 21:10:20",
                "datetime": "2025-02-28 00:44:38"
            },
            {
                "index": 16,
                "title": "孟子义米兰时装周出发啦",
                "category": "作品衍生,时尚",
                "hot": 230711,
                "url": "https://s.weibo.com/weibo?q=%E5%AD%9F%E5%AD%90%E4%B9%89%E7%B1%B3%E5%85%B0%E6%97%B6%E8%A3%85%E5%91%A8%E5%87%BA%E5%8F%91%E5%95%A6&Refer=index",
                "createtime": "2025-02-27 23:55:19",
                "datetime": "2025-02-28 00:44:38"
            },
            {
                "index": 17,
                "title": "方媛感受到了祖国的温暖",
                "category": "网红",
                "hot": 172881,
                "url": "https://s.weibo.com/weibo?q=%E6%96%B9%E5%AA%9B%E6%84%9F%E5%8F%97%E5%88%B0%E4%BA%86%E7%A5%96%E5%9B%BD%E7%9A%84%E6%B8%A9%E6%9A%96&Refer=index",
                "createtime": "2025-02-27 23:46:18",
                "datetime": "2025-02-28 00:44:38"
            },
            {
                "index": 18,
                "title": "男子陪妻子看病医生多看一眼救一命",
                "category": "正能量",
                "hot": 39100,
                "url": "https://s.weibo.com/weibo?q=%E7%94%B7%E5%AD%90%E9%99%AA%E5%A6%BB%E5%AD%90%E7%9C%8B%E7%97%85%E5%8C%BB%E7%94%9F%E5%A4%9A%E7%9C%8B%E4%B8%80%E7%9C%BC%E6%95%91%E4%B8%80%E5%91%BD&Refer=index",
                "createtime": "2025-02-27 23:22:19",
                "datetime": "2025-02-28 00:44:38"
            },
            {
                "index": 19,
                "title": "美国民众称特朗普卖金卡是笑话",
                "category": "海外新闻",
                "hot": 172246,
                "url": "https://s.weibo.com/weibo?q=%E7%BE%8E%E5%9B%BD%E6%B0%91%E4%BC%97%E7%A7%B0%E7%89%B9%E6%9C%97%E6%99%AE%E5%8D%96%E9%87%91%E5%8D%A1%E6%98%AF%E7%AC%91%E8%AF%9D&Refer=index",
                "createtime": "2025-02-27 23:30:18",
                "datetime": "2025-02-28 00:44:38"
            },
            {
                "index": 20,
                "title": "偶遇靳东以为是公司领导",
                "category": "艺人",
                "hot": 228941,
                "url": "https://s.weibo.com/weibo?q=%E5%81%B6%E9%81%87%E9%9D%B3%E4%B8%9C%E4%BB%A5%E4%B8%BA%E6%98%AF%E5%85%AC%E5%8F%B8%E9%A2%86%E5%AF%BC&Refer=index",
                "createtime": "2025-02-27 23:56:18",
                "datetime": "2025-02-28 00:44:38"
            },
            {
                "index": 21,
                "title": "陈昊宇柳智敏边佑锡生图",
                "category": "作品衍生,时尚",
                "hot": 212109,
                "url": "https://s.weibo.com/weibo?q=%E9%99%88%E6%98%8A%E5%AE%87%E6%9F%B3%E6%99%BA%E6%95%8F%E8%BE%B9%E4%BD%91%E9%94%A1%E7%94%9F%E5%9B%BE&Refer=index",
                "createtime": "2025-02-28 00:26:16",
                "datetime": "2025-02-28 00:44:38"
            },
            {
                "index": 22,
                "title": "关晓彤",
                "category": "艺人",
                "hot": 198218,
                "url": "https://s.weibo.com/weibo?q=%E5%85%B3%E6%99%93%E5%BD%A4&Refer=index",
                "createtime": "2025-02-28 00:39:15",
                "datetime": "2025-02-28 00:44:38"
            },
            {
                "index": 23,
                "title": "香港丁克夫妻29平的房怎么住",
                "category": "情感",
                "hot": 187959,
                "url": "https://s.weibo.com/weibo?q=%E9%A6%99%E6%B8%AF%E4%B8%81%E5%85%8B%E5%A4%AB%E5%A6%BB29%E5%B9%B3%E7%9A%84%E6%88%BF%E6%80%8E%E4%B9%88%E4%BD%8F&Refer=index",
                "createtime": "2025-02-27 21:56:21",
                "datetime": "2025-02-28 00:44:38"
            },
            {
                "index": 24,
                "title": "Gucci全平台更新肖战",
                "category": "作品衍生,时尚",
                "hot": 150308,
                "url": "https://s.weibo.com/weibo?q=Gucci%E5%85%A8%E5%B9%B3%E5%8F%B0%E6%9B%B4%E6%96%B0%E8%82%96%E6%88%98&Refer=index",
                "createtime": "2025-02-28 00:37:16",
                "datetime": "2025-02-28 00:44:38"
            },
            {
                "index": 25,
                "title": "零食鲍菇螺肉主配料为福寿螺肉",
                "category": "民生新闻",
                "hot": 128601,
                "url": "https://s.weibo.com/weibo?q=%E9%9B%B6%E9%A3%9F%E9%B2%8D%E8%8F%87%E8%9E%BA%E8%82%89%E4%B8%BB%E9%85%8D%E6%96%99%E4%B8%BA%E7%A6%8F%E5%AF%BF%E8%9E%BA%E8%82%89&Refer=index",
                "createtime": "2025-02-27 23:09:21",
                "datetime": "2025-02-28 00:44:38"
            },
            {
                "index": 26,
                "title": "宝可梦发布会",
                "category": "游戏",
                "hot": 74933,
                "url": "https://s.weibo.com/weibo?q=%E5%AE%9D%E5%8F%AF%E6%A2%A6%E5%8F%91%E5%B8%83%E4%BC%9A&Refer=index",
                "createtime": "2025-02-27 23:20:20",
                "datetime": "2025-02-28 00:44:38"
            },
            {
                "index": 27,
                "title": "哪吒2票房已破140亿",
                "category": "电影",
                "hot": 123035,
                "url": "https://s.weibo.com/weibo?q=%E5%93%AA%E5%90%922%E7%A5%A8%E6%88%BF%E5%B7%B2%E7%A0%B4140%E4%BA%BF&Refer=index",
                "createtime": "2025-02-27 17:43:18",
                "datetime": "2025-02-28 00:44:38"
            },
            {
                "index": 28,
                "title": "周杰伦演唱会唱了难哄主题曲任性",
                "category": "演出",
                "hot": 122996,
                "url": "https://s.weibo.com/weibo?q=%E5%91%A8%E6%9D%B0%E4%BC%A6%E6%BC%94%E5%94%B1%E4%BC%9A%E5%94%B1%E4%BA%86%E9%9A%BE%E5%93%84%E4%B8%BB%E9%A2%98%E6%9B%B2%E4%BB%BB%E6%80%A7&Refer=index",
                "createtime": "2025-02-28 00:11:18",
                "datetime": "2025-02-28 00:44:38"
            },
            {
                "index": 29,
                "title": "老人退休金9000多元家中却垃圾成山",
                "category": "民生新闻",
                "hot": 115464,
                "url": "https://s.weibo.com/weibo?q=%E8%80%81%E4%BA%BA%E9%80%80%E4%BC%91%E9%87%919000%E5%A4%9A%E5%85%83%E5%AE%B6%E4%B8%AD%E5%8D%B4%E5%9E%83%E5%9C%BE%E6%88%90%E5%B1%B1&Refer=index",
                "createtime": "2025-02-27 19:12:19",
                "datetime": "2025-02-28 00:44:38"
            },
            {
                "index": 30,
                "title": "翟潇闻创2的含金量还在上升",
                "category": "综艺",
                "hot": 106550,
                "url": "https://s.weibo.com/weibo?q=%E7%BF%9F%E6%BD%87%E9%97%BB%E5%88%9B2%E7%9A%84%E5%90%AB%E9%87%91%E9%87%8F%E8%BF%98%E5%9C%A8%E4%B8%8A%E5%8D%87&Refer=index",
                "createtime": "2025-02-28 00:06:18",
                "datetime": "2025-02-28 00:44:38"
            },
            {
                "index": 31,
                "title": "陈昊宇米兰首秀g社生图",
                "category": "作品衍生,时尚",
                "hot": 93556,
                "url": "https://s.weibo.com/weibo?q=%E9%99%88%E6%98%8A%E5%AE%87%E7%B1%B3%E5%85%B0%E9%A6%96%E7%A7%80g%E7%A4%BE%E7%94%9F%E5%9B%BE&Refer=index",
                "createtime": "2025-02-27 22:20:19",
                "datetime": "2025-02-28 00:44:38"
            },
            {
                "index": 32,
                "title": "鬼灭之刃变柱灭之刃",
                "category": "动漫",
                "hot": 97125,
                "url": "https://s.weibo.com/weibo?q=%E9%AC%BC%E7%81%AD%E4%B9%8B%E5%88%83%E5%8F%98%E6%9F%B1%E7%81%AD%E4%B9%8B%E5%88%83&Refer=index",
                "createtime": "2025-02-27 23:13:20",
                "datetime": "2025-02-28 00:44:38"
            },
            {
                "index": 33,
                "title": "章若楠追星周杰伦成功",
                "category": "艺人",
                "hot": 104098,
                "url": "https://s.weibo.com/weibo?q=%E7%AB%A0%E8%8B%A5%E6%A5%A0%E8%BF%BD%E6%98%9F%E5%91%A8%E6%9D%B0%E4%BC%A6%E6%88%90%E5%8A%9F&Refer=index",
                "createtime": "2025-02-27 18:38:18",
                "datetime": "2025-02-28 00:44:38"
            },
            {
                "index": 34,
                "title": "柳智敏好美",
                "category": "作品衍生,时尚",
                "hot": 95838,
                "url": "https://s.weibo.com/weibo?q=%E6%9F%B3%E6%99%BA%E6%95%8F%E5%A5%BD%E7%BE%8E&Refer=index",
                "createtime": "2025-02-27 21:54:21",
                "datetime": "2025-02-28 00:44:38"
            },
            {
                "index": 35,
                "title": "厂家回应零食主配料为福寿螺肉",
                "category": "民生新闻",
                "hot": 95330,
                "url": "https://s.weibo.com/weibo?q=%E5%8E%82%E5%AE%B6%E5%9B%9E%E5%BA%94%E9%9B%B6%E9%A3%9F%E4%B8%BB%E9%85%8D%E6%96%99%E4%B8%BA%E7%A6%8F%E5%AF%BF%E8%9E%BA%E8%82%89&Refer=index",
                "createtime": "2025-02-27 23:07:20",
                "datetime": "2025-02-28 00:44:38"
            },
            {
                "index": 36,
                "title": "爱你",
                "category": "剧集",
                "hot": 90919,
                "url": "https://s.weibo.com/weibo?q=%E7%88%B1%E4%BD%A0&Refer=index",
                "createtime": "2025-02-27 19:38:19",
                "datetime": "2025-02-28 00:44:38"
            },
            {
                "index": 37,
                "title": "哪吒炸出了多少民间高手",
                "category": "电影",
                "hot": 58946,
                "url": "https://s.weibo.com/weibo?q=%E5%93%AA%E5%90%92%E7%82%B8%E5%87%BA%E4%BA%86%E5%A4%9A%E5%B0%91%E6%B0%91%E9%97%B4%E9%AB%98%E6%89%8B&Refer=index",
                "createtime": "2025-02-27 21:29:20",
                "datetime": "2025-02-28 00:44:38"
            },
            {
                "index": 38,
                "title": "婚房7年没住被小区保洁换锁养鸡",
                "category": "民生新闻",
                "hot": 89942,
                "url": "https://s.weibo.com/weibo?q=%E5%A9%9A%E6%88%BF7%E5%B9%B4%E6%B2%A1%E4%BD%8F%E8%A2%AB%E5%B0%8F%E5%8C%BA%E4%BF%9D%E6%B4%81%E6%8D%A2%E9%94%81%E5%85%BB%E9%B8%A1&Refer=index",
                "createtime": "2025-02-27 18:50:18",
                "datetime": "2025-02-28 00:44:38"
            },
            {
                "index": 39,
                "title": "卡卡我尽了一切努力挽救婚姻",
                "category": "体育",
                "hot": 89699,
                "url": "https://s.weibo.com/weibo?q=%E5%8D%A1%E5%8D%A1%E6%88%91%E5%B0%BD%E4%BA%86%E4%B8%80%E5%88%87%E5%8A%AA%E5%8A%9B%E6%8C%BD%E6%95%91%E5%A9%9A%E5%A7%BB&Refer=index",
                "createtime": "2025-02-27 21:56:21",
                "datetime": "2025-02-28 00:44:38"
            },
            {
                "index": 40,
                "title": "韩佳人自曝曾一年内流产三次",
                "category": "艺人",
                "hot": 87953,
                "url": "https://s.weibo.com/weibo?q=%E9%9F%A9%E4%BD%B3%E4%BA%BA%E8%87%AA%E6%9B%9D%E6%9B%BE%E4%B8%80%E5%B9%B4%E5%86%85%E6%B5%81%E4%BA%A7%E4%B8%89%E6%AC%A1&Refer=index",
                "createtime": "2025-02-27 16:56:20",
                "datetime": "2025-02-28 00:44:38"
            },
            {
                "index": 41,
                "title": "300元一张的始祖鸟吊牌到底谁在买",
                "category": "民生新闻",
                "hot": 82458,
                "url": "https://s.weibo.com/weibo?q=300%E5%85%83%E4%B8%80%E5%BC%A0%E7%9A%84%E5%A7%8B%E7%A5%96%E9%B8%9F%E5%90%8A%E7%89%8C%E5%88%B0%E5%BA%95%E8%B0%81%E5%9C%A8%E4%B9%B0&Refer=index",
                "createtime": "2025-02-27 18:39:18",
                "datetime": "2025-02-28 00:44:38"
            },
            {
                "index": 42,
                "title": "研招网回应考生伪造考研成绩",
                "category": "教育",
                "hot": 80494,
                "url": "https://s.weibo.com/weibo?q=%E7%A0%94%E6%8B%9B%E7%BD%91%E5%9B%9E%E5%BA%94%E8%80%83%E7%94%9F%E4%BC%AA%E9%80%A0%E8%80%83%E7%A0%94%E6%88%90%E7%BB%A9&Refer=index",
                "createtime": "2025-02-27 23:14:20",
                "datetime": "2025-02-28 00:44:38"
            },
            {
                "index": 43,
                "title": "长沙一32层居民楼承重墙被装修误拆",
                "category": "民生新闻",
                "hot": 73187,
                "url": "https://s.weibo.com/weibo?q=%E9%95%BF%E6%B2%99%E4%B8%8032%E5%B1%82%E5%B1%85%E6%B0%91%E6%A5%BC%E6%89%BF%E9%87%8D%E5%A2%99%E8%A2%AB%E8%A3%85%E4%BF%AE%E8%AF%AF%E6%8B%86&Refer=index",
                "createtime": "2025-02-27 20:06:20",
                "datetime": "2025-02-28 00:44:38"
            },
            {
                "index": 44,
                "title": "小米耳机",
                "category": "数码",
                "hot": 72893,
                "url": "https://s.weibo.com/weibo?q=%E5%B0%8F%E7%B1%B3%E8%80%B3%E6%9C%BA&Refer=index",
                "createtime": "2025-02-27 21:09:20",
                "datetime": "2025-02-28 00:44:38"
            },
            {
                "index": 45,
                "title": "我国古代已人手中国结",
                "category": "民生新闻",
                "hot": 71368,
                "url": "https://s.weibo.com/weibo?q=%E6%88%91%E5%9B%BD%E5%8F%A4%E4%BB%A3%E5%B7%B2%E4%BA%BA%E6%89%8B%E4%B8%AD%E5%9B%BD%E7%BB%93&Refer=index",
                "createtime": "2025-02-27 23:29:18",
                "datetime": "2025-02-28 00:44:38"
            },
            {
                "index": 46,
                "title": "专家科普中国结来源",
                "category": "民生新闻",
                "hot": 64133,
                "url": "https://s.weibo.com/weibo?q=%E4%B8%93%E5%AE%B6%E7%A7%91%E6%99%AE%E4%B8%AD%E5%9B%BD%E7%BB%93%E6%9D%A5%E6%BA%90&Refer=index",
                "createtime": "2025-02-28 00:19:18",
                "datetime": "2025-02-28 00:44:38"
            },
            {
                "index": 47,
                "title": "樊振东可直接参加全运会决赛阶段单打比赛",
                "category": "体育",
                "hot": 70408,
                "url": "https://s.weibo.com/weibo?q=%E6%A8%8A%E6%8C%AF%E4%B8%9C%E5%8F%AF%E7%9B%B4%E6%8E%A5%E5%8F%82%E5%8A%A0%E5%85%A8%E8%BF%90%E4%BC%9A%E5%86%B3%E8%B5%9B%E9%98%B6%E6%AE%B5%E5%8D%95%E6%89%93%E6%AF%94%E8%B5%9B&Refer=index",
                "createtime": "2025-02-27 23:25:19",
                "datetime": "2025-02-28 00:44:38"
            },
            {
                "index": 48,
                "title": "赵露思新头像寓意",
                "category": "艺人",
                "hot": 70188,
                "url": "https://s.weibo.com/weibo?q=%E8%B5%B5%E9%9C%B2%E6%80%9D%E6%96%B0%E5%A4%B4%E5%83%8F%E5%AF%93%E6%84%8F&Refer=index",
                "createtime": "2025-02-27 19:53:19",
                "datetime": "2025-02-28 00:44:38"
            },
            {
                "index": 49,
                "title": "雷军回应当首富",
                "category": "互联网,财经",
                "hot": 68734,
                "url": "https://s.weibo.com/weibo?q=%E9%9B%B7%E5%86%9B%E5%9B%9E%E5%BA%94%E5%BD%93%E9%A6%96%E5%AF%8C&Refer=index",
                "createtime": "2025-02-27 16:24:17",
                "datetime": "2025-02-28 00:44:38"
            },
            {
                "index": 50,
                "title": "宝可梦手游新作",
                "category": "游戏",
                "hot": 66422,
                "url": "https://s.weibo.com/weibo?q=%E5%AE%9D%E5%8F%AF%E6%A2%A6%E6%89%8B%E6%B8%B8%E6%96%B0%E4%BD%9C&Refer=index",
                "createtime": "2025-02-27 23:31:19",
                "datetime": "2025-02-28 00:44:38"
            },
            {
                "index": 51,
                "title": "行动是打消不安最好的利器",
                "category": "情感",
                "hot": 59238,
                "url": "https://s.weibo.com/weibo?q=%E8%A1%8C%E5%8A%A8%E6%98%AF%E6%89%93%E6%B6%88%E4%B8%8D%E5%AE%89%E6%9C%80%E5%A5%BD%E7%9A%84%E5%88%A9%E5%99%A8&Refer=index",
                "createtime": "2025-02-28 00:44:15",
                "datetime": "2025-02-28 00:44:38"
            }
        ]
    }
}